Workbook

Sheet Извлечение из текстов
A1: Глобально ожидаем получить на вход БЗ JSON следующего вида: { "sex": "0", "age": "35", "weight": "110", "height": "180", "BMI": "33.95", "score_scale": "9", "smoking_status": "1"}
A3: "cough":"-1" = 'отсутствует', 'жалоб на кашель не имеет', 'жалоб на кашель не предъявляет'
A4: "cough":"0" = 'кашель'
A5: "cough":"1" = 'сухой кашель', 'непродуктивный кашель', 'кашель без мокроты'
A6: "cough":"2" = 'сухой кашель', 'непродуктивный кашель', 'кашель без мокроты'
A7: "cough":"3" = 'сухой кашель', 'непродуктивный кашель', 'кашель без мокроты'
A8: "cough":"4" = 'сухой кашель', 'непродуктивный кашель', 'кашель без мокроты'
A9: "cough":"5" = 'сухой кашель', 'непродуктивный кашель', 'кашель без мокроты'
A10: "cough":"6" = 'сухой кашель', 'непродуктивный кашель', 'кашель без мокроты'
A11: "cough":"1" = 'сухой кашель', 'непродуктивный кашель', 'кашель без мокроты'
A12: "sputum":"0" = 'кашель'
A13: "sputum":"1" = 'сухой кашель', 'непродуктивный кашель', 'кашель без мокроты'
... A18: "sputum":"6" = 'сухой кашель', 'непродуктивный кашель', 'кашель без мокроты'

Sheet Скрипт activation_condition old
B1: INSERT INTO public.activation_conditions(
D2: id, name, label, kb_id, has_numeric_type, possible_numeric_range_start_point, include_start_point, possible_numeric_range_end_point, include_end_point, possible_string_values, possible_string_values_encoding, is_deleted, description, current_state, previous_state, init_state)
D3: VALUES
A5: ( | B5: id | C5: , ' | D5: name | E5: ', ' | F5: label | G5: ', | H5: kb_id | I5: , | J5: has_numeric_type | K5: , | L5: possible_numeric_range_start_point | M5: , | N5: include_start_point | O5: , | P5: possible_numeric_range_end_point | Q5: , | R5: include_end_point | S5: , '{ | T5: possible_string_values | U5: }', ' | V5: possible_string_values_encoding | W5: ', | X5: is_deleted | Y5: , ' | Z5: description | AA5: ', | AB5: current_state | AC5: , | AD5: previous_state | AE5: , | AF5: init_state | AG5: ),
A6: ( | B6: 1 | C6: , ' | D6: Кашель | E6: ', ' | F6: cough | G6: ', | H6: 1 | I6: , | J6: false | K6: , | L6: null | M6: , | N6: null | O6: , | P6: null | Q6: , | R6: null | S6: , '{ | T6: -1.6 | U6: }', ' | V6: [ {"value":"-1", "encoding":"отсутствует"}, {"value":"0", "encoding":"без уточнения"}, {"value":"1", "encoding":"непродуктивный"}, {"value":"2", "encoding":"малопродуктивный"}, {"value":"3", "encoding":"продуктивный"}, {"value":"4", "encoding":"надсадный"}, {"value":"5", "encoding":"изнуряющий"}, {"value":"6", "encoding":"с примесью крови"} ] | W6: ', | X6: false | Y6: , ' | Z6: Жалоба на кашель | AA6: ', | AC6: , | AE6: , | AG6: ),
A7: ( | B7: 2 | C7: , ' | D7: Температура тела | E7: ', ' | F7: temperature | G7: ', | H7: 1 | I7: , | J7: true | K7: , | L7: 27.00 | M7: , | N7: true | O7: , | P7: 46.50 | Q7: , | R7: true | S7: , | T7: null | U7: , | V7: null | W7: , | X7: false | Y7: , ' | Z7: Температура тела пациента | AA7: ', | AC7: , | AE7: , | AG7: ),
A8: ( | B8: 3 | C8: , ' | D8: Мокрота | E8: ', ' | F8: sputum | G8: ', | H8: 1 | I8: , | J8: false | K8: , | L8: null | M8: , | N8: null | O8: , | P8: null | Q8: , | R8: null | S8: , '{ | T8: 0.7 | U8: }', ' | V8: [ {"value":"0", "encoding":"без уточнения"}, {"value":"1", "encoding":"слизистая"}, {"value":"2", "encoding":"серозная"}, {"value":"3", "encoding":"слизисто-гнойная"}, {"value":"4", "encoding":"гнойная"}, {"value":"5", "encoding":""ржавая" мокрота"}, {"value":"6", "encoding":"серозно-геморрагическая мокрота"}, {"value":"7", "encoding":"кровавая мокрота"} ] | W8: ', | X8: false | Y8: , ' | Z8: Характер мокроты | AA8: ', | AC8: , | AE8: , | AG8: ),
A9: ( | B9: 4 | C9: , ' | D9: Боль в грудной клетке | E9: ', ' | F9: chest_pain | G9: ', | H9: 1 | I9: , | J9: false | K9: , | L9: null | M9: , | N9: null | O9: , | P9: null | Q9: , | R9: null | S9: , '{ | T9: 0.1 | U9: }', ' | V9: [ {"value":"0", "encoding":"нет"}, {"value":"1", "encoding":"есть"} ] | W9: ', | X9: false | Y9: , ' | Z9: Боль в грудной клетке | AA9: ', | AC9: , | AE9: , | AG9: ),
A10: ( | B10: 5 | C10: , ' | D10: Артралгия | E10: ', ' | F10: arthralgia | G10: ', | H10: 1 | I10: , | J10: false | K10: , | L10: null | M10: , | N10: null | O10: , | P10: null | Q10: , | R10: null | S10: , '{ | T10: 0.1 | U10: }', ' | V10: [ {"value":"0", "encoding":"нет"}, {"value":"1", "encoding":"есть"} ] | W10: ', | X10: false | Y10: , ' | Z10: Боль в суставах | AA10: ', | AC10: , | AE10: , | AG10: ),
A11: ( | B11: 6 | C11: , ' | D11: Миалгия | E11: ', ' | F11: myalgia | G11: ', | H11: 1 | I11: , | J11: false | K11: , | L11: null | M11: , | N11: null | O11: , | P11: null | Q11: , | R11: null | S11: , '{ | T11: 0.1 | U11: }', ' | V11: [ {"value":"0", "encoding":"нет"}, {"value":"1", "encoding":"есть"} ] | W11: ', | X11: false | Y11: , ' | Z11: Боль в мышцах | AA11: ', | AC11: , | AE11: , | AG11: ),
A12: ( | B12: 7 | C12: , ' | D12: Оссалгия | E12: ', ' | F12: ossalgia | G12: ', | H12: 1 | I12: , | J12: false | K12: , | L12: null | M12: , | N12: null | O12: , | P12: null | Q12: , | R12: null | S12: , '{ | T12: 0.1 | U12: }', ' | V12: [ {"value":"0", "encoding":"нет"}, {"value":"1", "encoding":"есть"} ] | W12: ', | X12: false | Y12: , ' | Z12: Боль в костях | AA12: ', | AC12: , | AE12: , | AG12: ),
A13: ( | B13: 8 | C13: , ' | D13: Боль в глазных яблоках | E13: ', ' | F13: eyeballs_pain | G13: ', | H13: 1 | I13: , | J13: false | K13: , | L13: null | M13: , | N13: null | O13: , | P13: null | Q13: , | R13: null | S13: , '{ | T13: 0.1 | U13: }', ' | V13: [ {"value":"0", "encoding":"нет"}, {"value":"1", "encoding":"есть"} ] | W13: ', | X13: false | Y13: , ' | Z13: Боль в глазных яблоках | AA13: ', | AC13: , | AE13: , | AG13: ),
A14: ( | B14: 9 | C14: , ' | D14: Конъюнктивит | E14: ', ' | F14: conjunctivitis | G14: ', | H14: 1 | I14: , | J14: false | K14: , | L14: null | M14: , | N14: null | O14: , | P14: null | Q14: , | R14: null | S14: , '{ | T14: 0.1 | U14: }', ' | V14: [ {"value":"0", "encoding":"нет"}, {"value":"1", "encoding":"есть"} ] | W14: ', | X14: false | Y14: , ' | Z14: Конъюнктивит | AA14: ', | AC14: , | AE14: , | AG14: ),
A15: ( | B15: 10 | C15: , ' | D15: Головная боль | E15: ', ' | F15: headache | G15: ', | H15: 1 | I15: , | J15: false | K15: , | L15: null | M15: , | N15: null | O15: , | P15: null | Q15: , | R15: null | S15: , '{ | T15: 0.1 | U15: }', ' | V15: [ {"value":"0", "encoding":"нет"}, {"value":"1", "encoding":"есть"} ] | W15: ', | X15: false | Y15: , ' | Z15: Головная боль | AA15: ', | AC15: , | AE15: , | AG15: ),
A16: ( | B16: 11 | C16: , ' | D16: Боль в плечевом суставе | E16: ', ' | F16: shoulder_joint_pain | G16: ', | H16: 1 | I16: , | J16: false | K16: , | L16: null | M16: , | N16: null | O16: , | P16: null | Q16: , | R16: null | S16: , '{ | T16: 0.1 | U16: }', ' | V16: [ {"value":"0", "encoding":"нет"}, {"value":"1", "encoding":"есть"} ] | W16: ', | X16: false | Y16: , | Z16: Боль в плечевом суставе | AA16: ', | AC16: , | AE16: , | AG16: ),
A17: ( | B17: 12 | C17: , ' | D17: Боль в плече | E17: ', ' | F17: shoulder_joint_pain | G17: ', | H17: 1 | I17: , | J17: false | K17: , | L17: null | M17: , | N17: null | O17: , | P17: null | Q17: , | R17: null | S17: , '{ | T17: 0.1 | U17: }', ' | V17: [ {"value":"0", "encoding":"нет"}, {"value":"1", "encoding":"есть"} ] | W17: ', | X17: false | Y17: , | Z17: Боль в плече | AA17: ', | AC17: , | AE17: , | AG17: ),
A18: ( | B18: 13 | C18: , ' | D18: Атрофия мышц предплечья | E18: ', ' | F18: muscles_forearm_atrophy | G18: ', | H18: 1 | I18: , | J18: false | K18: , | L18: null | M18: , | N18: null | O18: , | P18: null | Q18: , | R18: null | S18: , '{ | T18: 0.1 | U18: }', ' | V18: [ {"value":"0", "encoding":"нет"}, {"value":"1", "encoding":"есть"} ] | W18: ', | X18: false | Y18: , | Z18: Атрофия мышц предплечья | AA18: ', | AC18: , | AE18: , | AG18: ),
A19: ( | B19: 14 | C19: , ' | D19: Голос | E19: ', ' | F19: voice | G19: ', | H19: 1 | I19: , | J19: false | K19: , | L19: null | M19: , | N19: null | O19: , | P19: null | Q19: , | R19: null | S19: , '{ | T19: 0.4 | U19: }', ' | V19: [ {"value":"0", "encoding":"нормальный"}, {"value":"1", "encoding":"осиплый"}, {"value":"2", "encoding":"охриплый"}, {"value":"3", "encoding":"тихий"}, {"value":"4", "encoding":"потерян"} ] | W19: ', | X19: false | Y19: , | Z19: Голос | AA19: ', | AC19: , | AE19: , | AG19: ),
A20: ( | B20: 15 | C20: , ' | D20: Насморк | E20: ', ' | F20: runny_nose | G20: ', | H20: 1 | I20: , | J20: false | K20: , | L20: null | M20: , | N20: null | O20: , | P20: null | Q20: , | R20: null | S20: , '{ | T20: 0.2 | U20: }', ' | V20: [ {"value":"0", "encoding":"отсутствует"}, {"value":"1", "encoding":"заложенность носа"}, {"value":"2", "encoding":"острый ринит"} ] | W20: ', | X20: false | Y20: , | Z20: Заложенность носа | AA20: ', | AC20: , | AE20: , | AG20: ),
A21: ( | B21: 16 | C21: , ' | D21: Чихание | E21: ', ' | F21: sneezing | G21: ', | H21: 1 | I21: , | J21: false | K21: , | L21: null | M21: , | N21: null | O21: , | P21: null | Q21: , | R21: null | S21: , '{ | T21: 0.1 | U21: }', ' | V21: [ {"value":"0", "encoding":"нет"}, {"value":"1", "encoding":"есть"} ] | W21: ', | X21: false | Y21: , | AA21: ', | AC21: , | AE21: , | AG21: ),
A22: ( | B22: 17 | C22: , ' | D22: Одышка | E22: ', ' | F22: dyspnea | G22: ', | H22: 1 | I22: , | J22: false | K22: , | L22: null | M22: , | N22: null | O22: , | P22: null | Q22: , | R22: null | S22: , '{ | T22: 0.2 | U22: }', ' | V22: [ {"value":"0", "encoding:"отсутствует"}, {"value":"1", "ecoding":"при физической активности"}, {"value":"2", "encoding":"в покое"} ] | W22: ', | X22: false | Y22: , | AA22: ', | AC22: , | AE22: , | AG22: ),
A23: ( | B23: 18 | C23: , ' | D23: Пол | E23: ', ' | F23: sex | G23: ', | H23: 1 | I23: , | J23: false | K23: , | L23: null | M23: , | N23: null | O23: , | P23: null | Q23: , | R23: null | S23: , '{ | T23: -1.1 | U23: }', ' | V23: [ {"value":"-1", "encoding:"Не определён"}, {"value":"0", "ecoding":"Мужской"}, {"value":"1", "encoding":"Женский"} ] | W23: ', | X23: false | Y23: , ' | AA23: ', | AC23: , | AE23: , | AG23: ),
A24: ( | B24: 19 | C24: , ' | D24: Наличие работы | E24: ', ' | F24: employment | G24: ', | H24: 1 | I24: , | J24: false | K24: , | L24: null | M24: , | N24: null | O24: , | P24: null | Q24: , | R24: null | S24: , '{ | T24: 0.2 | U24: }', ' | V24: [ {"value":"0", "encoding:"Безработный"}, {"value":"1", "ecoding":"Работает"}, {"value":"2", "encoding":"Учащийся"} ] | W24: ', | X24: false | Y24: , ' | AA24: ', | AC24: , | AE24: , | AG24: ),
A25: ( | B25: 20 | C25: , ' | D25: Наличие МБТ в мокроте | E25: ', ' | F25: MBT_sputum | G25: ', | H25: 1 | I25: , | J25: false | K25: , | L25: null | M25: , | N25: null | O25: , | P25: null | Q25: , | R25: null | S25: , '{ | T25: 0.1 | U25: }', ' | V25: [ {"value":"0", "encoding":"нет"}, {"value":"1", "encoding":"есть"} ] | W25: ', | X25: false | Y25: , ' | AA25: ', | AC25: , | AE25: , | AG25: ),
A26: ( | B26: 21 | C26: , ' | D26: Наличие МБТ в бронхоальвеолярном лаваже | E26: ', ' | F26: MBT_lavage | G26: ', | H26: 1 | I26: , | J26: false | K26: , | L26: null | M26: , | N26: null | O26: , | P26: null | Q26: , | R26: null | S26: , '{ | T26: 0.1 | U26: }', ' | V26: [ {"value":"0", "encoding":"нет"}, {"value":"1", "encoding":"есть"} ] | W26: ', | X26: false | Y26: , | AA26: ', | AC26: , | AE26: , | AG26: ),
A27: ( | B27: 22 | C27: , ' | E27: ', ' | G27: ', | H27: 1 | I27: , | K27: , | M27: , | O27: , | Q27: , | S27: , '{ | U27: , ' | W27: ', | X27: false | Y27: , | AA27: ', | AC27: , | AE27: , | AG27: ),
A28: ( | B28: 23 | C28: , ' | E28: ', ' | G28: ', | H28: 1 | I28: , | K28: , | M28: , | O28: , | Q28: , | S28: , '{ | U28: , ' | W28: ', | X28: false | Y28: , ' | AA28: ', | AC28: , | AE28: , | AG28: ),
A29: ( | B29: 24 | C29: , ' | E29: ', ' | G29: ', | H29: 1 | I29: , | K29: , | M29: , | O29: , | Q29: , | S29: , '{ | U29: , ' | W29: ', | X29: false | Y29: , | AA29: ', | AC29: , | AE29: , | AG29: ),
A30: ( | B30: 25 | C30: , ' | E30: ', ' | G30: ', | H30: 1 | I30: , | K30: , | M30: , | O30: , | Q30: , | S30: , '{ | U30: , ' | W30: ', | X30: false | Y30: , | AA30: ', | AC30: , | AE30: , | AG30: ),
A31: ( | B31: 26 | C31: , ' | E31: ', ' | G31: ', | H31: 1 | I31: , | K31: , | M31: , | O31: , | Q31: , | S31: , '{ | U31: , ' | W31: ', | X31: false | Y31: , | AA31: ', | AC31: , | AE31: , | AG31: ),
A32: ( | B32: 27 | C32: , ' | E32: ', ' | G32: ', | H32: 1 | I32: , | K32: , | M32: , | O32: , | Q32: , | S32: , '{ | U32: , ' | W32: ', | X32: false | Y32: , | AA32: ', | AC32: , | AE32: , | AG32: ),
A33: ( | B33: 28 | C33: , ' | E33: ', ' | G33: ', | H33: 1 | I33: , | K33: , | M33: , | O33: , | Q33: , | S33: , '{ | U33: , ' | W33: ', | X33: false | Y33: , | AA33: ', | AC33: , | AE33: , | AG33: ),
A34: ( | B34: 29 | C34: , ' | E34: ', ' | G34: ', | H34: 1 | I34: , | K34: , | M34: , | O34: , | Q34: , | S34: , '{ | U34: , ' | W34: ', | X34: false | Y34: , | AA34: ', | AC34: , | AE34: , | AG34: ),
A35: ( | B35: 30 | C35: , ' | E35: ', ' | G35: ', | H35: 1 | I35: , | K35: , | M35: , | O35: , | Q35: , | S35: , '{ | U35: , ' | W35: ', | X35: false | Y35: , | AA35: ', | AC35: , | AE35: , | AG35: ),
A36: ( | B36: 31 | C36: , ' | E36: ', ' | G36: ', | H36: 1 | I36: , | K36: , | M36: , | O36: , | Q36: , | S36: , '{ | U36: , ' | W36: ', | X36: false | Y36: , | AA36: ', | AC36: , | AE36: , | AG36: ),
A37: ( | B37: 32 | C37: , ' | E37: ', ' | G37: ', | H37: 1 | I37: , | K37: , | M37: , | O37: , | Q37: , | S37: , '{ | U37: , ' | W37: ', | X37: false | Y37: , | AA37: ', | AC37: , | AE37: , | AG37: ),
A38: ( | B38: 33 | C38: , ' | E38: ', ' | G38: ', | H38: 1 | I38: , | K38: , | M38: , | O38: , | Q38: , | S38: , '{ | U38: , ' | W38: ', | X38: false | Y38: , | AA38: ', | AC38: , | AE38: , | AG38: ),
... A55: ( | B55: 50 | C55: , ' | E55: ', ' | G55: ', | H55: 1 | I55: , | K55: , | M55: , | O55: , | Q55: , | S55: , '{ | U55: , ' | W55: ', | X55: false | Y55: , | AA55: ', | AC55: , | AE55: , | AG55: ),

Sheet Скрипт node_activation_cond old
B1: INSERT INTO public.node_activation_conditions(
D2: id, node_id, activation_condition_id, numeric_range_start_point, include_start_point, numeric_range_end_point, include_end_point, string_values, is_deleted, description, current_state, init_state)
B3: VALUES
A4: ( | B4: id | C4: , | D4: node_id | E4: , | F4: activation_condition_id | G4: , | H4: numeric_range_start_point | I4: , | J4: include_start_point | K4: , | L4: numeric_range_end_point | M4: , | N4: include_end_point | O4: , '{ | P4: string_values | Q4: }', | R4: is_deleted | S4: , ' | T4: description | U4: ', | V4: current_state | W4: , | X4: init_state | Y4: ),
A5: ( | B5: 1 | C5: , | D5: --- | E5: , | F5: 1 | G5: , | H5: null | I5: , | J5: null | K5: , | L5: null | M5: , | N5: null | O5: , '{ | P5: -1 | Q5: }', | R5: false | S5: , ' | T5: отсутствует | U5: ', | V5: 2090 | W5: , | X5: 2090 | Y5: ), | Z5: =VLOOKUP(F5,'Скрипт activation_condition'!$B$6:$D$53,3,0) -> Кашель отсутсвует
A6: ( | B6: 2 | C6: , | D6: --- | E6: , | F6: 1 | G6: , | H6: null | I6: , | J6: null | K6: , | L6: null | M6: , | N6: null | O6: , '{ | P6: 0 | Q6: }', | R6: false | S6: , ' | T6: без уточнения | U6: ', | W6: , | Y6: ), | Z6: =VLOOKUP(F6,'Скрипт activation_condition'!$B$6:$D$53,3,0) -> Кашель отсутсвует
A7: ( | B7: 3 | C7: , | D7: 15 | E7: , | F7: 1 | G7: , | H7: null | I7: , | J7: null | K7: , | L7: null | M7: , | N7: null | O7: , '{ | P7: 1 | Q7: }', | R7: false | S7: , ' | T7: сухой | U7: ', | W7: , | Y7: ), | Z7: =VLOOKUP(F7,'Скрипт activation_condition'!$B$6:$D$53,3,0) -> Кашель отсутсвует
A8: ( | B8: 4 | C8: , | D8: 17 | E8: , | F8: 1 | G8: , | H8: null | I8: , | J8: null | K8: , | L8: null | M8: , | N8: null | O8: , '{ | P8: 2 | Q8: }', | R8: false | S8: , ' | T8: малопродуктивный | U8: ', | W8: , | Y8: ), | Z8: =VLOOKUP(F8,'Скрипт activation_condition'!$B$6:$D$53,3,0) -> Кашель отсутсвует
A9: ( | B9: 5 | C9: , | D9: 9 | E9: , | F9: 1 | G9: , | H9: null | I9: , | J9: null | K9: , | L9: null | M9: , | N9: null | O9: , '{ | P9: 3 | Q9: }', | R9: false | S9: , ' | T9: влажный | U9: ', | W9: , | Y9: ), | Z9: =VLOOKUP(F9,'Скрипт activation_condition'!$B$6:$D$53,3,0) -> Кашель отсутсвует
A10: ( | B10: 6 | C10: , | D10: 10 | E10: , | F10: 1 | G10: , | H10: null | I10: , | J10: null | K10: , | L10: null | M10: , | N10: null | O10: , '{ | P10: 4 | Q10: }', | R10: false | S10: , ' | T10: надсадный | U10: ', | W10: , | Y10: ), | Z10: =VLOOKUP(F10,'Скрипт activation_condition'!$B$6:$D$53,3,0) -> Кашель отсутсвует
A11: ( | B11: 7 | C11: , | D11: 18 | E11: , | F11: 1 | G11: , | H11: null | I11: , | J11: null | K11: , | L11: null | M11: , | N11: null | O11: , '{ | P11: 5 | Q11: }', | R11: false | S11: , ' | T11: изнуряющий | U11: ', | W11: , | Y11: ), | Z11: =VLOOKUP(F11,'Скрипт activation_condition'!$B$6:$D$53,3,0) -> Кашель отсутсвует
A12: ( | B12: 8 | C12: , | D12: 16 | E12: , | F12: 1 | G12: , | H12: null | I12: , | J12: null | K12: , | L12: null | M12: , | N12: null | O12: , '{ | P12: 6 | Q12: }', | R12: false | S12: , ' | T12: с кровью | U12: ', | W12: , | Y12: ), | Z12: =VLOOKUP(F12,'Скрипт activation_condition'!$B$6:$D$53,3,0) -> Кашель отсутсвует
A13: ( | B13: 9 | C13: , | D13: --- | E13: , | F13: 2 | G13: , | H13: 27.00 | I13: , | J13: true | K13: , | L13: 35.40 | M13: , | N13: true | O13: , | P13: null | Q13: , | R13: false | S13: , ' | T13: Низкая температура | U13: ', | W13: , | Y13: ), | Z13: =VLOOKUP(F13,'Скрипт activation_condition'!$B$6:$D$53,3,0) -> Кашель без уточнения
A14: ( | B14: 10 | C14: , | D14: --- | E14: , | F14: 2 | G14: , | H14: 35.50 | I14: , | J14: true | K14: , | L14: 37.00 | M14: , | N14: true | O14: , | P14: null | Q14: , | R14: false | S14: , ' | T14: Нормальная температура тела | U14: ', | W14: , | Y14: ), | Z14: =VLOOKUP(F14,'Скрипт activation_condition'!$B$6:$D$53,3,0) -> Кашель без уточнения
A15: ( | B15: 11 | C15: , | D15: 172 | E15: , | F15: 2 | G15: , | H15: 37.10 | I15: , | J15: true | K15: , | L15: 38.00 | M15: , | N15: true | O15: , | P15: null | Q15: , | R15: false | S15: , ' | T15: Субфебрильная температура тела | U15: ', | W15: , | Y15: ), | Z15: =VLOOKUP(F15,'Скрипт activation_condition'!$B$6:$D$53,3,0) -> Кашель без уточнения
A16: ( | B16: 12 | C16: , | D16: 173 | E16: , | F16: 2 | G16: , | H16: 38.10 | I16: , | J16: true | K16: , | L16: 39.50 | M16: , | N16: true | O16: , | P16: null | Q16: , | R16: false | S16: , ' | T16: Фебрильная температура тела | U16: ', | W16: , | Y16: ), | Z16: =VLOOKUP(F16,'Скрипт activation_condition'!$B$6:$D$53,3,0) -> Кашель без уточнения
A17: ( | B17: 13 | C17: , | D17: 174 | E17: , | F17: 2 | G17: , | H17: 39.60 | I17: , | J17: true | K17: , | L17: 42.00 | M17: , | N17: true | O17: , | P17: null | Q17: , | R17: false | S17: , ' | T17: Пиретическая температура тела | U17: ', | W17: , | Y17: ), | Z17: =VLOOKUP(F17,'Скрипт activation_condition'!$B$6:$D$53,3,0) -> Кашель без уточнения
A18: ( | B18: 14 | C18: , | D18: --- | E18: , | F18: 2 | G18: , | H18: 42.10 | I18: , | J18: true | K18: , | L18: 46.50 | M18: , | N18: true | O18: , | P18: null | Q18: , | R18: false | S18: , ' | T18: Гиперпирексическая температура тела | U18: ', | W18: , | Y18: ), | Z18: =VLOOKUP(F18,'Скрипт activation_condition'!$B$6:$D$53,3,0) -> Кашель без уточнения
A19: ( | B19: 15 | C19: , | D19: --- | E19: , | F19: 3 | G19: , | H19: null | I19: , | J19: null | K19: , | L19: null | M19: , | N19: null | O19: , '{ | P19: 0 | Q19: }', | R19: false | S19: , ' | T19: без уточнения | U19: ', | W19: , | Y19: ), | Z19: =VLOOKUP(F19,'Скрипт activation_condition'!$B$6:$D$53,3,0) -> Кашель непродуктивный
A20: ( | B20: 16 | C20: , | D20: 14 | E20: , | F20: 3 | G20: , | H20: null | I20: , | J20: null | K20: , | L20: null | M20: , | N20: null | O20: , '{ | P20: 1 | Q20: }', | R20: false | S20: , ' | T20: слизистая | U20: ', | W20: , | Y20: ), | Z20: =VLOOKUP(F20,'Скрипт activation_condition'!$B$6:$D$53,3,0) -> Кашель непродуктивный
A21: ( | B21: 17 | C21: , | D21: --- | E21: , | F21: 3 | G21: , | H21: null | I21: , | J21: null | K21: , | L21: null | M21: , | N21: null | O21: , '{ | P21: 2 | Q21: }', | R21: false | S21: , ' | T21: серозная | U21: ', | W21: , | Y21: ), | Z21: =VLOOKUP(F21,'Скрипт activation_condition'!$B$6:$D$53,3,0) -> Кашель непродуктивный
A22: ( | B22: 18 | C22: , | D22: 12 | E22: , | F22: 3 | G22: , | H22: null | I22: , | J22: null | K22: , | L22: null | M22: , | N22: null | O22: , '{ | P22: 3 | Q22: }', | R22: false | S22: , ' | T22: слизисто-гнойная | U22: ', | W22: , | Y22: ), | Z22: =VLOOKUP(F22,'Скрипт activation_condition'!$B$6:$D$53,3,0) -> Кашель непродуктивный
A23: ( | B23: 19 | C23: , | D23: --- | E23: , | F23: 3 | G23: , | H23: null | I23: , | J23: null | K23: , | L23: null | M23: , | N23: null | O23: , '{ | P23: 4 | Q23: }', | R23: false | S23: , ' | T23: гнойная | U23: ', | W23: , | Y23: ), | Z23: =VLOOKUP(F23,'Скрипт activation_condition'!$B$6:$D$53,3,0) -> Кашель непродуктивный
A24: ( | B24: 20 | C24: , | D24: 13 | E24: , | F24: 3 | G24: , | H24: null | I24: , | J24: null | K24: , | L24: null | M24: , | N24: null | O24: , '{ | P24: 5 | Q24: }', | R24: false | S24: , ' | T24: "ржавая" мокрота | U24: ', | W24: , | Y24: ), | Z24: =VLOOKUP(F24,'Скрипт activation_condition'!$B$6:$D$53,3,0) -> Кашель непродуктивный
A25: ( | B25: 21 | C25: , | D25: 11 | E25: , | F25: 3 | G25: , | H25: null | I25: , | J25: null | K25: , | L25: null | M25: , | N25: null | O25: , '{ | P25: 6 | Q25: }', | R25: false | S25: , ' | T25: серозно-геморрагическая | U25: ', | W25: , | Y25: ), | Z25: =VLOOKUP(F25,'Скрипт activation_condition'!$B$6:$D$53,3,0) -> Кашель непродуктивный
A26: ( | B26: 22 | C26: , | D26: --- | E26: , | F26: 3 | G26: , | H26: null | I26: , | J26: null | K26: , | L26: null | M26: , | N26: null | O26: , '{ | P26: 7 | Q26: }', | R26: false | S26: , ' | T26: кровавая мокрота | U26: ', | W26: , | Y26: ), | Z26: =VLOOKUP(F26,'Скрипт activation_condition'!$B$6:$D$53,3,0) -> Кашель непродуктивный
A27: ( | B27: 23 | C27: , | D27: 19 | E27: , | F27: 4 | G27: , | H27: null | I27: , | J27: null | K27: , | L27: null | M27: , | N27: null | O27: , '{ | P27: 1 | Q27: }', | R27: false | S27: , ' | T27: боль в грудной клетке имеется | U27: ', | W27: , | Y27: ), | Z27: =VLOOKUP(F27,'Скрипт activation_condition'!$B$6:$D$53,3,0) -> Кашель малопродуктивный
A28: ( | B28: 24 | C28: , | D28: 20 | E28: , | F28: 5 | G28: , | H28: null | I28: , | J28: null | K28: , | L28: null | M28: , | N28: null | O28: , '{ | P28: 1 | Q28: }', | R28: false | S28: , ' | T28: боль в суставах имеется | U28: ', | W28: , | Y28: ), | Z28: =VLOOKUP(F28,'Скрипт activation_condition'!$B$6:$D$53,3,0) -> Кашель продуктивный
A29: ( | B29: 25 | C29: , | D29: 21 | E29: , | F29: 6 | G29: , | H29: null | I29: , | J29: null | K29: , | L29: null | M29: , | N29: null | O29: , '{ | P29: 1 | Q29: }', | R29: false | S29: , ' | T29: боль в мышцах имеется | U29: ', | W29: , | Y29: ), | Z29: =VLOOKUP(F29,'Скрипт activation_condition'!$B$6:$D$53,3,0) -> Кашель надсадный
A30: ( | B30: 26 | C30: , | D30: 22 | E30: , | F30: 7 | G30: , | H30: null | I30: , | J30: null | K30: , | L30: null | M30: , | N30: null | O30: , '{ | P30: 1 | Q30: }', | R30: false | S30: , ' | T30: боль в костях имеется | U30: ', | W30: , | Y30: ), | Z30: =VLOOKUP(F30,'Скрипт activation_condition'!$B$6:$D$53,3,0) -> Кашель изнуряющий
A31: ( | B31: 27 | C31: , | D31: 23 | E31: , | F31: 8 | G31: , | H31: null | I31: , | J31: null | K31: , | L31: null | M31: , | N31: null | O31: , '{ | P31: 1 | Q31: }', | R31: false | S31: , ' | T31: Боль в глазных яблоках | U31: ', | W31: , | Y31: ), | Z31: =VLOOKUP(F31,'Скрипт activation_condition'!$B$6:$D$53,3,0) -> Кашель с примесью крови
A32: ( | B32: 28 | C32: , | D32: 24 | E32: , | F32: 9 | G32: , | H32: null | I32: , | J32: null | K32: , | L32: null | M32: , | N32: null | O32: , '{ | P32: 1 | Q32: }', | R32: false | S32: , ' | T32: Конъюнктивит | U32: ', | W32: , | Y32: ), | Z32: =VLOOKUP(F32,'Скрипт activation_condition'!$B$6:$D$53,3,0) -> Температура тела
A33: ( | B33: 29 | C33: , | D33: 25 | E33: , | F33: 10 | G33: , | H33: null | I33: , | J33: null | K33: , | L33: null | M33: , | N33: null | O33: , '{ | P33: 1 | Q33: }', | R33: false | S33: , ' | T33: Головная боль | U33: ', | W33: , | Y33: ), | Z33: =VLOOKUP(F33,'Скрипт activation_condition'!$B$6:$D$53,3,0) -> Мокрота
A34: ( | B34: 30 | C34: , | D34: 26 | E34: , | F34: 11 | G34: , | H34: null | I34: , | J34: null | K34: , | L34: null | M34: , | N34: null | O34: , '{ | P34: 1 | Q34: }', | R34: false | S34: , ' | T34: Боль в плечевом суставе | U34: ', | W34: , | Y34: ), | Z34: =VLOOKUP(F34,'Скрипт activation_condition'!$B$6:$D$53,3,0) -> Боль в грудной клетке
A35: ( | B35: 31 | C35: , | D35: 27 | E35: , | F35: 12 | G35: , | H35: null | I35: , | J35: null | K35: , | L35: null | M35: , | N35: null | O35: , '{ | P35: 1 | Q35: }', | R35: false | S35: , ' | T35: Боль в плече | U35: ', | W35: , | Y35: ), | Z35: =VLOOKUP(F35,'Скрипт activation_condition'!$B$6:$D$53,3,0) -> Артралгия
A36: ( | B36: 32 | C36: , | D36: 28 | E36: , | F36: 13 | G36: , | H36: null | I36: , | J36: null | K36: , | L36: null | M36: , | N36: null | O36: , '{ | P36: 1 | Q36: }', | R36: false | S36: , ' | T36: Атрофия мышц предплечья | U36: ', | W36: , | Y36: ), | Z36: =VLOOKUP(F36,'Скрипт activation_condition'!$B$6:$D$53,3,0) -> Миалгия
A37: ( | B37: 33 | C37: , | D37: --- | E37: , | F37: 14 | G37: , | H37: null | I37: , | J37: null | K37: , | L37: null | M37: , | N37: null | O37: , '{ | P37: 0 | Q37: }', | R37: false | S37: , ' | T37: Голос не изменён | U37: ', | W37: , | Y37: ), | Z37: =VLOOKUP(F37,'Скрипт activation_condition'!$B$6:$D$53,3,0) -> Оссалгия
A38: ( | B38: 34 | C38: , | D38: 30 | E38: , | F38: 14 | G38: , | H38: null | I38: , | J38: null | K38: , | L38: null | M38: , | N38: null | O38: , '{ | P38: 1 | Q38: }', | R38: false | S38: , ' | T38: Осиплый голос | U38: ', | W38: , | Y38: ), | Z38: =VLOOKUP(F38,'Скрипт activation_condition'!$B$6:$D$53,3,0) -> Оссалгия
A39: ( | B39: 35 | C39: , | D39: --- | E39: , | F39: 14 | G39: , | H39: null | I39: , | J39: null | K39: , | L39: null | M39: , | N39: null | O39: , '{ | P39: 2 | Q39: }', | R39: false | S39: , ' | T39: Охриплый голос | U39: ', | W39: , | Y39: ), | Z39: =VLOOKUP(F39,'Скрипт activation_condition'!$B$6:$D$53,3,0) -> Оссалгия
A40: ( | B40: 36 | C40: , | D40: --- | E40: , | F40: 14 | G40: , | H40: null | I40: , | J40: null | K40: , | L40: null | M40: , | N40: null | O40: , '{ | P40: 3 | Q40: }', | R40: false | S40: , ' | T40: Тихий голос | U40: ', | W40: , | Y40: ), | Z40: =VLOOKUP(F40,'Скрипт activation_condition'!$B$6:$D$53,3,0) -> Оссалгия
A41: ( | B41: 37 | C41: , | D41: --- | E41: , | F41: 14 | G41: , | H41: null | I41: , | J41: null | K41: , | L41: null | M41: , | N41: null | O41: , '{ | P41: 4 | Q41: }', | R41: false | S41: , ' | T41: Потеря голоса | U41: ', | W41: , | Y41: ), | Z41: =VLOOKUP(F41,'Скрипт activation_condition'!$B$6:$D$53,3,0) -> Оссалгия
A42: ( | B42: 38 | C42: , | D42: --- | E42: , | F42: 15 | G42: , | H42: null | I42: , | J42: null | K42: , | L42: null | M42: , | N42: null | O42: , '{ | P42: 0 | Q42: }', | R42: false | S42: , ' | T42: Насморк отсутствует | U42: ', | W42: , | Y42: ), | Z42: =VLOOKUP(F42,'Скрипт activation_condition'!$B$6:$D$53,3,0) -> Боль в глазных яблоках
A43: ( | B43: 39 | C43: , | D43: 31 | E43: , | F43: 15 | G43: , | H43: null | I43: , | J43: null | K43: , | L43: null | M43: , | N43: null | O43: , '{ | P43: 1 | Q43: }', | R43: false | S43: , ' | T43: Заложенность носа | U43: ', | W43: , | Y43: ), | Z43: =VLOOKUP(F43,'Скрипт activation_condition'!$B$6:$D$53,3,0) -> Боль в глазных яблоках
A44: ( | B44: 40 | C44: , | D44: 32 | E44: , | F44: 15 | G44: , | H44: null | I44: , | J44: null | K44: , | L44: null | M44: , | N44: null | O44: , '{ | P44: 2 | Q44: }', | R44: false | S44: , ' | T44: Острый ринит | U44: ', | W44: , | Y44: ), | Z44: =VLOOKUP(F44,'Скрипт activation_condition'!$B$6:$D$53,3,0) -> Боль в глазных яблоках
A45: ( | B45: 41 | C45: , | D45: 33 | E45: , | F45: 16 | G45: , | H45: null | I45: , | J45: null | K45: , | L45: null | M45: , | N45: null | O45: , '{ | P45: 1 | Q45: }', | R45: false | S45: , ' | T45: Чихание | U45: ', | W45: , | Y45: ), | Z45: =VLOOKUP(F45,'Скрипт activation_condition'!$B$6:$D$53,3,0) -> Конъюнктивит
A46: ( | B46: 42 | C46: , | D46: 34 | E46: , | F46: 17 | G46: , | H46: null | I46: , | J46: null | K46: , | L46: null | M46: , | N46: null | O46: , '{ | P46: 1 | Q46: }', | R46: false | S46: , ' | T46: Одышка при физической активности | U46: ', | W46: , | Y46: ), | Z46: =VLOOKUP(F46,'Скрипт activation_condition'!$B$6:$D$53,3,0) -> Головная боль
A47: ( | B47: 43 | C47: , | D47: 34 | E47: , | F47: 17 | G47: , | H47: null | I47: , | J47: null | K47: , | L47: null | M47: , | N47: null | O47: , '{ | P47: 2 | Q47: }', | R47: false | S47: , ' | T47: Одышка в покое | U47: ', | W47: , | Y47: ), | Z47: =VLOOKUP(F47,'Скрипт activation_condition'!$B$6:$D$53,3,0) -> Головная боль
A48: ( | B48: 44 | C48: , | D48: 35 | E48: , | F48: 18 | G48: , | H48: null | I48: , | J48: null | K48: , | L48: null | M48: , | N48: null | O48: , '{ | P48: 0 | Q48: }', | R48: false | S48: , ' | T48: Мужской пол | U48: ', | W48: , | Y48: ), | Z48: =VLOOKUP(F48,'Скрипт activation_condition'!$B$6:$D$53,3,0) -> Боль в плечевом суставе
A49: ( | B49: 45 | C49: , | D49: 36 | E49: , | F49: 18 | G49: , | H49: null | I49: , | J49: null | K49: , | L49: null | M49: , | N49: null | O49: , '{ | P49: 1 | Q49: }', | R49: false | S49: , ' | T49: Женский пол | U49: ', | W49: , | Y49: ), | Z49: =VLOOKUP(F49,'Скрипт activation_condition'!$B$6:$D$53,3,0) -> Боль в плечевом суставе
A50: ( | B50: 46 | C50: , | D50: 37 | E50: , | F50: 19 | G50: , | H50: null | I50: , | J50: null | K50: , | L50: null | M50: , | N50: null | O50: , '{ | P50: 0 | Q50: }', | R50: false | S50: , ' | T50: Безработный | U50: ', | W50: , | Y50: ), | Z50: =VLOOKUP(F50,'Скрипт activation_condition'!$B$6:$D$53,3,0) -> Боль в плече
A51: ( | B51: 47 | C51: , | D51: --- | E51: , | F51: 19 | G51: , | H51: null | I51: , | J51: null | K51: , | L51: null | M51: , | N51: null | O51: , '{ | P51: 1 | Q51: }', | R51: false | S51: , ' | T51: Работает | U51: ', | W51: , | Y51: ), | Z51: =VLOOKUP(F51,'Скрипт activation_condition'!$B$6:$D$53,3,0) -> Боль в плече
A52: ( | B52: 48 | C52: , | D52: --- | E52: , | F52: 19 | G52: , | H52: null | I52: , | J52: null | K52: , | L52: null | M52: , | N52: null | O52: , '{ | P52: 2 | Q52: }', | R52: false | S52: , ' | T52: Учащийся | U52: ', | W52: , | Y52: ), | Z52: =VLOOKUP(F52,'Скрипт activation_condition'!$B$6:$D$53,3,0) -> Боль в плече
A53: ( | B53: 49 | C53: , | D53: --- | E53: , | F53: 20 | G53: , | H53: null | I53: , | J53: null | K53: , | L53: null | M53: , | N53: null | O53: , '{ | P53: 0 | Q53: }', | R53: false | S53: , ' | T53: Отсутствие МБТ в мокроте | U53: ', | W53: , | Y53: ), | Z53: =VLOOKUP(F53,'Скрипт activation_condition'!$B$6:$D$53,3,0) -> Атрофия мышц предплечья
A54: ( | B54: 50 | C54: , | D54: 38 | E54: , | F54: 20 | G54: , | H54: null | I54: , | J54: null | K54: , | L54: null | M54: , | N54: null | O54: , '{ | P54: 1 | Q54: }', | R54: false | S54: , ' | T54: Наличие МБТ в мокроте | U54: ', | W54: , | Y54: ), | Z54: =VLOOKUP(F54,'Скрипт activation_condition'!$B$6:$D$53,3,0) -> Атрофия мышц предплечья
A55: ( | B55: 51 | C55: , | D55: --- | E55: , | F55: 21 | G55: , | H55: null | I55: , | J55: null | K55: , | L55: null | M55: , | N55: null | O55: , '{ | P55: 0 | Q55: }', | R55: false | S55: , ' | T55: Отсутствие МБТ в бронхоальвеолярном лаваже | U55: ', | W55: , | Y55: ), | Z55: =VLOOKUP(F55,'Скрипт activation_condition'!$B$6:$D$53,3,0) -> Голос
A56: ( | B56: 52 | C56: , | D56: 39 | E56: , | F56: 21 | G56: , | H56: null | I56: , | J56: null | K56: , | L56: null | M56: , | N56: null | O56: , '{ | P56: 1 | Q56: }', | R56: false | S56: , ' | T56: Наличие МБТ в бронхоальвеолярном лаваже | U56: ', | W56: , | Y56: ), | Z56: =VLOOKUP(F56,'Скрипт activation_condition'!$B$6:$D$53,3,0) -> Голос
A57: ( | B57: 53 | C57: , | E57: , | G57: , | I57: , | K57: , | M57: , | O57: , | Q57: , | R57: false | S57: , ' | T57: null | U57: ', | W57: , | Y57: ), | Z57: =VLOOKUP(F57,'Скрипт activation_condition'!$B$6:$D$53,3,0) -> #N/A
A58: ( | B58: 54 | C58: , | E58: , | G58: , | I58: , | K58: , | M58: , | O58: , | Q58: , | R58: false | S58: , ' | T58: null | U58: ', | W58: , | Y58: ), | Z58: =VLOOKUP(F58,'Скрипт activation_condition'!$B$6:$D$53,3,0) -> #N/A
A59: ( | B59: 55 | C59: , | E59: , | G59: , | I59: , | K59: , | M59: , | O59: , | Q59: , | R59: false | S59: , ' | T59: null | U59: ', | W59: , | Y59: ), | Z59: =VLOOKUP(F59,'Скрипт activation_condition'!$B$6:$D$53,3,0) -> #N/A
A60: ( | B60: 56 | C60: , | E60: , | G60: , | I60: , | K60: , | M60: , | O60: , | Q60: , | R60: false | S60: , ' | T60: null | U60: ', | W60: , | Y60: ), | Z60: =VLOOKUP(F60,'Скрипт activation_condition'!$B$6:$D$53,3,0) -> #N/A
A61: ( | B61: 57 | C61: , | E61: , | G61: , | I61: , | K61: , | M61: , | O61: , | Q61: , | R61: false | S61: , ' | T61: null | U61: ', | W61: , | Y61: ), | Z61: =VLOOKUP(F61,'Скрипт activation_condition'!$B$6:$D$53,3,0) -> #N/A
A62: ( | B62: 58 | C62: , | E62: , | G62: , | I62: , | K62: , | M62: , | O62: , | Q62: , | R62: false | S62: , ' | T62: null | U62: ', | W62: , | Y62: ), | Z62: =VLOOKUP(F62,'Скрипт activation_condition'!$B$6:$D$53,3,0) -> #N/A
A63: ( | B63: 59 | C63: , | E63: , | G63: , | I63: , | K63: , | M63: , | O63: , | Q63: , | R63: false | S63: , ' | T63: null | U63: ', | W63: , | Y63: ), | Z63: =VLOOKUP(F63,'Скрипт activation_condition'!$B$6:$D$53,3,0) -> #N/A
A64: ( | B64: 60 | C64: , | E64: , | G64: , | I64: , | K64: , | M64: , | O64: , | Q64: , | R64: false | S64: , ' | T64: null | U64: ', | W64: , | Y64: ), | Z64: =VLOOKUP(F64,'Скрипт activation_condition'!$B$6:$D$53,3,0) -> #N/A
A65: ( | B65: 61 | C65: , | E65: , | G65: , | I65: , | K65: , | M65: , | O65: , | Q65: , | R65: false | S65: , ' | T65: null | U65: ', | W65: , | Y65: ), | Z65: =VLOOKUP(F65,'Скрипт activation_condition'!$B$6:$D$53,3,0) -> #N/A
A66: ( | B66: 62 | C66: , | E66: , | G66: , | I66: , | K66: , | M66: , | O66: , | Q66: , | R66: false | S66: , ' | T66: null | U66: ', | W66: , | Y66: ), | Z66: =VLOOKUP(F66,'Скрипт activation_condition'!$B$6:$D$53,3,0) -> #N/A
A67: ( | B67: 63 | C67: , | E67: , | G67: , | I67: , | K67: , | M67: , | O67: , | Q67: , | R67: false | S67: , ' | T67: null | U67: ', | W67: , | Y67: ), | Z67: =VLOOKUP(F67,'Скрипт activation_condition'!$B$6:$D$53,3,0) -> #N/A
A68: ( | B68: 64 | C68: , | E68: , | G68: , | I68: , | K68: , | M68: , | O68: , | Q68: , | R68: false | S68: , ' | T68: null | U68: ', | W68: , | Y68: ), | Z68: =VLOOKUP(F68,'Скрипт activation_condition'!$B$6:$D$53,3,0) -> #N/A
... A104: ( | B104: 100 | C104: , | E104: , | G104: , | I104: , | K104: , | M104: , | O104: , | Q104: , | R104: false | S104: , ' | T104: null | U104: ', | W104: , | Y104: ), | Z104: =VLOOKUP(F104,'Скрипт activation_condition'!$B$6:$D$53,3,0) -> #N/A

Sheet Примечания
A1: Выбрать 3 болезни для диф диагноза
A2: Сказать НА какие выбрала
A4: Разделы для БЗ
A5: 1. Жалобы
A6: 2. Общий осмотр (осмотр, пальпация, перкуссия, аускультация)
A7: 3. Лабораторные методы обследования
A8: 4. Инструментальные методы обследования
A10: Опционально
A11: Факторы риска
A12: История заболевания (анамнез морби)
A13: История жизни (анамнез витэ)
A14: Наследственность
... A28: 7. Аденомы легких
A29: 8. ХОБЛ | B29: ????
A32: Два типа пневмоний или абсцесс
A35: Формы туберкулеза: очаговая, инфильтративная, диссеменированная, кавернозная, фиброзно-кавернозная, казеозная пневмония, милиарный туберкулез, туберкулема, …
A38: Писать ли норму для анализов крови, потому что она разная для м и ж

Sheet Чек-лист
A1: Заболевание | B1: elibrary | C1: Киберленинка | D1: Pubmed | E1: Запрос
A2: Туберкулез | B2: + | C2: + | E2: туберкулез легких
A3: Туберкулез | B3: + | C3: + | E3: диагностика туберкулеза легких
A4: Туберкулез | B4: + | C4: + | E4: туберкулез органов дыхания
A5: Рак легких | C5: + | E5: рак легких
A6: Рак легких | E6: диагностика рака легких
A7: Рак легких | D7: + | E7: lung cancer diagnosis
A8: Бактериальная пневмония | C8: + | E8: бактериальная пневмония
A9: Бактериальная пневмония | C9: + | E9: диагностика бактериальная пневмония !детей !дети !ВИЧ
A10: Бактериальная пневмония | C10: + | E10: бактериальные инфекции дыхательных путей
A11: Вирусная пневмония | C11: + | E11: вирусная пневмония
A12: Вирусная пневмония | D12: + | E12: viral pneumonia

Sheet Справочники
A1: Раздел | B1: Исследование | C1: Расшифровка
A2: Жалобы | B2: Опрос
A3: Общий осмотр | B3: Осмотр
A4: Лабораторные методы обследования | B4: Пальпация
A5: Инструментальные методы обследования | B5: Перкуссия
A6: Факторы риска | B6: Аускультация
B7: Общий анализ крови
B8: Биохимический анализ крови
B9: КТ ОГК | C9: КТ органов грудной клетки
B10: МРТ
B11: Рентгенография ОГК | C11: Рентгенография органов грудной клетки
B12: ПЭТ КТ
B13: ОФЭКТ | C13: Однофотонная эмиссионная КТ
B14: Сцинтиграфия
B15: Фибробронхоскопия
B16: Общий анализ мочи
B17: Коагулограмма
B18: Гистология ???
B19: ЭКГ
B20: КТ-ангиография

Sheet Пневмония бак
A1: Раздел | B1: Признак | C1: Атрибут | D1: Значение (характеристика) | E1: Исследование | F1: Комментарии | G1: Вставила | H1: Источник
A2: Жалобы | B2: боль | C2: локазлизация | D2: грудная клетка | E2: Опрос | F2: связана с дыханием | G2: 1 | H2: Клинические рекомендации
A3: Жалобы | B3: лихорадка | C3: температура тела | D3: >38 С | E3: Опрос | G3: 1 | H3: Клинические рекомендации
A4: Жалобы | B4: слабость | C4: наличие | D4: есть | E4: Опрос | G4: 1 | H4: Клинические рекомендации
A5: Жалобы | B5: утомляемость | C5: наличие | D5: есть | E5: Опрос | G5: 1 | H5: Клинические рекомендации
A6: Жалобы | B6: озноб | C6: наличие | D6: есть | E6: Опрос | G6: 1 | H6: Клинические рекомендации
A7: Жалобы | B7: потоотделение | C7: время | D7: ночь | E7: Опрос | G7: 1 | H7: Клинические рекомендации
A8: Жалобы | B8: мокрота | C8: характер | D8: слизистая | E8: Опрос
A9: Жалобы | B9: мокрота | C9: характер | D9: "ржавая" | E9: Опрос
A10: Жалобы | B10: мокрота | C10: характер | D10: слизисто-гнойная | E10: Опрос
A11: Жалобы | B11: синдром интоксикации | C11: сонливость | E11: Опрос | G11: 1 | H11: Клинические рекомендации
A12: Жалобы | B12: синдром интоксикации | C12: беспокойство | E12: Опрос | G12: 1 | H12: Клинические рекомендации
A13: Жалобы | B13: синдром интоксикации | C13: спутанность сознания | E13: Опрос | G13: 1 | H13: Клинические рекомендации
A14: Жалобы | B14: синдром интоксикации | C14: анорексия | E14: Осмотр | G14: 1 | H14: Клинические рекомендации
A15: Жалобы | B15: синдром интоксикации | C15: тошнота | E15: Опрос | G15: 1 | H15: Клинические рекомендации
A16: Жалобы | B16: синдром интоксикации | C16: рвота | E16: Опрос | G16: 1 | H16: Клинические рекомендации
A17: Жалобы | B17: диарея | C17: наличие | D17: есть | E17: Опрос | F17: х-на для легионеллезной ВП | G17: 1 | H17: Клинические рекомендации
A18: Общий осмотр | B18: дыхательная недостаточность | C18: наличие | D18: есть | E18: - | F18: при тяжелой ВП | G18: - | H18: Клинические рекомендации
A19: Общий осмотр | B19: шок | C19: тип | D19: септический | E19: - | F19: при тяжелой ВП | G19: - | H19: Клинические рекомендации
A20: Инструментальные методы обследования | B20: инфильтрация | C20: характер | D20: очаговая | E20: Рентгенография ОГК | G20: 1 | H20: Клинические рекомендации
A21: Лабораторные методы обследования | B21: ОАК | C21: лейкоциты | D21: повышены ( > 10х10 9/л) | E21: Общий анализ крови | F21: высокая вероятность бак инфекции | G21: 1 | H21: Клинические рекомендации
A22: Лабораторные методы обследования | B22: ОАК | C22: лейкоцитарная формула | D22: палочкоядерный сдвиг (> 10%) | E22: Общий анализ крови | F22: высокая вероятность бак инфекции | G22: 1 | H22: Клинические рекомендации
A23: Общий осмотр | B23: дыхание | C23: характер | D23: бронхиальное | E23: Аускультация | G23: 1 | H23: Клинические рекомендации
A24: Общий осмотр | B24: перкуссия | C24: звук | D24: укорочение (притупление) | E24: Перкуссия | G24: 1 | H24: Клинические рекомендации
A25: Общий осмотр | B25: хрипы | C25: размер | D25: мелкопузырчатые | E25: Аускультация | G25: 1 | H25: Клинические рекомендации
A26: Общий осмотр | B26: крепитация | C26: наличие | D26: есть | E26: Аускультация | G26: 1 | H26: Клинические рекомендации
A27: Общий осмотр | B27: бронхофония | C27: характер | D27: усилена | E27: Аускультация | G27: 1 | H27: Клинические рекомендации
A28: Общий осмотр | B28: голосовое дрожание | C28: характер | D28: усилено | E28: Пальпация | G28: 1 | H28: Клинические рекомендации
A29: Общий осмотр | B29: отставание грудной клетки при дыхании | C29: локализация | D29: пораженная сторона | E29: Осмотр | G29: 1 | H29: Клинические рекомендации
A30: Лабораторные методы обследования | B30: ОАК | C30: нейтрофилы | D30: повышение | E30: Общий анализ крови | F30: высокая вероятность бак инфекции | G30: 1 | H30: Клинические рекомендации
A31: Лабораторные методы обследования | B31: ОАК | C31: нейтрофильно-лейкоцитарное соотношение | D31: >20 | E31: Общий анализ крови | F31: высокая вероятность бак инфекции | G31: 1 | H31: Клинические рекомендации
A32: Лабораторные методы обследования | B32: биохимический анализ крови | C32: СРБ | D32: повышение () | E32: Биохимический анализ крови | G32: 1 | H32: Клинические рекомендации
A33: Лабораторные методы обследования | B33: биохимический анализ крови | C33: СРБ | D33: >100 мг/л | E33: Биохимический анализ крови | F33: специфичность в подтверждении диагноза пневмония 90% | G33: 1 | H33: Клинические рекомендации
A34: Лабораторные методы обследования | B34: биохимический анализ крови | C34: СРБ | D34: <20 мг/л | E34: Биохимический анализ крови | F34: пневмония маловероятна | G34: 1 | H34: Клинические рекомендации
A35: Лабораторные методы обследования | B35: биохимический анализ крови | C35: прокальцитонин | D35: 0,5 нг/мл | E35: Биохимический анализ крови | F35: отрезная точка для дифдиагностики бак и вир пневмонии | G35: 1 | H35: Клинические рекомендации
A36: Лабораторные методы обследования | B36: Бактериоскопия мокроты | C36: бактерии | D36: обнаружены | E36: микроскопия окрашенного препарата мокроты (по Граму) | F36: для госпитализарованных паципентов (для амбулаторных не актуально) | G36: 1 | H36: Клинические рекомендации
A37: Лабораторные методы обследования | B37: Культуральное исследование плевральной ж-ти на аэробные и факультативно-аэробные м/о | C37: бактерии | D37: обнаружены | E37: Культуральный метод | F37: для госпитализированных | G37: 1 | H37: Клинические рекомендации
A38: Инструментальные методы обследования | B38: инфильтрация легочной ткани | C38: тип | D38: альвеолярный | E38: Ретгенографи ОГК | F38: плевропневмония (чаще для бактерий, особенно пневмококка) | G38: 1 | H38: Клинические рекомендации
A39: Инструментальные методы обследования | B39: инфильтрация легочной ткани | C39: тип | D39: интерстициальный (матовое стекло) | E39: Ретгенографи ОГК | F39: чаще при небактериальных пневмониях | G39: 1 | H39: Клинические рекомендации
A40: Инструментальные методы обследования | B40: инфильтрация легочной ткани | C40: тип | D40: интерстициальный (матовое стекло) | E40: КТ ОГК | F40: чаще при небактериальных пневмониях | G40: 1 | H40: Клинические рекомендации
A41: Инструментальные методы обследования | B41: инфильтрация легочной ткани | C41: тип | D41: очаговый | E41: Ретгенография ОГК в двух проекциях | F41: бронхопневмония (при небактериальных инфекциях нижних дых путей) | G41: 1 | H41: Клинические рекомендации
A42: Жалобы | B42: начало | C42: характер | D42: острое | E42: Опрос | G42: 1 | H42: Диагностика и лечение внебольничной пневмоний в амбулаторных условиях
A43: Жалобы | B43: кашель | C43: характер | D43: продуктивный | E43: Опрос | G43: 1 | H43: Диагностика и лечение внебольничной пневмоний в амбулаторных условиях
A44: Жалобы | B44: одышка | C44: наличие | D44: есть | E44: Опрос | F44: в тяжелом случае | G44: 1 | H44: Диагностика и лечение внебольничной пневмоний в амбулаторных условиях
A45: Жалобы | B45: кровохарканье | C45: наличие | D45: есть | E45: Опрос | F45: в тяжелом случае | G45: 1 | H45: Диагностика и лечение внебольничной пневмоний в амбулаторных условиях
A46: Жалобы | B46: боль | C46: локализация | D46: мышцы | E46: Опрос | F46: пневмония, вызванная Микоплазма пнеумониа или Хламилия пнеумония | G46: 1 | H46: Диагностика и лечение внебольничной пневмоний в амбулаторных условиях
A47: Жалобы | B47: боль | C47: локализация | D47: голова | E47: Опрос | F47: пневмония, вызванная Микоплазма пнеумониа или Хламилия пнеумония | G47: 1 | H47: Диагностика и лечение внебольничной пневмоний в амбулаторных условиях
A48: Жалобы | B48: дисфония | C48: наличие | D48: есть | E48: Опрос | F48: пневмония, вызванная Микоплазма пнеумониа или Хламилия пнеумония | G48: 1 | H48: Диагностика и лечение внебольничной пневмоний в амбулаторных условиях
A49: Жалобы | B49: кашель | C49: характер | D49: сухой | E49: Опрос | F49: пневмония, вызванная Микоплазма пнеумониа или Хламилия пнеумония | G49: 1 | H49: Диагностика и лечение внебольничной пневмоний в амбулаторных условиях
A50: Жалобы | B50: течение болезни | C50: характер | D50: цикличное | E50: Опрос | F50: пневмония, вызванная Микоплазма пнеумониа или Хламилия пнеумония | G50: - | H50: Диагностика и лечение внебольничной пневмоний в амбулаторных условиях
A51: Жалобы | B51: лихорадка | C51: степень выраженности | D51: слабая | E51: Опрос | F51: пневмония, вызванная Микоплазма пнеумониа или Хламилия пнеумония | G51: - | H51: Диагностика и лечение внебольничной пневмоний в амбулаторных условиях
A52: Жалобы | B52: слабость | C52: наличие | D52: есть | E52: Опрос | G52: 1 | H52: Диагностика и лечение внебольничной пневмоний в амбулаторных условиях
A53: Жалобы | B53: утомляемость | C53: наличие | D53: есть | E53: Опрос | G53: 1 | H53: Внебольничная пневмония: «bene dignoscitur, bene curator»
A54: Жалобы | B54: потоотделение | C54: степень выраженности | D54: обильное | E54: Опрос | G54: 1 | H54: Диагностика и лечение внебольничной пневмоний в амбулаторных условиях
A55: Жалобы | B55: головокружение | C55: наличие | D55: есть | E55: Опрос | G55: 1 | H55: Внебольничная пневмония: «bene dignoscitur, bene curator»
A56: Жалобы | B56: потоотделение | C56: время суток | D56: ночное | E56: Опрос | G56: 1 | H56: Внебольничная пневмония: «bene dignoscitur, bene curator»
A57: Жалобы | B57: пожилой возраст/иммунно ослабленные пациенты | C57: лихорадка | D57: слабая | E57: Опрос | F57: В ряде случаев лихорадка мб невыраженной вплость до полного отсутствия | G57: - | H57: Диагностика и лечение внебольничной пневмоний в амбулаторных условиях
A58: Жалобы | B58: сознание | C58: состояние | D58: нарушено | E58: Опрос | F58: В ряде случаев лихорадка мб невыраженной вплость до полного отсутствия | G58: - | H58: Диагностика и лечение внебольничной пневмоний в амбулаторных условиях
A59: Жалобы | B59: боль | C59: локализация | D59: область живота | E59: Опрос | F59: В ряде случаев лихорадка мб невыраженной вплость до полного отсутствия | G59: - | H59: Диагностика и лечение внебольничной пневмоний в амбулаторных условиях
A60: Общий осмотр | B60: голосовое дрожание | C60: характер | D60: усилено (локально) | E60: Пальпация | F60: при большом поражении с больной стороны | G60: 1 | H60: Диагностика и лечение внебольничной пневмоний в амбулаторных условиях
A61: Общий осмотр | B61: перкуторный звук | C61: звук | D61: притупление (укорочение) | E61: Перкуссия | G61: 1 | H61: Диагностика и лечение внебольничной пневмоний в амбулаторных условиях
A62: Общий осмотр | B62: дыхание | C62: характер | D62: жесткое | E62: Аускультация | G62: 1 | H62: Диагностика и лечение внебольничной пневмоний в амбулаторных условиях
A63: Общий осмотр | B63: дыхание | C63: характер | D63: ослабленное | E63: Аускультация | F63: при осложненном течении (плевральный выпот, формирование субплеврально расположенной полости деструкции) | G63: - | H63: Диагностика и лечение внебольничной пневмоний в амбулаторных условиях
A64: Общий осмотр | B64: дыхание | C64: характер | D64: амфорическое | E64: Аускультация | F64: при осложненном течении (плевральный выпот, формирование субплеврально расположенной полости деструкции) | G64: - | H64: Диагностика и лечение внебольничной пневмоний в амбулаторных условиях
A65: Общий осмотр | B65: голосовое дрожание | C65: характер | D65: ослабленное | E65: Пальпация | F65: при осложненном течении (плевральный выпот, формирование субплеврально расположенной полости деструкции) | G65: - | H65: Диагностика и лечение внебольничной пневмоний в амбулаторных условиях
A66: Лабораторные методы обследования | B66: ОАК | C66: СОЭ | D66: ускорение | E66: Общий анализ крови | G66: 1 | H66: Диагностика и лечение внебольничной пневмоний в амбулаторных условиях
A67: Лабораторные методы обследования | B67: ОАК | C67: лейкоциты | D67: повышены - лейкоцитоз | E67: Общий анализ крови | G67: 1 | H67: Диагностика и лечение внебольничной пневмоний в амбулаторных условиях
A68: Лабораторные методы обследования | B68: ОАК | C68: лейкоцитарная формула | D68: сдвиг влево (палочкоядерный) | E68: Общий анализ крови | G68: 1 | H68: Диагностика и лечение внебольничной пневмоний в амбулаторных условиях
A69: Лабораторные методы обследования | B69: ОАК | C69: гемоглобин | D69: снижение (<90 г/л) | E69: Общий анализ крови | F69: при тяжелом состоянии | G69: 1 | H69: Диагностика и лечение внебольничной пневмоний в амбулаторных условиях
A70: Лабораторные методы обследования | B70: ОАК | C70: лейкоциты | D70: повышены (>25*10^9/л) - лейкоцитоз | E70: Общий анализ крови | F70: при тяжелом состоянии | G70: - | H70: Диагностика и лечение внебольничной пневмоний в амбулаторных условиях
A71: Лабораторные методы обследования | B71: ОАК | C71: лейкоциты | D71: понижены (<4*10^9/л) - лейкопения | E71: Общий анализ крови | F71: при тяжелом состоянии | G71: - | H71: Диагностика и лечение внебольничной пневмоний в амбулаторных условиях
A72: Лабораторные методы обследования | B72: ОАК | C72: гематокрит | D72: снижение (<30%) | E72: Общий анализ крови | F72: при тяжелом состоянии | G72: 1 | H72: Диагностика и лечение внебольничной пневмоний в амбулаторных условиях
A73: Инструментальные методы обследования | B73: Рентгенография | C73: очагово-инфильтративные изменения в легких | D73: обнаружены | E73: Рентгенография ОГК в двух проекциях | G73: 1 | H73: Диагностика и лечение внебольничной пневмоний в амбулаторных условиях
A74: Лабораторные методы обследования | B74: биохимический анализ крови | C74: С-реактивный белок | D74: повышение | E74: Биохимический анализ крови | G74: 1 | H74: С-реактивный белок - новый или старый маркер бронхолегочных инфекций?
A75: Лабораторные методы обследования | B75: биохимический анализ крови | C75: С-реактивный белок | D75: повышение (> 100 мг/л) | E75: Биохимический анализ крови | F75: наилучший маркер для дифференциайии внебольничной пневмонии от дугих заболеваний | G75: 1 | H75: С-реактивный белок - новый или старый маркер бронхолегочных инфекций?
A76: Лабораторные методы обследования | B76: биохимический анализ крови | C76: С-реактивный белок | D76: <11 мг/л | E76: Биохимический анализ крови | F76: практически исключает диагноз ВП | G76: 1 | H76: С-реактивный белок - новый или старый маркер бронхолегочных инфекций?
A77: Лабораторные методы обследования | B77: биохимический анализ крови | C77: С-реактивный белок | D77: <20 мг/л | E77: Биохимический анализ крови | F77: диагноз внебольничная пневмония маловероятен | G77: 1 | H77: Биомаркеры воспаления при заболеваниях органов дыхания: клиническая практика и перспективы
A78: Лабораторные методы обследования | B78: прокальцитонин | C78: уровень | D78: < 25 мкг/л | E78: тест B·R·A·H·M·S PCT | F78: низкая вероятность бактериальной инфекции | G78: 1 | H78: Прокальцитонин – надежный биомаркер бактериальной инфекции и оценки эффективности антибиотикотерапии
A79: Жалобы | B79: эпидемиологический анамнез | D79: осложнен | E79: Опрос | G79: 1 | H79: Клинические рекомендации
A80: Факторы риска | B80: возраст | C80: возраст | D80: взрослые () | E80: Опрос | G80: 1 | H80: Review of Non-bacterial Infections in Respiratory Medicine: Viral Pneumonia
B81: течение болезни | C81: характер | D81: острое | E81: Осмотр | G81: - | H81: Review of Non-bacterial Infections in Respiratory Medicine: Viral Pneumonia
A82: Общий осмотр | B82: частота дыхания | C82: частота | D82: повышена (>20) - тахипноэ | E82: Осмотр | G82: 1 | H82: Review of Non-bacterial Infections in Respiratory Medicine: Viral Pneumonia
A83: Лабораторная диагностика | B83: ОАК | C83: лейкоциты (при поступлении) | D83: < 4* 10^6/л | E83: Общий анализ крови | G83: 1 | H83: Review of Non-bacterial Infections in Respiratory Medicine: Viral Pneumonia
A84: Лабораторная диагностика | B84: ОАК | C84: лейкоциты (при поступлении) | D84: > 15* 10^6/л | E84: Общий анализ крови | G84: 1 | H84: Review of Non-bacterial Infections in Respiratory Medicine: Viral Pneumonia
A85: Лабораторная диагностика | B85: СРБ | C85: СРБ (при поступлении) | D85: > 60 мг/л | E85: Общий анализ крови | G85: - | H85: Review of Non-bacterial Infections in Respiratory Medicine: Viral Pneumonia
A86: Лабораторная диагностика | B86: прокальцитонин в сыворотке | C86: прокальцитонин (при поступлении) | D86: > 0,5 мкг/л (>1 мкг/л - больше специфичность) | G86: 1 | H86: Review of Non-bacterial Infections in Respiratory Medicine: Viral Pneumonia
A87: Инструментальные методы диагностики | B87: легочные инфильтраты | C87: распределение | D87: долевое | E87: КТ легких | G87: 1 | H87: Review of Non-bacterial Infections in Respiratory Medicine: Viral Pneumonia
A88: Инструментальные методы диагностики | B88: легочные инфильтраты | C88: локализация | D88: альвеолярный | E88: КТ легких | G88: 1 | H88: Review of Non-bacterial Infections in Respiratory Medicine: Viral Pneumonia

Sheet Пневмония вир
A1: Раздел | B1: Признак | C1: Атрибут | D1: Значение (характеристика) | E1: Исследование | F1: Вставила | G1: Источник | H1: Комментарии
A2: Жалобы | B2: одышка | C2: характер | D2: инспираторный | E2: Опрос | F2: 0 | G2: Небактериальные маски пневмоний в клинической практике терапевта | H2: в тяжелых случая
A3: Жалобы | B3: одышка | C3: характер | D3: смешанный | E3: Опрос | F3: 0 | G3: Небактериальные маски пневмоний в клинической практике терапевта | H3: в тяжелых случаях
A4: Жалобы | B4: боль | C4: локализация | D4: грудная клетка | E4: Опрос | F4: 1 | G4: Небактериальные маски пневмоний в клинической практике терапевта
A5: Жалобы | B5: кровохарканье | C5: наличие | D5: есть | E5: Опрос | F5: 1 | G5: Небактериальные маски пневмоний в клинической практике терапевта | H5: реже, чем при бактериальной
A6: Жалобы | B6: кашель | C6: характер | D6: сухой | E6: Опрос | F6: 1 | G6: Небактериальные маски пневмоний в клинической практике терапевта | H6: в начале заболевания
A7: Жалобы | B7: кашель | C7: характер | D7: непродуктивный | E7: Опрос | F7: 1 | G7: Вирусные пневмонии новый взгляд на старую проблему
A8: Жалобы | B8: мокрота | C8: характер | D8: слизистая | E8: Опрос | F8: 1 | G8: Небактериальные маски пневмоний в клинической практике терапевта
A9: Общий осмотр | B9: цианоз | C9: локализация | D9: губы | E9: Осмотр | F9: 1 | G9: Небактериальные маски пневмоний в клинической практике терапевта
A10: Общий осмотр | B10: цианоз | C10: локализация | D10: акроцианоз | E10: Осмотр | F10: 1 | G10: Небактериальные маски пневмоний в клинической практике терапевта
A11: Общий осмотр | B11: температура тела | C11: температура | D11: повышена (37,1 — 38 °С) - субфебрильная | E11: Осмотр | F11: 1 | G11: Небактериальные маски пневмоний в клинической практике терапевта
A12: Общий осмотр | B12: температура тела | C12: температура | D12: повышена (38-39° C) - фебрильная | E12: Осмотр | F12: 1 | G12: Небактериальные маски пневмоний в клинической практике терапевта | H12: иногда
A13: Общий осмотр | B13: перкуторный звук | C13: звук | D13: укорочение | E13: Перкуссия | F13: 1 | G13: Небактериальные маски пневмоний в клинической практике терапевта | H13: над пораженными участками
A14: Общий осмотр | B14: дыхание | C14: характер | D14: ослаблено | E14: Аускультация | F14: 1 | G14: Небактериальные маски пневмоний в клинической практике терапевта | H14: над пораженными участками
A15: Общий осмотр | B15: крепитация | C15: наличие | D15: есть | E15: Аускультация | F15: 1 | G15: Небактериальные маски пневмоний в клинической практике терапевта
A16: Общий осмотр | B16: хрипы | C16: характер | D16: влажные | E16: Аускультация | F16: 1 | G16: Небактериальные маски пневмоний в клинической практике терапевта | H16: реже
A17: Общий осмотр | B17: хрипы | C17: характер | D17: сухие | E17: Аускультация | F17: 1
A18: Общий осмотр | B18: акцент 2 тона | C18: локализация | D18: над легочной артерией | E18: Аускультация сердца | F18: 1 | G18: Небактериальные маски пневмоний в клинической практике терапевта | H18: обусловлено легочной гипертензией
A19: Общий осмотр | B19: расщепление 1 тона | C19: локализация | D19: над трикуспидальным клапаном | E19: Аускультация сердца | F19: 1 | G19: Небактериальные маски пневмоний в клинической практике терапевта | H19: обусловлено легочной гипертензией
A20: Лабораторная диагностика | B20: ОАК | C20: лейкоциты | D20: снижение () - лейкопения | E20: Общий анализ крови | F20: 1 | G20: Небактериальные маски пневмоний в клинической практике терапевта
A21: Лабораторная диагностика | B21: ОАК | C21: нейтрофилы | D21: снижение () - нейтропения | E21: Общий анализ крови | F21: 1 | G21: Небактериальные маски пневмоний в клинической практике терапевта
A22: Лабораторная диагностика | B22: ОАК | C22: лимфоциты | D22: повышение () - абсолютный лимфоцитоз | E22: Общий анализ крови | F22: 1 | G22: Небактериальные маски пневмоний в клинической практике терапевта
A23: Лабораторная диагностика | B23: ОАК | C23: моноциты | D23: повышение () - моноцитоз | E23: Общий анализ крови | F23: 1 | G23: Небактериальные маски пневмоний в клинической практике терапевта
A24: Лабораторная диагностика | B24: ОАК | C24: СОЭ | D24: нормальная | E24: Общий анализ крови | F24: 1 | G24: Небактериальные маски пневмоний в клинической практике терапевта
A25: Лабораторная диагностика | B25: ОАК | C25: СОЭ | D25: повышенная | E25: Общий анализ крови | F25: 1 | G25: Небактериальные маски пневмоний в клинической практике терапевта
A26: Инструментальные методы диагностики | B26: сатурация крови кислородом | C26: сатурация | D26: пониженная () - гипоксемия | E26: Пульсоксиметрия | F26: 1 | G26: Небактериальные маски пневмоний в клинической практике терапевта
A27: Инструментальные методы диагностики | B27: корни легких | C27: размер | D27: расширены | E27: Рентгенограмма ОГК в двух проекциях | F27: 1 | G27: Небактериальные маски пневмоний в клинической практике терапевта
A28: Инструментальные методы диагностики | B28: легочные поля | C28: характер | D28: консолидированные | E28: Рентгенограмма ОГК в двух проекциях | F28: 1 | G28: Небактериальные маски пневмоний в клинической практике терапевта
A29: Инструментальные методы диагностики | B29: легочные поля | C29: характер | D29: сетчатые | E29: Рентгенограмма ОГК в двух проекциях | F29: 1 | G29: Небактериальные маски пневмоний в клинической практике терапевта
A30: Инструментальные методы диагностики | B30: легочные поля | C30: плотность | D30: повышенная | E30: Рентгенограмма ОГК в двух проекциях | F30: 1 | G30: Небактериальные маски пневмоний в клинической практике терапевта
A31: Инструментальные методы диагностики | B31: легочный рисунок | C31: характер | D31: усилен | E31: Рентгенограмма ОГК в двух проекциях | F31: 1 | G31: Небактериальные маски пневмоний в клинической практике терапевта
A32: Инструментальные методы диагностики | B32: "матовое стекло" | C32: распространение | D32: долевое | E32: КТ легких | F32: 1 | G32: Небактериальные маски пневмоний в клинической практике терапевта
A33: Инструментальные методы диагностики | B33: симптом "воздушной бронхограммы" | C33: наличие | D33: есть | E33: Рентгенограмма ОГК в двух проекциях | F33: 1
A34: Инструментальные методы диагностики | B34: "матовое стекло" | C34: распространение | D34: диффузное | E34: КТ легких | F34: 1 | G34: Небактериальные маски пневмоний в клинической практике терапевта
A35: Инструментальные методы диагностики | B35: междольковые септы | C35: размер | D35: утолщены | E35: КТ легких | F35: 1 | G35: Небактериальные маски пневмоний в клинической практике терапевта
A36: Инструментальные методы диагностики | B36: очаги | C36: размер | D36: маленький | E36: КТ легких | F36: 1 | G36: Вирусные пневмонии. Радиологические признаки сложности диагностики | H36: чем меньше очаг, тем больше вероятность вирусного происхождения
A37: Инструментальные методы диагностики | B37: легочная ткань | C37: пневмотизация | D37: снижена диффузно в виде "матового стекла" | E37: КТ легких | F37: 1 | G37: Вирусные пневмонии. Радиологические признаки сложности диагностики | H37: двустороннее снижение - признак гриппозной пневмонии
A38: Инструментальные методы диагностики | B38: легочная ткань | C38: пневмотизация | D38: уплотнена неравномерно по типу "мозаичной перфузии" | E38: КТ легких | F38: 1 | G38: Вирусные пневмонии. Радиологические признаки сложности диагностики
A39: Инструментальные методы диагностики | B39: симптом патологической исчерченности | C39: наличие | D39: есть | E39: КТ легких | F39: 1 | G39: Вирусные пневмонии. Радиологические признаки сложности диагностики | H39: синоним: симптом "булыжной мостовой"
A40: Факторы риска | B40: возраст | C40: возраст | D40: старше 65 лет | E40: Опрос | F40: 1 | G40: Вирусные пневмонии. Радиологические признаки сложности диагностики
A41: Факторы риска | B41: сезон | C41: сезон | D41: осень | E41: Опрос | F41: 1 | G41: Вирусные пневмонии. Радиологические признаки сложности диагностики
A42: Факторы риска | B42: сезон | C42: сезон | D42: зима | E42: Опрос | F42: 1 | G42: Вирусные пневмонии. Радиологические признаки сложности диагностики
A43: Жалобы | B43: начало | C43: характер | D43: острое | E43: Опрос | F43: 1 | G43: Вирусные пневмонии. Радиологические признаки сложности диагностики
A44: Жалобы | B44: интоксикационный синдром | C44: боль | D44: в мышцах (миалгия) | E44: Опрос | F44: 1 | G44: Вирусные пневмонии. Радиологические признаки сложности диагностики
A45: Жалобы | B45: интоксикационный синдром | C45: боль | D45: в глазных яблоках | E45: Опрос | F45: 1 | G45: Вирусные пневмонии. Радиологические признаки сложности диагностики
A46: Жалобы | B46: интоксикационный синдром | C46: боль | D46: в костях (оссалгия) | E46: Опрос | F46: 1 | G46: Вирусные пневмонии. Радиологические признаки сложности диагностики
A47: Жалобы | B47: интоксикационный синдром | C47: боль | D47: головная | E47: Опрос | F47: 1 | G47: Вирусные пневмонии. Радиологические признаки сложности диагностики
A48: Жалобы | B48: интоксикационный синдром | C48: лихорадка | E48: Опрос | F48: 1 | G48: Вирусные пневмонии. Радиологические признаки сложности диагностики
A49: Жалобы | B49: интоксикационный синдром | C49: озноб | E49: Опрос | F49: 1 | G49: Вирусные пневмонии. Радиологические признаки сложности диагностики
A50: Лабораторная диагностика | B50: вирусы в слизи носа и носоглотки | C50: наличие | D50: обнаружены | E50: ИФА с МАТ | F50: 1 | G50: Вирусные пневмонии. Радиологические признаки сложности диагностики
A51: Лабораторная диагностика | B51: титр противовирусных АТ | C51: титр | D51: увеличение в ≥4 раза | E51: ИФА | F51: 1 | G51: Вирусные пневмонии. Радиологические признаки сложности диагностики | H51: через 10–14 дней с начала заболевания
A52: Общий осмотр | B52: дыхание | C52: характер | D52: жесткое | E52: Аускультация | F52: 1 | G52: Вирусные пневмонии. Радиологические признаки сложности диагностики
A53: Инструментальные методы диагностики | B53: перибронховаскулярный интерстиций | C53: плотность | D53: уплотнение | E53: КТ легких | F53: 1 | G53: Вирусные пневмонии. Радиологические признаки сложности диагностики
A54: Инструментальные методы диагностики | B54: пневматизация | C54: характер | D54: неравномерная | E54: КТ легких | F54: 1 | G54: Вирусные пневмонии. Радиологические признаки сложности диагностики | H54: с формированием "воздушых ловуше" - гриппозная пневмония
A55: Жалобы | B55: кашель | C55: характер | D55: сухой | E55: Опрос | F55: 1 | G55: Вирусные пневмонии. Радиологические признаки сложности диагностики
A56: Жалобы | B56: нос | C56: состояние | D56: заложенность | E56: Опрос | F56: 1 | G56: Вирусные пневмонии. Радиологические признаки сложности диагностики
A57: Общий осмотр | B57: шейные лимфоузлы | C57: размер | D57: увеличены | E57: Пальпация шейных лимфоузлов | F57: 1 | G57: Вирусные пневмонии. Радиологические признаки сложности диагностики
A58: Общий осмотр | B58: шейные лимфоузлы | C58: болезненность | D58: есть | E58: Пальпация шейных лимфоузлов | F58: 1 | G58: Вирусные пневмонии. Радиологические признаки сложности диагностики
A59: Общий осмотр | B59: конъюктивит | C59: наличие | D59: есть | E59: Осмотр | F59: 1 | G59: Вирусные пневмонии. Радиологические признаки сложности диагностики
A60: Инструментальные методы диагностики | B60: очаги затемнения | C60: размер | D60: мелкий | E60: Рентгенография ОГК | F60: 1 | G60: Вирусные пневмонии. Радиологические признаки сложности диагностики
A61: Инструментальные методы диагностики | B61: легочный рисунок | C61: характер | D61: диффузно усилен | E61: Рентгенография ОГК | F61: 1 | G61: Вирусные пневмонии. Радиологические признаки сложности диагностики
A62: Инструментальные методы диагностики | B62: интерстиций | C62: плотность | D62: уплотнен | E62: КТ легких | F62: 1 | G62: Вирусные пневмонии. Радиологические признаки сложности диагностики
A63: Инструментальные методы диагностики | B63: лимфаденопатия | C63: локализация | D63: медиастинальная | E63: КТ легких | F63: 1 | G63: Вирусные пневмонии. Радиологические признаки сложности диагностики
A64: Инструментальные методы диагностики | B64: очаги | C64: локализация | D64: перибронхиальные | E64: КТ легких | F64: 1 | G64: Вирусные пневмонии. Радиологические признаки сложности диагностики
A65: Инструментальные методы диагностики | B65: очаги | C65: размер | D65: мелкий | E65: КТ легких | F65: 1 | G65: Вирусные пневмонии. Радиологические признаки сложности диагностики
A66: Инструментальные методы диагностики | B66: очаги | C66: контур | D66: нечеткий | E66: КТ легких | F66: 1 | G66: Вирусные пневмонии. Радиологические признаки сложности диагностики
A67: Инструментальные методы диагностики | B67: признак гало | C67: наличие | D67: есть | E67: КТ легких | F67: 1 | G67: Вирусные пневмонии. Радиологические признаки сложности диагностики | H67: «halo» – ореола уплотнения вокруг очагов по типу «матового стекла», отражающее геморрагическую природу очагов
A68: Жалобы | B68: кашель | C68: характер | D68: малопродуктивный | E68: Опрос | F68: 1 | G68: Вирусные пневмонии. Радиологические признаки сложности диагностики
A69: Жалобы | B69: кашель | C69: характер | D69: изнуряющий (коклюшеподобный) | E69: Опрос | F69: 1 | G69: Вирусные пневмонии. Радиологические признаки сложности диагностики
A70: Лабораторная диагностика | B70: ПЦР мазка из носо/ротоглотки | C70: наличие РНК/ДНК вируса | D70: обнаружено | E70: ПЦР | F70: 1 | G70: Вирусные пневмонии новый взгляд на старую проблему
A71: Жалобы | B71: эпидемический анамнез | D71: осложнен | E71: Опрос | F71: 1 | G71: Вирусные пневмонии новый взгляд на старую проблему
A72: Общий осмотр | B72: дыхание | C72: характер | D72: ослаблено в нижне-базальных отделах | E72: Аускультация | F72: 1 | G72: Вирусные пневмонии новый взгляд на старую проблему
A73: Жалобы | B73: мокрота | C73: характер | D73: серозно-геморрагическая | E73: Опрос | F73: 1 | G73: Вирусные пневмонии новый взгляд на старую проблему
A74: Жалобы | B74: головокружение | C74: наличие | D74: есть | E74: Опрос | F74: 1 | G74: Вирусные пневмонии новый взгляд на старую проблему
A75: Жалобы | B75: диарея | C75: наличие | D75: есть | E75: Опрос | F75: 1 | G75: Вирусные пневмонии новый взгляд на старую проблему
A76: Жалобы | B76: рвота | C76: наличие | D76: есть | E76: Опрос | F76: 1 | G76: Вирусные пневмонии новый взгляд на старую проблему
A77: Лабораторная диагностика | B77: ОАК | C77: тромбоциты | D77: снижение () - тромбоцитопения | E77: Общий анализ крови | F77: 1 | G77: Вирусные пневмонии новый взгляд на старую проблему
A78: Лабораторная диагностика | B78: ОАК | C78: лимфоциты | D78: снижение () - лимфоцитопения | E78: Общий анализ крови | F78: 1 | G78: Вирусные пневмонии новый взгляд на старую проблему
A79: Лабораторная диагностика | B79: диурез | C79: объем | D79: снижен | E79: Анализ мочи по Зимницкому | F79: 1 | G79: Вирусные пневмонии новый взгляд на старую проблему | H79: ????
A80: Общий осмотр | B80: течение болезни | C80: характер | D80: затяжное | E80: Опрос | F80: - | G80: Вирусные пневмонии новый взгляд на старую проблему
B81: ??? | C81: цитокины | D81: повышение () - гиперцитокинемия | F81: - | G81: Вирусные пневмонии новый взгляд на старую проблему | H81: цитокиновый шторм
A82: Лабораторная диагностика | B82: биохимический анализ крови | C82: ферритин | D82: повышение () | E82: Биохимический анализ крови | F82: 1 | G82: Вирусные пневмонии новый взгляд на старую проблему
A83: Лабораторная диагностика | B83: биохимический анализ крови | C83: СРБ | D83: повышение () | E83: Биохимический анализ крови | F83: 1 | G83: Вирусные пневмонии новый взгляд на старую проблему
A84: Жалобы | B84: чувство нехватки воздуха | C84: наличие | D84: есть | E84: Опрос | F84: 1 | G84: Вирусные пневмонии новый взгляд на старую проблему
A85: Инструментальные методы диагностики | B85: симптом "дерево в почках" | C85: наличие | D85: есть | E85: КТ легких | F85: 1 | G85: Вирусные пневмонии новый взгляд на старую проблему | H85: дерево в бутоне ???
A86: Лабораторная диагностика | B86: биохимический анализ крови | C86: прокальцитонин | D86: низкие показатели (<0,5 мкг/л) | E86: Биохимический анализ крови | F86: 1 | G86: Вирусные пневмонии новый взгляд на старую проблему | H86: бактериальная инфекция маловероятна
A87: Жалобы | B87: ринит | C87: наличие | D87: есть | E87: Опрос | F87: 1 | G87: ЛАБОРАТОРНО-ИНСТРУМЕНТАЛЬНАЯ ДИАГНОСТИКА ВИРУСНЫХ ПНЕВМОНИЙ (ОБЗОР)
A88: Лабораторная диагностика | B88: ОАК | C88: лейкоциты | D88: лейкопения | E88: Общий анализ крови | F88: 1 | G88: ЛАБОРАТОРНО-ИНСТРУМЕНТАЛЬНАЯ ДИАГНОСТИКА ВИРУСНЫХ ПНЕВМОНИЙ (ОБЗОР)
A89: Лабораторная диагностика | B89: ОАК | C89: лейкоциты | D89: лимфопения | E89: Общий анализ крови | F89: 1 | G89: ЛАБОРАТОРНО-ИНСТРУМЕНТАЛЬНАЯ ДИАГНОСТИКА ВИРУСНЫХ ПНЕВМОНИЙ (ОБЗОР)
A90: Инструментальные методы диагностики | B90: знак "перевернутого ореола" | C90: наличие | D90: есть | E90: КТ легких | F90: 1 | G90: ЛАБОРАТОРНО-ИНСТРУМЕНТАЛЬНАЯ ДИАГНОСТИКА ВИРУСНЫХ ПНЕВМОНИЙ (ОБЗОР) | H90: редко
A91: Инструментальные методы диагностики | B91: легочные узелки со знаком ореола | C91: наличие | D91: есть | E91: КТ легких | F91: 1 | G91: ЛАБОРАТОРНО-ИНСТРУМЕНТАЛЬНАЯ ДИАГНОСТИКА ВИРУСНЫХ ПНЕВМОНИЙ (ОБЗОР) | H91: редко
A92: Лабораторная диагностика | B92: ИФА материала из носоглотки | C92: наличие вируса | D92: обнаружен | E92: ИФА | F92: 1 | G92: ЛАБОРАТОРНО-ИНСТРУМЕНТАЛЬНАЯ ДИАГНОСТИКА ВИРУСНЫХ ПНЕВМОНИЙ (ОБЗОР)
A93: Общий осмотр | B93: бронхообструктивный синдром | C93: дыхание | D93: жесткое | E93: Аускультация | F93: 1 | G93: Вирусные пневмонии. Радиологические признаки сложности диагностики | H93: признаки взяла из литературы учебной
A94: Общий осмотр | B94: бронхообструктивный синдром | C94: хрипы | D94: сухие свистящие | E94: Аускультация | F94: - | G94: признаки взяла из литературы учебной
A95: Общий осмотр | B95: бронхообструктивный синдром | C95: цианоз | D95: лицо | E95: Осмотр | F95: 1 | G95: признаки взяла из литературы учебной
A96: Общий осмотр | B96: бронхообструктивный синдром | C96: цианоз | D96: акроцианоз | E96: Осмотр | F96: 1 | G96: признаки взяла из литературы учебной
A97: Общий осмотр | B97: частота дыхания | C97: частота | D97: повышена (> 20) | E97: Осмотр | F97: 1 | G97: Viral pneumonia: epidemiological, clinical, pathophysiological and therapeutic aspects
A98: Лабораторная диагностика | B98: вирус-специфичные IgG АТ | C98: титр | D98: повышен (не менее, чем в 4 раза) | F98: 1 | G98: Viral pneumonia Maria Angeles | H98: ретроспективно
A99: Инструментальные методы диагностики | B99: легочные инфильтраты | C99: распределение | D99: билатеральное (двустороннее) | E99: КТ легких | F99: 1 | G99: Review of Non-bacterial Infections in Respiratory Medicine: Viral Pneumonia
A100: Инструментальные методы диагностики | B100: легочные инфильтраты | C100: локализация | D100: интерстиций | E100: КТ легких | F100: 1 | G100: Review of Non-bacterial Infections in Respiratory Medicine: Viral Pneumonia
...

Sheet Рак легких
A1: Раздел | B1: Признак | C1: Атрибут | D1: Значение (характеристика) | E1: Исследование | F1: Источник | G1: Вставила | H1: Комментарии
A2: Факторы риска | B2: пол | C2: пол | D2: мужской | E2: Опрос | F2: Рекомендации по ранней диагностике рака лёгкого для врачей первичного звена | G2: 1
A3: Факторы риска | B3: курение | C3: характеристика | D3: активное | E3: Опрос | F3: Рекомендации по ранней диагностике рака лёгкого для врачей первичного звена | G3: -
A4: Факторы риска | B4: курение | C4: характеристика | D4: пассивное | E4: Опрос | F4: Рекомендации по ранней диагностике рака лёгкого для врачей первичного звена | G4: -
A5: Факторы риска | B5: курение | C5: продолжительность | D5: более 30 лет | E5: Опрос | F5: Рекомендации по ранней диагностике рака лёгкого для врачей первичного звена | G5: -
A6: Факторы риска | B6: курение | C6: в настоящее время | D6: да | E6: Опрос | F6: Current and Future Development in Lung Cancer Diagnosis | G6: -
A7: Факторы риска | B7: курение | C7: в настоящее время | D7: нет (бросил <15 лет назад) | E7: Опрос | F7: Current and Future Development in Lung Cancer Diagnosis | G7: -
A8: Факторы риска | B8: вдыхание радона | C8: концентрация | D8: более 4 пкюри/л | E8: Опрос | F8: Рекомендации по ранней диагностике рака лёгкого для врачей первичного звена | G8: 1
A9: Факторы риска | B9: ХОБЛ | C9: стадия | D9: III-IV ст. | E9: Опрос | F9: Рекомендации по ранней диагностике рака лёгкого для врачей первичного звена | G9: 1
A10: Факторы риска | B10: работа | C10: отрасль | D10: газификация и коксование | E10: Опрос | F10: Рекомендации по ранней диагностике рака лёгкого для врачей первичного звена | G10: 1
A11: Факторы риска | B11: работа | C11: отрасль | D11: алюминиевая промышленность | E11: Опрос | F11: Рекомендации по ранней диагностике рака лёгкого для врачей первичного звена | G11: 1
A12: Факторы риска | B12: работа | C12: отрасль | D12: добыча гематита | E12: Опрос | F12: Рекомендации по ранней диагностике рака лёгкого для врачей первичного звена | G12: 1
A13: Факторы риска | B13: работа | C13: отрасль | D13: литейная промышленность | E13: Опрос | F13: Рекомендации по ранней диагностике рака лёгкого для врачей первичного звена | G13: 1
A14: Факторы риска | B14: работа | C14: отрасль | D14: производство изопропилового спирта | E14: Опрос | F14: Рекомендации по ранней диагностике рака лёгкого для врачей первичного звена | G14: 1
A15: Факторы риска | B15: работа | C15: отрасль | D15: производство фуксина | E15: Опрос | F15: Рекомендации по ранней диагностике рака лёгкого для врачей первичного звена | G15: 1
A16: Факторы риска | B16: работа | C16: отрасль | D16: резиновая промышленность | E16: Опрос | F16: Рекомендации по ранней диагностике рака лёгкого для врачей первичного звена | G16: 1
A17: Факторы риска | B17: постоянный контакт | C17: вещество | D17: асбест | E17: Опрос | F17: Рекомендации по ранней диагностике рака лёгкого для врачей первичного звена | G17: 1
A18: Факторы риска | B18: постоянный контакт | C18: вещество | D18: бериллий | E18: Опрос | F18: Рекомендации по ранней диагностике рака лёгкого для врачей первичного звена | G18: 1
A19: Факторы риска | B19: постоянный контакт | C19: вещество | D19: винилхлорид | E19: Опрос | F19: Рекомендации по ранней диагностике рака лёгкого для врачей первичного звена | G19: 1
... A33: Жалобы | B33: состояние | C33: аппетит | D33: снижение | E33: Опрос | F33: Рекомендации по ранней диагностике рака лёгкого для врачей первичного звена | G33: 1
A34: Жалобы | B34: вес | C34: изменение | D34: похудание | E34: Опрос | F34: Рекомендации по ранней диагностике рака лёгкого для врачей первичного звена | G34: 1 | H34: степень???
A35: Жалобы | B35: повышение температуры тела | C35: продолжительность | D35: не менее месяца | E35: Опрос | F35: Рекомендации по ранней диагностике рака лёгкого для врачей первичного звена | G35: 1
A36: Жалобы | B36: интоксикация | C36: продолжительность | D36: не менее месяца | E36: Опрос | F36: Рекомендации по ранней диагностике рака лёгкого для врачей первичного звена | G36: -
A37: Жалобы | B37: кашель | C37: характер | D37: сухой | E37: Опрос | F37: Рекомендации по ранней диагностике рака лёгкого для врачей первичного звена | G37: 1 | H37: при центральном раке
A38: Жалобы | B38: кашель | C38: примесь | D38: мокрота | E38: Опрос | F38: Рекомендации по ранней диагностике рака лёгкого для врачей первичного звена | G38: 1
A39: Жалобы | B39: кашель | C39: примесь | D39: кровь | E39: Опрос | F39: Рекомендации по ранней диагностике рака лёгкого для врачей первичного звена | G39: 1
A40: Жалобы | B40: одышка | C40: наличие | D40: есть | E40: Опрос | F40: Рекомендации по ранней диагностике рака лёгкого для врачей первичного звена | G40: 1
A41: Жалобы | B41: голос | C41: характер | D41: осиплый | E41: Опрос | F41: Рекомендации по ранней диагностике рака лёгкого для врачей первичного звена | G41: 1
A42: Жалобы | B42: боль | C42: локализация | D42: грудная клетка | E42: Опрос | F42: Рекомендации по ранней диагностике рака лёгкого для врачей первичного звена | G42: 1
A43: Общий осмотр | B43: кожные покровы | C43: цвет | D43: цианоз | E43: Осмотр | F43: Рекомендации по ранней диагностике рака лёгкого для врачей первичного звена | G43: 1
A44: Общий осмотр | B44: лицо | C44: состояние | D44: одутловатость | E44: Осмотр | F44: Рекомендации по ранней диагностике рака лёгкого для врачей первичного звена | G44: 1
A45: Общий осмотр | B45: вены лица и шеи | C45: состояние | D45: набухание | E45: Осмотр | F45: Рекомендации по ранней диагностике рака лёгкого для врачей первичного звена | G45: 1
A46: Факторы риска | B46: лучевая терапия | C46: на грудную клетку | D46: в анамнезе | E46: Опрос | F46: Злокачественное новообразование бронхов и легкого | G46: 1
A47: Жалобы | B47: кашель | C47: характер | D47: надсадный | E47: Опрос | F47: Злокачественное новообразование бронхов и легкого | G47: 1 | H47: центральный рак
A48: Жалобы | B48: кровохарканье | C48: наличие | D48: есть | E48: Опрос | F48: Злокачественное новообразование бронхов и легкого | G48: 1
A49: Жалобы | B49: боль в грудной клетке | C49: локализация | D49: на стороне поражения | E49: Опрос | F49: Злокачественное новообразование бронхов и легкого | G49: -
A50: Лабораторные методы обследования | B50: нейронспецифическая енолаза | C50: значение | D50: повышена 16,4 - 1000 нг/мл) | E50: Анализ на онкомаркеры | F50: Злокачественное новообразование бронхов и легкого | G50: 1 | H50: при МРЛ
A51: Лабораторные методы обследования | B51: растворимый фрагмент цитокератина 19 (CYFRA 21-1) в крови | C51: повышен | D51: 2,1-1000 нг/мл. | E51: Анализ на онкомаркеры | F51: Злокачественное новообразование бронхов и легкого | G51: 1
A52: Лабораторные методы обследования | B52: CYFRA 21-1 в крови | C52: повышен | D52: 2,1-1000 нг/мл. | E52: Анализ на онкомаркеры | F52: Злокачественное новообразование бронхов и легкого | G52: 1 | H52: при аденокарциноме
A53: Лабораторные методы обследования | B53: антиген раковый CA-125 в крови | C53: повышен | D53: 36-1000 Ед/мл | E53: Анализ на онкомаркеры | F53: Злокачественное новообразование бронхов и легкого | G53: 1 | H53: при аденокарциноме
A54: Лабораторные методы обследования | B54: CYFRA 21-1 в крови | C54: повышен | D54: 2,1-1000 нг/мл. | E54: Анализ на онкомаркеры | F54: Злокачественное новообразование бронхов и легкого | G54: 1 | H54: при крупноклеточном раке
A55: Лабораторные методы обследования | B55: антиген плоскоклеточной карциномы в крови | C55: повышена | D55: 1,6-1000 нг/мл. | E55: Анализ на онкомаркеры | F55: Злокачественное новообразование бронхов и легкого | G55: 1 | H55: при крупноклеточном раке
A56: Лабораторные методы обследования | B56: раковый эмбриональный антиген (СЕА) | C56: повышение | D56: для некурящих 3,9-1000 нг/мл | E56: Анализ на онкомаркеры | F56: Злокачественное новообразование бронхов и легкого | G56: 1 | H56: при крупноклеточном раке
A57: Лабораторные методы обследования | B57: раковый эмбриональный антиген (СЕА) | C57: повышение | D57: для курящих 5,6-1000 нг/мл | G57: 1
A58: Жалобы | B58: Симптомокомплекс Панкоста | C58: боль | D58: плечевой сустав | E58: Опрос | F58: Злокачественное новообразование бронхов и легкого | G58: 1 | H58: Периферический рак верхушки легкого
A59: Жалобы | B59: Симптомокомплекс Панкоста | C59: боль | D59: плечо | E59: Опрос | F59: Злокачественное новообразование бронхов и легкого | G59: 1
A60: Общий осмотр | B60: Симптомокомплекс Панкоста | C60: атрофия мышц | D60: предплечье | E60: Осмотр | F60: Злокачественное новообразование бронхов и легкого | G60: 1
A61: Общий осмотр | B61: Симптомокомплекс Панкоста | C61: синдром Горнера | D61: птоз | E61: Осмотр | F61: Злокачественное новообразование бронхов и легкого | G61: 1
A62: Общий осмотр | B62: Симптомокомплекс Панкоста | C62: синдром Горнера | D62: миоз | E62: Осмотр | F62: Злокачественное новообразование бронхов и легкого | G62: 1
A63: Общий осмотр | B63: Симптомокомплекс Панкоста | C63: синдром Горнера | D63: энофтальм | E63: Осмотр | F63: Злокачественное новообразование бронхов и легкого | G63: 1
A64: Инструментальные методы обследования | B64: Опухолевый узел | C64: локализация | D64: верхушка легкого | E64: Рентгенография ОГК | F64: Злокачественное новообразование бронхов и легкого | G64: - | H64: х-но для синдрома Панкоста
A65: Инструментальные методы обследования | B65: Опухолевый узел | C65: прорастание | D65: в плевру | E65: Рентгенография ОГК | F65: Злокачественное новообразование бронхов и легкого | G65: - | H65: х-но для синдрома Панкоста
A66: Инструментальные методы обследования | B66: деструкция костей | C66: локализация | D66: 1, 2 ребро | E66: Рентгенография ОГК | F66: Злокачественное новообразование бронхов и легкого | G66: 1 | H66: х-но для синдрома Панкоста
A67: Инструментальные методы обследования | B67: прорастание опухоли в плевру | C67: наличие | D67: есть | E67: Рентгенография ОГК | F67: Злокачественное новообразование бронхов и легкого | G67: 1
A68: Инструментальные методы обследования | B68: деструкция костей | C68: локализация | D68: поперечные отростки позвонков | E68: Рентгенография ОГК | F68: Злокачественное новообразование бронхов и легкого | G68: 1 | H68: х-но для синдрома Панкоста
A69: Общий осмотр | B69: Синдром сдавления верхней полой вены | C69: цианоз | D69: лицо, шея, верхние конечности | E69: Осмотр | F69: Злокачественное новообразование бронхов и легкого | G69: 1 | H69: наиболее х-но для МРЛ
A70: Общий осмотр | B70: Синдром сдавления верхней полой вены | C70: отек | D70: лицо, шея, верхние конечности | E70: Осмотр | F70: Злокачественное новообразование бронхов и легкого | G70: 1 | H70: наиболее х-но для МРЛ
A71: Общий осмотр | B71: Синдром сдавления верхней полой вены | C71: развитые подкожные коллатерали | D71: туловище | E71: Осмотр | F71: Злокачественное новообразование бронхов и легкого | G71: 1 | H71: наиболее х-но для МРЛ
A72: Инструментальные методы обследования | B72: Синдром Мари-Бамберга | C72: утолщение и склероз костей | D72: голень и предплечья | E72: Ретгенография | F72: Злокачественное новообразование бронхов и легкого | G72: 1
A73: Инструментальные методы обследования | B73: Синдром Мари-Бамберга | C73: утолщение и склероз костей | D73: кистей и стоп | E73: Ретгенография | F73: Злокачественное новообразование бронхов и легкого | G73: 1
A74: Общий осмотр | B74: Синдром Мари-Бамберга | C74: припухлость суставов | D74: локтевые, голеностопные | E74: Осмотр | F74: Злокачественное новообразование бронхов и легкого | G74: 1
A75: Общий осмотр | B75: Синдром Мари-Бамберга | C75: синдром "барабанных палочек" | E75: Осмотр | F75: Злокачественное новообразование бронхов и легкого | G75: 1
A76: Лабораторные методы обследования | B76: Молекулярно-генетическое исследование биопсийного материала | C76: мутация в гене EGFR (18–21-й экзоны) | D76: обнаружена | E76: Молекулярно-генетическое исследование биопсийного материала | F76: Злокачественное новообразование бронхов и легкого | G76: - | H76: при выявлении неплоскоклеточного рака
A77: Лабораторные методы обследования | B77: Молекулярно-генетическое исследование биопсийного материала | C77: мутация в гене BRAF V600E | D77: обнаружена | E77: Молекулярно-генетическое исследование биопсийного материала | F77: Злокачественное новообразование бронхов и легкого | G77: -
A78: Лабораторные методы обследования | B78: Молекулярно-генетическое исследование | C78: транслокации генов ALK и ROS1 | D78: обнаружена | E78: Молекулярно-генетическое исследование | F78: Злокачественное новообразование бронхов и легкого | G78: - | H78: нужно для определения вида терапии
A79: Лабораторные методы обследования | B79: Определение экспрессии белка PD-L1 | C79: экспрессия | D79: избыточная | E79: Иммуногистохимический метод | F79: Злокачественное новообразование бронхов и легкого | G79: - | H79: При отрицательных или неизвестных данных о наличии мутаций гена EGFR или транслокаций гена ALK (показано для неплоскоклеточного и плоскоклеточного немелкоклеточного РЛ – НМРЛ и только на гистологическом материале)
A80: Инструментальные методы обследования | B80: Рентгенография | C80: очаг | D80: одиночный | E80: Рентгенография ОГК | F80: Злокачественное новообразование бронхов и легкого | G80: 1 | H80: периферическая опухоль
A81: Инструментальные методы обследования | B81: полость распада | E81: КТ ОГК | F81: Злокачественное новообразование бронхов и легкого | G81: 1 | H81: периферическая опухоль
A82: Инструментальные методы обследования | B82: участок инфильтрации | C82: форма | D82: некруглая | E82: КТ ОГК | F82: Злокачественное новообразование бронхов и легкого | G82: 1 | H82: периферическая опухоль
A83: Инструментальные методы обследования | B83: диссеминация | D83: очаговая | E83: КТ ОГК | F83: Злокачественное новообразование бронхов и легкого | G83: 1
A84: Инструментальные методы обследования | B84: Врастание | C84: локализация | D84: грудная стенка | E84: КТ ОГК | F84: Злокачественное новообразование бронхов и легкого | G84: 1 | H84: кортикоплевральная форма
A85: Инструментальные методы обследования | B85: Врастание | C85: локализация | D85: средостение | E85: КТ ОГК | F85: Злокачественное новообразование бронхов и легкого | G85: 1 | H85: медиастенальная форма
A86: Инструментальные методы обследования | B86: Врастание | C86: локализация | D86: верхняя апертура | E86: КТ ОГК | F86: Злокачественное новообразование бронхов и легкого | G86: 1 | H86: опухоль Панкоста
A87: Инструментальные методы обследования | B87: Очаг | C87: плотность | D87: солидный тип | E87: КТ ОГК | F87: Злокачественное новообразование бронхов и легкого | G87: 1
A88: Инструментальные методы обследования | B88: Очаг | C88: плотность | D88: частично солидный тип | E88: КТ ОГК | F88: Злокачественное новообразование бронхов и легкого | G88: 1 | H88: Субсолидный очаг имеет центральный солидный компонент и периферическую зону «матового стекла»
A89: Инструментальные методы обследования | B89: Очаг | C89: плотность | D89: по типу "матового стекла" | E89: КТ ОГК | F89: Злокачественное новообразование бронхов и легкого | G89: 1 | H89: характерен для аденокарциномы со стелющимся ростом, в том числе in situ
A90: Инструментальные методы обследования | B90: Солидный очаг | C90: контуры | D90: бугристые/лучистые | E90: КТ ОГК | F90: Злокачественное новообразование бронхов и легкого | G90: 1
A91: Инструментальные методы обследования | B91: Солидный очаг | C91: стенки дренирующего бронха | D91: утолщены | E91: КТ ОГК | F91: Злокачественное новообразование бронхов и легкого | G91: 1
A92: Инструментальные методы обследования | B92: Солидный очаг | C92: висцеральная плевра | D92: втянута в опухоль | E92: КТ ОГК | F92: Злокачественное новообразование бронхов и легкого | G92: 1
A93: Инструментальные методы обследования | B93: Солидный очаг | C93: висцеральная плевра | D93: локально утолщена | E93: КТ ОГК | F93: Злокачественное новообразование бронхов и легкого | G93: 1
A94: Инструментальные методы обследования | B94: Очаг по типу "матового стекла" | C94: уровень накопления изотопа | D94: низкий | E94: ПЭТ КТ | F94: Злокачественное новообразование бронхов и легкого | G94: - | H94: с ФДГ
A95: Жалобы | B95: Боль | C95: локализация | D95: суставы (артралгия) | E95: Опрос | F95: Рекомендации по ранней диагностике рака лёгкого для врачей первичного звена | G95: 1
A96: Лабораторные методы обследования | B96: СОЭ | C96: повышен | E96: Общий анализ крови | F96: Синдром полости в легком: абсцесс, гангрена легких, рак легких | G96: 1
A97: Лабораторные методы обследования | B97: Анемия | C97: эритроциты | D97: понижен | E97: Общий анализ крови | F97: Синдром полости в легком: абсцесс, гангрена легких, рак легких | G97: 1
A98: Лабораторные методы обследования | B98: Анемия | C98: гемоглобин | D98: понижен | E98: Общий анализ крови | F98: Синдром полости в легком: абсцесс, гангрена легких, рак легких | G98: 1
A99: Инструментальные методы обследования | B99: Полость в легком | C99: стенки | D99: толстые | E99: Рентгенография ОГК | F99: Синдром полости в легком: абсцесс, гангрена легких, рак легких | G99: 1
A100: Инструментальные методы обследования | B100: Полость в легком | C100: внутренние контуры | D100: бухтообразные, достаточно четкие | E100: Рентгенография ОГК | F100: Синдром полости в легком: абсцесс, гангрена легких, рак легких | G100: 1
A101: Инструментальные методы обследования | B101: Полость в легком | C101: расположение | D101: эксцентрическое | E101: Рентгенография ОГК | F101: Синдром полости в легком: абсцесс, гангрена легких, рак легких | G101: 1
A102: Инструментальные методы обследования | B102: Полость в легком | C102: количество жидкости | D102: малое | E102: Рентгенография ОГК | F102: Синдром полости в легком: абсцесс, гангрена легких, рак легких | G102: 1
A103: Инструментальные методы обследования | B103: Полость в легком | C103: наружные контуры | D103: четкие, иногда с полицикличностью | E103: Рентгенография ОГК | F103: Синдром полости в легком: абсцесс, гангрена легких, рак легких | G103: 1
A104: Жалобы | B104: Боль | C104: локализация | D104: кости | E104: Опрос | F104: Lung Cancer: Diagnosis and Management | G104: 1 | H104: при метастазах в костях
A105: Жалобы | B105: Боль | C105: локализация | D105: голова | E105: Опрос | F105: Lung Cancer: Diagnosis and Management | G105: 1 | H105: метастазы в ГМ
A106: Жалобы | B106: Тошнота | C106: наличие | D106: есть | E106: Опрос | F106: Lung Cancer: Diagnosis and Management | G106: 1 | H106: метастазы в ГМ
A107: Жалобы | B107: Рвота | C107: наличие | D107: есть | E107: Опрос | F107: Lung Cancer: Diagnosis and Management | G107: 1 | H107: метастазы в ГМ
A108: Жалобы | B108: Судороги | C108: наличие | D108: есть | E108: Опрос | F108: Lung Cancer: Diagnosis and Management | G108: 1 | H108: метастазы в ГМ
A109: Общий осмотр | B109: Спутанность сознания | C109: наличие | D109: есть | E109: Опрос | F109: Lung Cancer: Diagnosis and Management | G109: 1 | H109: метастазы в ГМ
A110: Общий осмотр | B110: Очаговый неврологический дефицит | C110: наличие | D110: есть | E110: Осмотр | F110: Lung Cancer: Diagnosis and Management | G110: 1 | H110: метастазы в ГМ
A111: Лабораторные методы обследования | B111: биохимический анализ крови | C111: АЛТ | D111: повышение | E111: Биохимический анализ крови | F111: Lung Cancer: Diagnosis and Management | G111: - | H111: метастазы в печени
A112: Лабораторные методы обследования | B112: биохимический анализ крови | C112: АСТ | D112: повышение | E112: Биохимический анализ крови | F112: Lung Cancer: Diagnosis and Management | G112: - | H112: метастазы в печени
A113: Общий осмотр | B113: Лимфоузлы | C113: размер | D113: увеличение | E113: Пальпация | F113: Lung Cancer: Diagnosis and Management | G113: 1 | H113: метастазы в л/у, особенно в надключичной ямке
...

Sheet Туберкулез
A1: Раздел | B1: Признак | C1: Атрибут | D1: Значение (характеристика) | E1: Исследование | F1: Источник | G1: Комментарии
A2: Жалобы | B2: кашель | C2: характер | D2: влажный (продуктивный) | E2: Опрос | F2: Туберкулез легких в пульмонологической практике
A3: Жалобы | B3: кашель | C3: характер | D3: сухой (непродуктивный) | E3: Опрос | F3: Туберкулез легких в пульмонологической практике | G3: более часто, чем влажный
A4: Жалобы | B4: боль | C4: локализация | D4: грудная клетка | E4: Опрос | F4: Туберкулез легких в пульмонологической практике
A5: Жалобы | B5: одышка | C5: наличие | D5: есть | E5: Опрос | F5: Туберкулез легких в пульмонологической практике
A6: Общий осмотр | B6: боль | C6: локализация | D6: мышцы плечевого пояса | E6: Пальпация
A7: Общий осмотр | B7: ригидность мышц | C7: локализация | D7: плечевой пояс | E7: Пальпация
A8: Общий осмотр | B8: укорочение перкуторного звука | C8: локализация | D8: надключичные пространства | E8: Перкуссия
A9: Общий осмотр | B9: укорочение перкуторного звука | D9: подключичные пространства | E9: Перкуссия
A10: Общий осмотр | B10: укорочение перкуторного звука | D10: надлопаточная область | E10: Перкуссия
A11: Общий осмотр | B11: укорочение перкуторного звука | D11: межлопаточная область | E11: Перкуссия
A12: Общий осмотр | B12: укорочение перкуторного звука | D12: подмышечная область | E12: Перкуссия
A13: Факторы риска | B13: пол | C13: пол | D13: мужской | E13: Опрос | F13: Туберкулез легких в пульмонологической практике
A14: Факторы риска | B14: социальный статус | D14: безработный | E14: Опрос | F14: Туберкулез легких в пульмонологической практике
A15: Лабораторные методы обследования | B15: наличие МБТ в мокроте | C15: МБТ | D15: обнаружено | E15: Бактериоскопия мокроты с окраской по Цилю-Нильсену | F15: Туберкулез легких в пульмонологической практике
A16: Лабораторные методы обследования | B16: наличие МБТ в бронхоальвеолярной жидкости | C16: МБТ | D16: обнаружено | E16: Микроскопия мазка с окраской по Цилю-Нильсену | F16: Туберкулез легких в пульмонологической практике
A17: Жалобы | B17: кровохарканье | C17: наличие | D17: есть | E17: Опрос | F17: Туберкулез у взрослых. Клинические рекомендации
A18: Жалобы | B18: ночные поты | C18: наличие | D18: есть | E18: Опрос | F18: Туберкулез у взрослых. Клинические рекомендации
A19: Жалобы | B19: потливость | C19: наличие | D19: есть | E19: Опрос | F19: Туберкулез у взрослых. Клинические рекомендации
A20: Жалобы | B20: снижение массы тела | C20: наличие | D20: есть | E20: Опрос | F20: Туберкулез у взрослых. Клинические рекомендации
A21: Жалобы | B21: головная боль | C21: наличие | D21: есть | E21: Опрос | F21: Туберкулез у взрослых. Клинические рекомендации
A22: Жалобы | B22: раздражительность | C22: наличие | D22: есть | E22: Опрос | F22: Туберкулез у взрослых. Клинические рекомендации
A23: Лабораторные методы обследования | B23: проба с аллергеном туберкулезным рекомбинантным | D23: положительная | E23: Проба с аллергеном туберкулезным рекомбинантным | F23: Туберкулез у взрослых. Клинические рекомендации
A24: Жалобы | B24: интоксикационный синдром | D24: утомляемость | E24: Опрос | F24: Туберкулез у взрослых. Клинические рекомендации
A25: Жалобы | B25: интоксикационный синдром | D25: слабость | E25: Опрос | F25: туберкулез легких в пульмонологической практике
A26: Жалобы | B26: интоксикационный синдром | D26: повышение температуры | E26: Опрос | F26: туберкулез легких в пульмонологической практике
A27: Факторы риска | B27: контакт с больными туберкулезом | C27: в анамнезе | D27: есть | E27: Опрос | F27: Диссеменированный туберкулез легких в клинической практике
A28: Инструментальные методы обследования | B28: очаговые тени | C28: размер | D28: средние | E28: Рентгенография ОГК | F28: Диссеменированный туберкулез легких в клинической практике
A29: Инструментальные методы обследования | B29: очаговые тени | C29: размер | D29: крупные | E29: Рентгенография ОГК | F29: Диссеменированный туберкулез легких в клинической практике
A30: Инструментальные методы обследования | B30: очаговые тени | C30: перифокальная реакция | D30: выражена | E30: Рентгенография ОГК | F30: Диссеменированный туберкулез легких в клинической практике
A31: Инструментальные методы обследования | B31: очаговые тени | C31: характер | D31: экссудативные | E31: Рентгенография ОГК | F31: Диссеменированный туберкулез легких в клинической практике
A32: Инструментальные методы обследования | B32: очаговые тени | C32: характер | D32: экссудативно-казеозные | E32: Рентгенография ОГК | F32: Диссеменированный туберкулез легких в клинической практике
A33: Инструментальные методы обследования | B33: очаговые тени | D33: сливающиеся | E33: Рентгенография ОГК | F33: Диссеменированный туберкулез легких в клинической практике
A34: Инструментальные методы обследования | B34: деструктивные полости | C34: расположение | D34: двустороннее | E34: Рентгенография ОГК | F34: Диссеменированный туберкулез легких в клинической практике | G34: при прогрессировании образующие полости распада
A35: Инструментальные методы обследования | B35: деструктивные полости | C35: ширина перикавитарной зоны инфильтрации | D35: неравномерная | E35: Рентгенография ОГК | F35: Диссеменированный туберкулез легких в клинической практике
A36: Инструментальные методы обследования | B36: деструктивные полости | C36: тип каверны | D36: пневмониогенный | E36: Рентгенография ОГК | F36: Диссеменированный туберкулез легких в клинической практике
A37: Инструментальные методы обследования | B37: деструктивные полости | C37: тип | D37: "штампованные" полости | E37: Рентгенография ОГК | F37: Диссеменированный туберкулез легких в клинической практике
A38: Инструментальные методы обследования | B38: лимфатические узлы | C38: размер | D38: увеличен | E38: Рентгенография ОГК | F38: Imaging in tuberculosis
A39: Инструментальные методы обследования | B39: лимфатические узлы | C39: размер | D39: увеличен | E39: КТ ОГК | F39: Imaging in tuberculosis
A40: Инструментальные методы обследования | B40: лимфатические узлы | C40: размер | D40: больше 2 см | E40: КТ ОГК | F40: Imaging in tuberculosis
A41: Инструментальные методы обследования | B41: лимфатические узлы | C41: кольцевидное усиление на периферии | D41: есть | E41: КТ ОГК | F41: Imaging in tuberculosis
A42: Инструментальные методы обследования | B42: лимфатические узлы | C42: вовлечение | D42: бронхолегочные | E42: КТ ОГК | F42: Imaging in tuberculosis
A43: Инструментальные методы обследования | B43: лимфатические узлы | C43: вовлечение | D43: медиастенальные | E43: КТ ОГК | F43: Imaging in tuberculosis
A44: Лабораторные методы обследования | B44: СОЭ | C44: повышение | E44: Общий анализ крови | F44: Рентгено-ультразвуковая картина при инфильтративном туберкулезе легких
A45: Лабораторные методы обследования | B45: лейкоциты | C45: повышение | E45: Общий анализ крови | F45: Рентгено-ультразвуковая картина при инфильтративном туберкулезе легких
A46: Лабораторные методы обследования | B46: лимфоциты | C46: понижение | E46: Общий анализ крови | F46: Диагностика туберкулеза органов дыхания в клинике внутренних болезней
A47: Лабораторные методы обследования | B47: моноциты | C47: повышение | E47: Общий анализ крови | F47: Диагностика туберкулеза органов дыхания в клинике внутренних болезней
A48: Лабораторные методы обследования | B48: сдвиг лейкоцитарной формулы | C48: палочкоядерный (влево) | E48: Общий анализ крови | F48: Диагностика туберкулеза органов дыхания в клинике внутренних болезней
A49: Инструментальные методы обследования | B49: инфильтративные изменения | C49: контуры | D49: неровные | E49: Рентгенография ОГК | F49: Рентгено-ультразвуковая картина при инфильтративном туберкулезе легких
A50: Инструментальные методы обследования | B50: инфильтративные изменения | C50: плотность | D50: неоднородная | E50: Рентгенография ОГК | F50: Рентгено-ультразвуковая картина при инфильтративном туберкулезе легких
A51: Инструментальные методы обследования | B51: инфильтративные изменения | C51: контуры | D51: нечеткие | E51: Рентгенография ОГК | F51: Рентгено-ультразвуковая картина при инфильтративном туберкулезе легких
A52: Инструментальные методы обследования | B52: инфильтративные изменения | C52: признаки деструкции | E52: Рентгенография ОГК | F52: Рентгено-ультразвуковая картина при инфильтративном туберкулезе легких
A53: Факторы риска | B53: курение | C53: в анамнезе | E53: Опрос | F53: Социальный портрет больного туберкулезом в мегаполисе
A54: Факторы риска | B54: ВИЧ-инфекция | E54: Опрос | F54: Социальный портрет больного туберкулезом в мегаполисе
A55: Факторы риска | B55: возраст | C55: возраст | D55: трудоспособный (18-60 лет) | E55: Опрос | F55: Социальный портрет больного туберкулезом в мегаполисе
A56: Факторы риска | B56: образование | C56: уровень | D56: среднее специальное | E56: Опрос | F56: Социальный портрет больного туберкулезом в мегаполисе
A57: Факторы риска | B57: образование | C57: уровень | D57: среднее | E57: Опрос | F57: Социальный портрет больного туберкулезом в мегаполисе
A58: Факторы риска | B58: доход | C58: уровень | D58: низкий | E58: Опрос | F58: Социальный портрет больного туберкулезом в мегаполисе
A59: Факторы риска | B59: доход | C59: уровень | D59: средний | E59: Опрос | F59: Социальный портрет больного туберкулезом в мегаполисе
A60: Факторы риска | B60: семейное положение | D60: не женат (холост) | E60: Опрос | F60: Социальный портрет больного туберкулезом в мегаполисе
A61: Жалобы | B61: температура тела | C61: значение | D61: субфебрильная | E61: Опрос | F61: Дифференциальная диагностика опухолевого поражения и туберкулеза легких: обзор
A62: Жалобы | B62: температура тела | C62: длительность | D62: длительно | E62: Опрос | F62: Дифференциальная диагностика опухолевого поражения и туберкулеза легких: обзор
A63: Факторы риска | B63: хронические заболевания | C63: сахарный диабет | D63: есть | E63: Опрос | F63: Дифференциальная диагностика опухолевого поражения и туберкулеза легких: обзор
A64: Факторы риска | B64: хронические заболевания | C64: пылевые (профессиональные) заболевания легких | E64: Опрос | F64: Дифференциальная диагностика опухолевого поражения и туберкулеза легких: обзор
A65: Факторы риска | B65: хронические заболевания | C65: заболевания ЖКТ | E65: Опрос | F65: Дифференциальная диагностика опухолевого поражения и туберкулеза легких: обзор
A66: Факторы риска | B66: хронические заболевания | C66: ХОБЛ | E66: Опрос | F66: Дифференциальная диагностика опухолевого поражения и туберкулеза легких: обзор
A67: Факторы риска | B67: хронические заболевания | C67: кахексия | E67: Опрос | F67: Дифференциальная диагностика опухолевого поражения и туберкулеза легких: обзор
A68: Факторы риска | B68: диспансерный учет | C68: наркологические учреждения | D68: состоят | E68: Опрос | F68: Дифференциальная диагностика опухолевого поражения и туберкулеза легких: обзор
A69: Факторы риска | B69: диспансерный учет | C69: психиатрические учреждения | D69: состоят | E69: Опрос | F69: Дифференциальная диагностика опухолевого поражения и туберкулеза легких: обзор
A70: Факторы риска | B70: терапия | C70: кортикостероидная | D70: получают | E70: Опрос | F70: Дифференциальная диагностика опухолевого поражения и туберкулеза легких: обзор
A71: Факторы риска | B71: терапия | C71: цитостатическая | D71: получают | E71: Опрос | F71: Дифференциальная диагностика опухолевого поражения и туберкулеза легких: обзор
A72: Факторы риска | B72: терапия | C72: лучевая | D72: получают | E72: Опрос | F72: Дифференциальная диагностика опухолевого поражения и туберкулеза легких: обзор
A73: Факторы риска | B73: авария на ЧАЭС | D73: в анамнезе | E73: Опрос | F73: Дифференциальная диагностика опухолевого поражения и туберкулеза легких: обзор
A74: Факторы риска | B74: экссудативный плеврит | D74: в анамнезе | E74: Опрос | F74: Дифференциальная диагностика опухолевого поражения и туберкулеза легких: обзор
A75: Факторы риска | B75: рецидивирующий сухой плеврит | D75: в анамнезе | E75: Опрос | F75: Дифференциальная диагностика опухолевого поражения и туберкулеза легких: обзор
A76: Факторы риска | B76: полиаденопатия | D76: в анамнезе | E76: Опрос | F76: Дифференциальная диагностика опухолевого поражения и туберкулеза легких: обзор
A77: Факторы риска | B77: фликтенулезный кератоконъюнктивит | D77: в анамнезе | E77: Опрос | F77: Дифференциальная диагностика опухолевого поражения и туберкулеза легких: обзор
A78: Факторы риска | B78: узловатая эритема | D78: в анамнезе | E78: Опрос | F78: Дифференциальная диагностика опухолевого поражения и туберкулеза легких: обзор
A79: Инструментальные методы обследования | B79: туберкулез | C79: локализация | D79: верхушечный сегмент верхней доли легкого | E79: Рентгенография | F79: Дифференциальная диагностика опухолевого поражения и туберкулеза легких: обзор | G79: 70-80%туберкулеза в этих местах
A80: Инструментальные методы обследования | B80: туберкулез | C80: локализация | D80: задний сегмен верхней доли легкого | E80: Рентгенография | F80: Дифференциальная диагностика опухолевого поражения и туберкулеза легких: обзор | G80: 70-80%туберкулеза в этих местах
A81: Инструментальные методы обследования | B81: «дерево в почках» | E81: Рентгенография | F81: Дифференциальная диагностика опухолевого поражения и туберкулеза легких: обзор | G81: мелкие центрилобулярные разветвленные Y- или V-образные структуры толщиной до 1–2 мм с утолщениями на концах
A82: Инструментальные методы обследования | B82: туберкулема | C82: количество | D82: единичные | E82: Рентгенография | F82: Дифференциальная диагностика опухолевого поражения и туберкулеза легких: обзор
A83: Инструментальные методы обследования | B83: пневмосклероз | C83: наличие | D83: есть | E83: Рентгенография | F83: Дифференциальная диагностика опухолевого поражения и туберкулеза легких: обзор
A84: Инструментальные методы обследования | B84: поглощение | C84: степень | D84: повышено | E84: ПЭТ-КТ с ФДГ | F84: Дифференциальная диагностика опухолевого поражения и туберкулеза легких: обзор
A85: Лабораторные методы обследования | B85: реакция Манту с 2 ТЕ | C85: реакция | D85: выраженная положительная (более 12 мм) | E85: Реакция Манту | F85: Диагностика туберкулеза органов дыхания в клинике внутренних болезней
A86: Лабораторные методы обследования | B86: реакция Манту с 2 ТЕ | C86: реакция | D86: туберкулиновая гиперергия (21 мм и более) | E86: Реакция Манту | F86: Диагностика туберкулеза органов дыхания в клинике внутренних болезней
A87: Лабораторные методы обследования | B87: реакция Манту с 2 ТЕ | C87: реакция | D87: везикула | E87: Реакция Манту | F87: Диагностика туберкулеза органов дыхания в клинике внутренних болезней
A88: Лабораторные методы обследования | B88: реакция Манту с 2 ТЕ | C88: реакция | D88: некроз | E88: Реакция Манту | F88: Диагностика туберкулеза органов дыхания в клинике внутренних болезней
A89: Лабораторные методы обследования | B89: реакция Манту с 2 ТЕ | C89: реакция | D89: регионарный лимфангит | E89: Реакция Манту | F89: Диагностика туберкулеза органов дыхания в клинике внутренних болезней
A90: Лабораторные методы обследования | B90: количественный ИФА крови на противотуберкулезные АТ | C90: результат | D90: положительная | E90: Количественный ИФА крови на противотуберкулезные АТ | F90: Пути оптимизации диагностики и диф диагностики диссеминированного туберкулеза легких
A91: Лабораторные методы обследования | B91: ПЦР мокроты на ДНК МБТ | C91: результат | D91: выявлена ДНК | E91: ПЦР | F91: Пути оптимизации диагностики и диф диагностики диссеминированного туберкулеза легких
A92: Общий осмотр | B92: дыхание | C92: характер | D92: жесткое | E92: Аускультация | F92: Пути оптимизации диагностики и диф диагностики диссеминированного туберкулеза легких
A93: Общий осмотр | B93: дыхание | C93: характер | D93: везикулярное | E93: Аускультация | F93: Пути оптимизации диагностики и диф диагностики диссеминированного туберкулеза легких
... A110: Лабораторные методы обследования | B110: гистологическое исследование операционного (биопсийного) материала | C110: казеификация | D110: обнаружена | E110: Гистологическое исследование операционного (биопсийного) материала | F110: Из ИБ
A111: Лабораторные методы обследования | B111: гистологическое исследование операционного (биопсийного) материала | C111: специфические гранулемы | D111: обнаружены | E111: Гистологическое исследование операционного (биопсийного) материала | F111: Туберкулез легких в пульмонологической практике | G111: абсолютные диагностические признаки
A112: Лабораторные методы обследования | B112: культивирование МБТ на жидкой/плотной питательной среде | C112: наличие (рост) МБТ | D112: обнаружено | E112: Культуральный метод | F112: ПРИКАЗ от 29 декабря 2014 года N 951 Об утверждении методических рекомендаций по совершенствованию диагностики и лечения туберкулеза органов дыхания
A113: Лабораторные методы обследования | B113: микробиологическое исследование бронхоальвеолярного лаважа на МБТ | C113: МБТ | D113: обнаружена | E113: Микробиологическое исследование бронхоальвеолярного лаважа на МБТ | F113: Пути оптимизации диагностики и диф диагностики диссеминированного туберкулеза легких
A114: Лабораторные методы обследования | B114: люминесцентная микроскопия мокроты | C114: наличие КУМ | D114: обнаружены | E114: Люминесцентная микроскопия мокроты | F114: Диагностические ошибки при инфильтративных изменениях в легких
A115: Лабораторные методы обследования | B115: Иммунохроматографический метод идентификации выросших культур микроорганизмов | C115: наличие специфического антигена MБT МРТ64 | D115: обнаружен | E115: Иммунохроматографический метод | F115: ПРИКАЗ от 29 декабря 2014 года N 951 Об утверждении методических рекомендаций по совершенствованию диагностики и лечения туберкулеза органов дыхания | G115: рекомендован в качестве основного при проведении идентификации культур, выросших на жидких и/или плотных питательных средах, а также в контаминированных культуральных образцах
A116: Лабораторные методы обследования | B116: исследование образца с помощью бактериологического анализатора Bactec MGIT - 960 | C116: рост МБТ | D116: обнаружен | E116: Культуральный метод | F116: СОВРЕМЕННЫЕ ВОЗМОЖНОСТИ ДИАГНОСТИКИ ТУБЕРКУЛЕЗА легких | G116: исследуется мокрота, плевральная ж-ть, БА лаваж и тд
...

Sheet ХОБЛ
A1: Раздел | B1: Признак | C1: Атрибут | D1: Значение | E1: Исследование | F1: Источник | G1: Комментарии
A2: Инструментальные методы обследования | B2: ОФВ1/ФЖЕЛ | C2: снижение | D2: <70% | E2: Спирометрия | F2: ХОБЛ: ключевые проблемы
A3: Общий осмотр | B3: хрипы | C3: характер | D3: дистанционные | F3: ХОБЛ: ключевые проблемы
A4: Жалобы | B4: одышка при физической нагрузке | C4: наличие | D4: есть | F4: ХОБЛ: ключевые проблемы
A5: Жалобы | B5: чувство сдавления в груди | C5: наличие | D5: есть | F5: ХОБЛ: ключевые проблемы
A6: Жалобы | B6: кашель | C6: характер | D6: продуктивный | F6: ХОБЛ: ключевые проблемы
B7: гипоксемия | F7: ХОБЛ: ключевые проблемы
B8: гиперкапния | F8: ХОБЛ: ключевые проблемы
A9: Инструментальные методы обследования | B9: пневмосклероз | C9: характер | D9: сетчатый | E9: Рентгенография ОГК | F9: Бронхоскопия в диагностике ХОБЛ
A10: Инструментальные методы обследования | B10: эмфизема | C10: наличие | D10: есть | E10: Рентгенография ОГК | F10: Бронхоскопия в диагностике ХОБЛ
A11: Инструментальные методы обследования | B11: эмфизема | C11: наличие | D11: есть | E11: КТ ОГК | F11: Бронхоскопия в диагностике ХОБЛ
A12: Инструментальные методы обследования | B12: слизистая оболочка бронхов | C12: состояние | D12: гиперемирована | E12: Бронхоскопия | F12: Бронхоскопия в диагностике ХОБЛ
A13: Инструментальные методы обследования | B13: сосудистый рисунок | C13: состояние | D13: смазан | E13: Бронхоскопия | F13: Бронхоскопия в диагностике ХОБЛ
A14: Инструментальные методы обследования | B14: секрет | C14: характер | D14: слизистые | E14: Бронхоскопия | F14: Бронхоскопия в диагностике ХОБЛ
A15: Инструментальные методы обследования | B15: слизистая оболочка бронхов | C15: цвет | D15: ярко-красный | E15: Бронхоскопия | F15: Бронхоскопия в диагностике ХОБЛ
A16: Инструментальные методы обследования | B16: сосудистый рисунок | C16: состояние | D16: не прослеживается | E16: Бронхоскопия | F16: Бронхоскопия в диагностике ХОБЛ
A17: Инструментальные методы обследования | B17: межкольцевые промежутки | C17: состояние | D17: сглажены | E17: Бронхоскопия | F17: Бронхоскопия в диагностике ХОБЛ | G17: имеются ввиду промежутки между хрящами
A18: Инструментальные методы обследования | B18: устья сегментарных бронхов | C18: размер | D18: сужены | E18: Бронхоскопия | F18: Бронхоскопия в диагностике ХОБЛ
A19: Инструментальные методы обследования | B19: устья субсегментарных бронхов | C19: размер | D19: сужены | E19: Бронхоскопия | F19: Бронхоскопия в диагностике ХОБЛ
A20: Инструментальные методы обследования | B20: секрет | C20: характер | D20: слизисто-гнойный | E20: Бронхоскопия | F20: Бронхоскопия в диагностике ХОБЛ
A21: Инструментальные методы обследования | B21: слизистая оболочка бронхов | C21: цвет | D21: багрово-синюшный цвет | E21: Бронхоскопия | F21: Бронхоскопия в диагностике ХОБЛ
A22: Инструментальные методы обследования | B22: секрет | C22: характер | D22: гнойный | E22: Бронхоскопия | F22: Бронхоскопия в диагностике ХОБЛ
A23: Инструментальные методы обследования | B23: секрет | C23: количество | D23: большое | E23: Бронхоскопия | F23: Бронхоскопия в диагностике ХОБЛ
A24: Инструментальные методы обследования | B24: дистония трахеи | C24: наличие | D24: есть | E24: Бронхоскопия | F24: Бронхоскопия в диагностике ХОБЛ
A25: Инструментальные методы обследования | B25: трахея | C25: состояние | D25: сужение | E25: Бронхоскопия | F25: Бронхоскопия в диагностике ХОБЛ
A26: Инструментальные методы обследования | B26: главные бронхи | C26: состояние | D26: сужение | E26: Бронхоскопия | F26: Бронхоскопия в диагностике ХОБЛ
A27: Инструментальные методы обследования | B27: слизистая оболочка бронхов | C27: цвет | D27: серый | E27: Бронхоскопия | F27: Бронхоскопия в диагностике ХОБЛ
A28: Инструментальные методы обследования | B28: хрящи | C28: контуры | D28: стерты | E28: Бронхоскопия | F28: Бронхоскопия в диагностике ХОБЛ
A29: Инструментальные методы обследования | B29: слизистая оболочка бронхов | C29: складчатость | D29: продольная | E29: Бронхоскопия | F29: Бронхоскопия в диагностике ХОБЛ
... A31: Инструментальные методы обследования | B31: междолевые шпоры | C31: состояние | D31: утолщены | E31: Бронхоскопия | F31: Бронхоскопия в диагностике ХОБЛ
A32: Инструментальные методы обследования | B32: секрет | C32: количество | D32: значительное | E32: Бронхоскопия | F32: Бронхоскопия в диагностике ХОБЛ | G32: про атрофический бронхит писать не стала
A33: Факторы риска | B33: курение | C33: наличие | D33: есть | E33: Опрос | F33: Свежий взгляд на ХОБЛ
A34: Факторы риска | B34: курение матери во время беременности | C34: наличие | D34: есть | E34: Опрос | F34: Свежий взгляд на ХОБЛ
A35: Факторы риска | B35: бронхиальная астма в анамнезе | C35: в сочетании с | D35: курение (в прошлом или в анамнезе) | E35: Опрос | F35: Свежий взгляд на ХОБЛ | G35: КлинРеки ХОБЛ (2021)
A36: Жалобы | B36: кашель | C36: длительность | D36: хронический | E36: Опрос | F36: ЭВОЛЮЦИЯ ВЗГЛЯДОВ НА ПРОБЛЕМУ ХОБЛ | G36: КлинРеки ХОБЛ (2021)
A37: Жалобы | B37: мокрота | C37: наличие | D37: есть | E37: Опрос | F37: ЭВОЛЮЦИЯ ВЗГЛЯДОВ НА ПРОБЛЕМУ ХОБЛ
A38: Факторы риска | B38: вдыхание вредных веществ | C38: вещество | D38: производственная пыль | E38: Опрос | F38: ЭВОЛЮЦИЯ ВЗГЛЯДОВ НА ПРОБЛЕМУ ХОБЛ
A39: Факторы риска | B39: респираторные инфекции | C39: частота | D39: часто | E39: Опрос | F39: ЭВОЛЮЦИЯ ВЗГЛЯДОВ НА ПРОБЛЕМУ ХОБЛ
A40: Жалобы | B40: масса тела | C40: вес | D40: уменьшение | E40: Опрос | F40: ЭВОЛЮЦИЯ ВЗГЛЯДОВ НА ПРОБЛЕМУ ХОБЛ
B41: обструкция бронхов | E41: Осмотр
B42: эмфизема | E42: Осмотр
B43: дыхательная недостаточность | E43: Осмотр
B44: оценка работы дыхательных мышц | E44: Осмотр
B45: SpO2 / SaO2 | C45: снижена | D45: И эритроцитоз = гипоксемия
B46: mMRC / MRC | C46: степень тяжести | D46: 1 | F46: КлинРеки
D47: 2 | F47: КлинРеки
D48: 3 | F48: КлинРеки
D49: 4 | F49: КлинРеки

Sheet ХТЭЛГ
A1: Раздел | B1: Признак | C1: Атрибут | D1: Значение | E1: Исследование | F1: Источник | G1: Комментарии
B2: ТЭЛА в анамнезе | G2: в течение 2 лет после острой ТЭЛА частота ХТЭЛГ составляет до 9,1%
B3: Тромбоз глубоких вен нижних конечностей | G3: 40-50% больныхХТЭЛГ имеют данный диагноз в анамнезе
B4: Возраст 45-60 лет
B5: Одышка при физических нагрузках | D5: Инспираторного характера, возникает при интенсивной нагрузке и в состоянии покоя
B6: Слабость
B7: Повышенная утомляемость
B8: Боли в области сердца | D8: давящие, ноющие, колющие, сжимающие; без четкого начала, продолжительностью от нескольких минут до суток
B9: Головокружение
B10: Обморочные состояния
B11: Кашель | C11: ???
B12: Кровохарканье
B13: Отеки | C13: Нижних конечностей
B14: Асцит
B15: Снижение аппетита
B16: Признаки развернутой правожелудочковой сердечной недостаточности
B17: Ортопноэ | D17: Связаны с сопутствующими заболеваниями
B18: Артралгии
B19: Кожные проявления
B20: Лихорадка
B21: Храп
B22: Ночное апноэ
B23: Признаки гипертрофии правого желудочка на ЭКГ | E23: ЭКГ
B24: Признаки дилатации правого предсердия | E24: ЭКГ
B25: Признаки гипертрофии правого предсердия | E25: ЭКГ
B26: Отклонение электрической оси сердца вправо | E26: ЭКГ

Sheet Симптомокомплексы
A1: Симптомокомплекс (условное название) | B1: Симптомокомплекс (официальное название) | C1: Признаки | D1: Обязательность
A2: Симптомокомплекс #1 | B2: Интоксикационный синдром, характерный для туберкулеза легких | C2: утомляемость | D2: Желателен
C3: слабость | D3: Желателен
C4: повышение температуры | D4: Желателен
A5: Симптомокомплекс #2 | B5: Интоксикационный синдром, характерный для бактериальной пневмонии | C5: сонливость | D5: Желателен
C6: беспокойство | D6: Желателен
C7: спутанность сознания | D7: Желателен
C8: анорексия | D8: Желателен
C9: тошнота | D9: Желателен
C10: рвота | D10: Желателен
C11: слабость | D11: Желателен
C12: утомляемость | D12: Желателен
A13: Симптомокомплекс #3 | B13: Интоксикационный синдром, характерный для вирусный пневмонии | C13: миалгия | D13: Желателен
C14: боль в глазных яблоках | D14: Желателен
C15: оссалгия | D15: Желателен
C16: головная боль | D16: Желателен
C17: лихорадка | D17: Желателен
C18: озноб | D18: Желателен
A19: Симптомокомплекс #4 | B19: Бронхообструктивный синдром | C19: жеское дыхание | D19: Желателен
C20: сухие свистящие хрипы | D20: Желателен
C21: цианоз лица | D21: Желателен
C22: акроцианоз | D22: Желателен
A23: Симптомокомплекс #5 | B23: Синдром сдавления верхней полой вены | C23: цианоз лица | D23: Желателен
C24: цианоз шеи | D24: Желателен
C25: цианоз верхних конечностей | D25: Желателен
C26: отек лица | D26: Желателен
C27: отек шеи | D27: Желателен
C28: отек верхних конечностей | D28: Желателен
C29: развитые подкожные коллатерали на туловище | D29: Желателен
A30: Симптомокомплекс #6 | B30: Синдром Горнера | C30: птоз | D30: обязателен
C31: миоз | D31: обязателен
C32: энофтальм | D32: обязателен
A33: Симптомокомплекс #7 | B33: Симптомокомплекс Панкоста | C33: боль в плечевом суставе | D33: обязателен
C34: боль в плече | D34: обязателен
C35: атрофия мышц предплечья | D35: обязателен
C36: синдром Горнера | D36: обязателен
A37: Симптомокомплекс #8 | B37: Синдром Мари-Бамберга | C37: утолщение и склероз костей голени
C38: утолщение и склероз костей предплечья
C39: утолщение и склероз костей кистей
C40: утолщение и склероз костей стоп
C41: припухлость локтевых суставов
C42: припухлость голеностопных суставов
C43: синдром "барабанных палочек"

Sheet Перечень разделов

Sheet Скрипт states
C1: INSERT INTO public.states( id, kb_id, user_id, table_name, action, occurrence_date)
A3: ( | B3: 1 | C3: , 1, 1, ' | D3: SECTIONS | E3: ', ' | F3: CREATE | G3: ', now()),
A4: ( | B4: 2 | C4: , 1, 1, ' | D4: SECTIONS | E4: ', ' | F4: CREATE | G4: ', now()),
A5: ( | B5: 3 | C5: , 1, 1, ' | D5: SECTIONS | E5: ', ' | F5: CREATE | G5: ', now()),
A6: ( | B6: 4 | C6: , 1, 1, ' | D6: SECTIONS | E6: ', ' | F6: CREATE | G6: ', now()),
A7: ( | B7: 5 | C7: , 1, 1, ' | D7: SECTIONS | E7: ', ' | F7: CREATE | G7: ', now()),
A8: ( | B8: 6 | C8: , 1, 1, ' | D8: SECTIONS | E8: ', ' | F8: CREATE | G8: ', now()),
A9: ( | B9: 7 | C9: , 1, 1, ' | D9: SECTIONS | E9: ', ' | F9: CREATE | G9: ', now()),
A10: ( | B10: 8 | C10: , 1, 1, ' | D10: SECTIONS | E10: ', ' | F10: CREATE | G10: ', now()),
A11: ( | B11: 9 | C11: , 1, 1, ' | D11: NODES | E11: ', ' | F11: CREATE | G11: ', now()),
A12: ( | B12: 10 | C12: , 1, 1, ' | D12: NODES | E12: ', ' | F12: CREATE | G12: ', now()),
A13: ( | B13: 11 | C13: , 1, 1, ' | D13: NODES | E13: ', ' | F13: CREATE | G13: ', now()),
A14: ( | B14: 12 | C14: , 1, 1, ' | D14: NODES | E14: ', ' | F14: CREATE | G14: ', now()),
... A4159: ( | B4159: 4157 | C4159: , 1, 1, ' | D4159: NODE_CONNECTIONS | E4159: ', ' | F4159: CREATE | G4159: ', now());

Sheet Скрипт sections
B1: INSERT INTO public.sections( name, kb_id, is_deleted, description, current_state, init_state)
C2: Имя секции | E2: Описание секции | G2: current_state | I2: init_state
A3: 1 | B3: (' | C3: Заболевания | D3: ', 1, false, ' | E3: Заболевания, которые необходимо диагностировать | F3: ', | G3: 1 | H3: , | I3: 1 | J3: ),
A4: 2 | B4: (' | C4: Жалобы | D4: ', 1, false, ' | E4: Жалобы, предъявляемые пациентом | F4: ', | G4: 2 | H4: , | I4: 2 | J4: ),
A5: 3 | B5: (' | C5: Общий осмотр | D5: ', 1, false, ' | E5: Признаки, полученные врачом в ходе общего осмотра | F5: ', | G5: 3 | H5: , | I5: 3 | J5: ),
A6: 4 | B6: (' | C6: Лабораторные методы обследования | D6: ', 1, false, ' | E6: Результаты лабораторных исследований | F6: ', | G6: 4 | H6: , | I6: 4 | J6: ),
A7: 5 | B7: (' | C7: Инструментальные методы обследования | D7: ', 1, false, ' | E7: Результаты инструментальных исследований | F7: ', | G7: 5 | H7: , | I7: 5 | J7: ),
A8: 6 | B8: (' | C8: Факторы риска | D8: ', 1, false, ' | E8: Факторы риска | F8: ', | G8: 6 | H8: , | I8: 6 | J8: ),
A9: 7 | B9: (' | C9: Риск заболевания | D9: ', 1, false, ' | E9: Наличие у пациента риска заболевания легких | F9: ', | G9: 7 | H9: , | I9: 7 | J9: ),
A10: 8 | B10: (' | C10: Синдромы и симптомокомплексы | D10: ', 1, false, ' | E10: Совокупность симптомов | F10: ', | G10: 8 | H10: , | I10: 8 | J10: );

Sheet Скрипт nodes
C1: INSERT INTO public.nodes( id, section_id, name, type, is_deleted, description, current_state, init_state)
D2: ID секции | F2: Имя узла | H2: Тип узла | J2: Метод | L2: Число | N2: Число
A3: ( | B3: 1 | C3: , | D3: 1 | E3: , ' | F3: ='Перечень узлов'!B2 -> Туберкулез | G3: ', ' | H3: ='Перечень узлов'!E2 -> TARGET_NODE | I3: ', false, ' | J3: ='Перечень узлов'!I2 -> A15, А16, A19 | K3: ', | L3: 9 | M3: , | N3: 9 | O3: ),
A4: ( | B4: 2 | C4: , | D4: 1 | E4: , ' | F4: ='Перечень узлов'!B3 -> Рак легких | G4: ', ' | H4: ='Перечень узлов'!E3 -> TARGET_NODE | I4: ', false, ' | J4: ='Перечень узлов'!I3 -> С34 | K4: ', | L4: 10 | M4: , | N4: 10 | O4: ),
A5: ( | B5: 3 | C5: , | D5: 1 | E5: , ' | F5: ='Перечень узлов'!B4 -> Вирусная пневмония | G5: ', ' | H5: ='Перечень узлов'!E4 -> TARGET_NODE | I5: ', false, ' | J5: ='Перечень узлов'!I4 -> J10, J12, U07 | K5: ', | L5: 11 | M5: , | N5: 11 | O5: ),
A6: ( | B6: 4 | C6: , | D6: 1 | E6: , ' | F6: ='Перечень узлов'!B5 -> Бактериальная пневмония | G6: ', ' | H6: ='Перечень узлов'!E5 -> TARGET_NODE | I6: ', false, ' | J6: ='Перечень узлов'!I5 -> J13 - J16, J18 | K6: ', | L6: 12 | M6: , | N6: 12 | O6: ),
A7: ( | B7: 5 | C7: , | D7: 7 | E7: , ' | F7: ='Перечень узлов'!B6 -> Повышенный риск туберкулеза | G7: ', ' | H7: ='Перечень узлов'!E6 -> TARGET_NODE | I7: ', false, ' | J7: ='Перечень узлов'!I6 -> null | K7: ', | L7: 13 | M7: , | N7: 13 | O7: ),
A8: ( | B8: 6 | C8: , | D8: 7 | E8: , ' | F8: ='Перечень узлов'!B7 -> Повышенный риск рака легкого | G8: ', ' | H8: ='Перечень узлов'!E7 -> TARGET_NODE | I8: ', false, ' | J8: ='Перечень узлов'!I7 -> null | K8: ', | L8: 14 | M8: , | N8: 14 | O8: ),
A9: ( | B9: 7 | C9: , | D9: 7 | E9: , ' | F9: ='Перечень узлов'!B8 -> Повышенный риск вирусной пневмонии | G9: ', ' | H9: ='Перечень узлов'!E8 -> TARGET_NODE | I9: ', false, ' | J9: ='Перечень узлов'!I8 -> null | K9: ', | L9: 15 | M9: , | N9: 15 | O9: ),
A10: ( | B10: 8 | C10: , | D10: 7 | E10: , ' | F10: ='Перечень узлов'!B9 -> Повышенный риск бактериальной пневмонии | G10: ', ' | H10: ='Перечень узлов'!E9 -> TARGET_NODE | I10: ', false, ' | J10: ='Перечень узлов'!I9 -> null | K10: ', | L10: 16 | M10: , | N10: 16 | O10: ),
A11: ( | B11: 9 | C11: , | D11: 2 | E11: , ' | F11: ='Перечень узлов'!B10 -> Продуктивный кашель | G11: ', ' | H11: ='Перечень узлов'!E10 -> FEATURE_NODE | I11: ', false, ' | J11: ='Перечень узлов'!I10 -> Опрос | K11: ', | L11: 17 | M11: , | N11: 17 | O11: ),
A12: ( | B12: 10 | C12: , | D12: 2 | E12: , ' | F12: ='Перечень узлов'!B11 -> Надсадный кашель | G12: ', ' | H12: ='Перечень узлов'!E11 -> FEATURE_NODE | I12: ', false, ' | J12: ='Перечень узлов'!I11 -> Опрос | K12: ', | L12: 18 | M12: , | N12: 18 | O12: ),
A13: ( | B13: 11 | C13: , | D13: 2 | E13: , ' | F13: ='Перечень узлов'!B12 -> Серозно-геморрагическая мокрота | G13: ', ' | H13: ='Перечень узлов'!E12 -> FEATURE_NODE | I13: ', false, ' | J13: ='Перечень узлов'!I12 -> Опрос | K13: ', | L13: 19 | M13: , | N13: 19 | O13: ),
A14: ( | B14: 12 | C14: , | D14: 2 | E14: , ' | F14: ='Перечень узлов'!B13 -> Слизисто-гнойная мокрота | G14: ', ' | H14: ='Перечень узлов'!E13 -> FEATURE_NODE | I14: ', false, ' | J14: ='Перечень узлов'!I13 -> Опрос | K14: ', | L14: 20 | M14: , | N14: 20 | O14: ),
... A693: ( | B693: 691 | C693: , | D693: 8 | E693: , ' | F693: ='Перечень узлов'!B692 -> Тромбоэмболия лёгочной артерии | G693: ', ' | H693: ='Перечень узлов'!E692 -> TARGET_NODE | I693: ', false, ' | J693: ='Перечень узлов'!I692 -> I26 | K693: ', | L693: 699 | M693: , | N693: 699 | O693: );

Sheet Скрипт node_connections
B1: INSERT INTO public.node_connections( id, from_node, to_node, connection_type, is_deleted, current_state, init_state)
D3: ОТ | F3: К | H3: ТИП СВЯЗИ | J3: число | L3: число | M3: ),
A4: ( | B4: 1 | C4: , | D4: =VLOOKUP('Установление связей'!B2,'Перечень узлов'!$B$2:$D$692,3,0) -> 299 | E4: , | F4: =VLOOKUP('Установление связей'!D2,'Перечень узлов'!$B$2:$D$692,3,0) -> 476 | G4: , ' | H4: =IF('Установление связей'!C2="может наблюдаться","RS",IF('Установление связей'!C2="всегда наблюдается","TRA",IF('Установление связей'!C2="может отсутствовать","SN","S"))) -> RS | I4: ', false, | J4: 700 | K4: , | L4: 700 | M4: ),
A5: ( | B5: 2 | C5: , | D5: =VLOOKUP('Установление связей'!B3,'Перечень узлов'!$B$2:$D$692,3,0) -> 299 | E5: , | F5: =VLOOKUP('Установление связей'!D3,'Перечень узлов'!$B$2:$D$692,3,0) -> 479 | G5: , ' | H5: =IF('Установление связей'!C3="может наблюдаться","RS",IF('Установление связей'!C3="всегда наблюдается","TRA",IF('Установление связей'!C3="может отсутствовать","SN","S"))) -> RS | I5: ', false, | J5: 701 | K5: , | L5: 701 | M5: ),
A6: ( | B6: 3 | C6: , | D6: =VLOOKUP('Установление связей'!B4,'Перечень узлов'!$B$2:$D$692,3,0) -> 299 | E6: , | F6: =VLOOKUP('Установление связей'!D4,'Перечень узлов'!$B$2:$D$692,3,0) -> 481 | G6: , ' | H6: =IF('Установление связей'!C4="может наблюдаться","RS",IF('Установление связей'!C4="всегда наблюдается","TRA",IF('Установление связей'!C4="может отсутствовать","SN","S"))) -> RS | I6: ', false, | J6: 702 | K6: , | L6: 702 | M6: ),
A7: ( | B7: 4 | C7: , | D7: =VLOOKUP('Установление связей'!B5,'Перечень узлов'!$B$2:$D$692,3,0) -> 299 | E7: , | F7: =VLOOKUP('Установление связей'!D5,'Перечень узлов'!$B$2:$D$692,3,0) -> 483 | G7: , ' | H7: =IF('Установление связей'!C5="может наблюдаться","RS",IF('Установление связей'!C5="всегда наблюдается","TRA",IF('Установление связей'!C5="может отсутствовать","SN","S"))) -> RS | I7: ', false, | J7: 703 | K7: , | L7: 703 | M7: ),
A8: ( | B8: 5 | C8: , | D8: =VLOOKUP('Установление связей'!B6,'Перечень узлов'!$B$2:$D$692,3,0) -> 236 | E8: , | F8: =VLOOKUP('Установление связей'!D6,'Перечень узлов'!$B$2:$D$692,3,0) -> 440 | G8: , ' | H8: =IF('Установление связей'!C6="может наблюдаться","RS",IF('Установление связей'!C6="всегда наблюдается","TRA",IF('Установление связей'!C6="может отсутствовать","SN","S"))) -> RS | I8: ', false, | J8: 704 | K8: , | L8: 704 | M8: ),
A9: ( | B9: 6 | C9: , | D9: =VLOOKUP('Установление связей'!B7,'Перечень узлов'!$B$2:$D$692,3,0) -> 236 | E9: , | F9: =VLOOKUP('Установление связей'!D7,'Перечень узлов'!$B$2:$D$692,3,0) -> 442 | G9: , ' | H9: =IF('Установление связей'!C7="может наблюдаться","RS",IF('Установление связей'!C7="всегда наблюдается","TRA",IF('Установление связей'!C7="может отсутствовать","SN","S"))) -> RS | I9: ', false, | J9: 705 | K9: , | L9: 705 | M9: ),
A10: ( | B10: 7 | C10: , | D10: =VLOOKUP('Установление связей'!B8,'Перечень узлов'!$B$2:$D$692,3,0) -> 236 | E10: , | F10: =VLOOKUP('Установление связей'!D8,'Перечень узлов'!$B$2:$D$692,3,0) -> 443 | G10: , ' | H10: =IF('Установление связей'!C8="может наблюдаться","RS",IF('Установление связей'!C8="всегда наблюдается","TRA",IF('Установление связей'!C8="может отсутствовать","SN","S"))) -> RS | I10: ', false, | J10: 706 | K10: , | L10: 706 | M10: ),
A11: ( | B11: 8 | C11: , | D11: =VLOOKUP('Установление связей'!B9,'Перечень узлов'!$B$2:$D$692,3,0) -> 13 | E11: , | F11: =VLOOKUP('Установление связей'!D9,'Перечень узлов'!$B$2:$D$692,3,0) -> 486 | G11: , ' | H11: =IF('Установление связей'!C9="может наблюдаться","RS",IF('Установление связей'!C9="всегда наблюдается","TRA",IF('Установление связей'!C9="может отсутствовать","SN","S"))) -> TRA | I11: ', false, | J11: 707 | K11: , | L11: 707 | M11: ),
A12: ( | B12: 9 | C12: , | D12: =VLOOKUP('Установление связей'!B10,'Перечень узлов'!$B$2:$D$692,3,0) -> 250 | E12: , | F12: =VLOOKUP('Установление связей'!D10,'Перечень узлов'!$B$2:$D$692,3,0) -> 281 | G12: , ' | H12: =IF('Установление связей'!C10="может наблюдаться","RS",IF('Установление связей'!C10="всегда наблюдается","TRA",IF('Установление связей'!C10="может отсутствовать","SN","S"))) -> TRA | I12: ', false, | J12: 708 | K12: , | L12: 708 | M12: ),
A13: ( | B13: 10 | C13: , | D13: =VLOOKUP('Установление связей'!B11,'Перечень узлов'!$B$2:$D$692,3,0) -> 215 | E13: , | F13: =VLOOKUP('Установление связей'!D11,'Перечень узлов'!$B$2:$D$692,3,0) -> 3 | G13: , ' | H13: =IF('Установление связей'!C11="может наблюдаться","RS",IF('Установление связей'!C11="всегда наблюдается","TRA",IF('Установление связей'!C11="может отсутствовать","SN","S"))) -> RS | I13: ', false, | J13: 709 | K13: , | L13: 709 | M13: ),
A14: ( | B14: 11 | C14: , | D14: =VLOOKUP('Установление связей'!B12,'Перечень узлов'!$B$2:$D$692,3,0) -> 118 | E14: , | F14: =VLOOKUP('Установление связей'!D12,'Перечень узлов'!$B$2:$D$692,3,0) -> 5 | G14: , ' | H14: =IF('Установление связей'!C12="может наблюдаться","RS",IF('Установление связей'!C12="всегда наблюдается","TRA",IF('Установление связей'!C12="может отсутствовать","SN","S"))) -> RS | I14: ', false, | J14: 710 | K14: , | L14: 710 | M14: ),
A15: ( | B15: 12 | C15: , | D15: =VLOOKUP('Установление связей'!B13,'Перечень узлов'!$B$2:$D$692,3,0) -> 139 | E15: , | F15: =VLOOKUP('Установление связей'!D13,'Перечень узлов'!$B$2:$D$692,3,0) -> 3 | G15: , ' | H15: =IF('Установление связей'!C13="может наблюдаться","RS",IF('Установление связей'!C13="всегда наблюдается","TRA",IF('Установление связей'!C13="может отсутствовать","SN","S"))) -> RS | I15: ', false, | J15: 711 | K15: , | L15: 711 | M15: ),
... A2473: ( | B2473: 2470 | C2473: , | D2473: =VLOOKUP('Установление связей'!B2471,'Перечень узлов'!$B$2:$D$692,3,0) -> 691 | E2473: , | F2473: =VLOOKUP('Установление связей'!D2471,'Перечень узлов'!$B$2:$D$692,3,0) -> 614 | G2473: , ' | H2473: =IF('Установление связей'!C2471="может наблюдаться","RS",IF('Установление связей'!C2471="всегда наблюдается","TRA",IF('Установление связей'!C2471="может отсутствовать","SN","S"))) -> RS | I2473: ', false, | J2473: 3169 | K2473: , | L2473: 3169 | M2473: );

Sheet Скрипт activation_condition
B1: INSERT INTO public.activation_conditions(
D2: id, name, label, kb_id, has_numeric_type, possible_numeric_range_start_point, include_start_point, possible_numeric_range_end_point, include_end_point, possible_string_values, possible_string_values_encoding, is_deleted, description, current_state, init_state)
D3: VALUES
A5: ( | B5: id | C5: , ' | D5: Дефекты контрастирования легочных артерий на КТ | E5: ', ' | F5: label | G5: ', | H5: kb_id | I5: , | J5: has_numeric_type | K5: , | L5: possible_numeric_range_start_point | M5: , | N5: include_start_point | O5: , | P5: possible_numeric_range_end_point | Q5: , | R5: include_end_point | S5: , '{ | T5: possible_string_values | U5: }', ' | V5: possible_string_values_encoding | W5: ', | X5: is_deleted | Y5: , ' | Z5: description | AA5: ', | AB5: current_state | AC5: , | AD5: init_state | AE5: ),
A6: ( | B6: 1 | C6: , ' | D6: Кашель отсутсвует | E6: ', ' | F6: cough_no | G6: ', | H6: 1 | I6: , | J6: false | K6: , | L6: null | M6: , | N6: null | O6: , | P6: null | Q6: , | R6: null | S6: , '{ | T6: 0.1 | U6: }', ' | V6: [ {"value":"0", "encoding":"нет"}, {"value":"1", "encoding":"есть"} ] | W6: ', | X6: false | Y6: , ' | Z6: Жалоба на кашель | AA6: ', | AB6: 3170 | AC6: , | AD6: 3170 | AE6: ),
A7: ( | B7: 2 | C7: , ' | D7: Кашель без уточнения | E7: ', ' | F7: cough_unspecified | G7: ', | H7: 1 | I7: , | J7: false | K7: , | L7: null | M7: , | N7: null | O7: , | P7: null | Q7: , | R7: null | S7: , '{ | T7: 0.1 | U7: }', ' | V7: [ {"value":"0", "encoding":"нет"}, {"value":"1", "encoding":"есть"} ] | W7: ', | X7: false | Y7: , ' | Z7: Жалоба на кашель | AA7: ', | AB7: 3171 | AC7: , | AD7: 3171 | AE7: ),
A8: ( | B8: 3 | C8: , ' | D8: Кашель непродуктивный | E8: ', ' | F8: cough_noproductive | G8: ', | H8: 1 | I8: , | J8: false | K8: , | L8: null | M8: , | N8: null | O8: , | P8: null | Q8: , | R8: null | S8: , '{ | T8: 0.1 | U8: }', ' | V8: [ {"value":"0", "encoding":"нет"}, {"value":"1", "encoding":"есть"} ] | W8: ', | X8: false | Y8: , ' | Z8: Жалоба на кашель | AA8: ', | AB8: 3172 | AC8: , | AD8: 3172 | AE8: ),
A9: ( | B9: 4 | C9: , ' | D9: Кашель малопродуктивный | E9: ', ' | F9: cough_unproductive | G9: ', | H9: 1 | I9: , | J9: false | K9: , | L9: null | M9: , | N9: null | O9: , | P9: null | Q9: , | R9: null | S9: , '{ | T9: 0.1 | U9: }', ' | V9: [ {"value":"0", "encoding":"нет"}, {"value":"1", "encoding":"есть"} ] | W9: ', | X9: false | Y9: , ' | Z9: Жалоба на кашель | AA9: ', | AB9: 3173 | AC9: , | AD9: 3173 | AE9: ),
A10: ( | B10: 5 | C10: , ' | D10: Кашель продуктивный | E10: ', ' | F10: cough_productive | G10: ', | H10: 1 | I10: , | J10: false | K10: , | L10: null | M10: , | N10: null | O10: , | P10: null | Q10: , | R10: null | S10: , '{ | T10: 0.1 | U10: }', ' | V10: [ {"value":"0", "encoding":"нет"}, {"value":"1", "encoding":"есть"} ] | W10: ', | X10: false | Y10: , ' | Z10: Жалоба на кашель | AA10: ', | AB10: 3174 | AC10: , | AD10: 3174 | AE10: ),
A11: ( | B11: 6 | C11: , ' | D11: Кашель надсадный | E11: ', ' | F11: cough_hacking | G11: ', | H11: 1 | I11: , | J11: false | K11: , | L11: null | M11: , | N11: null | O11: , | P11: null | Q11: , | R11: null | S11: , '{ | T11: 0.1 | U11: }', ' | V11: [ {"value":"0", "encoding":"нет"}, {"value":"1", "encoding":"есть"} ] | W11: ', | X11: false | Y11: , ' | Z11: Жалоба на кашель | AA11: ', | AB11: 3175 | AC11: , | AD11: 3175 | AE11: ),
A12: ( | B12: 7 | C12: , ' | D12: Кашель изнуряющий | E12: ', ' | F12: cough_debilitating | G12: ', | H12: 1 | I12: , | J12: false | K12: , | L12: null | M12: , | N12: null | O12: , | P12: null | Q12: , | R12: null | S12: , '{ | T12: 0.1 | U12: }', ' | V12: [ {"value":"0", "encoding":"нет"}, {"value":"1", "encoding":"есть"} ] | W12: ', | X12: false | Y12: , ' | Z12: Жалоба на кашель | AA12: ', | AB12: 3176 | AC12: , | AD12: 3176 | AE12: ),
A13: ( | B13: 8 | C13: , ' | D13: Кашель с примесью крови | E13: ', ' | F13: cough_blood | G13: ', | H13: 1 | I13: , | J13: false | K13: , | L13: null | M13: , | N13: null | O13: , | P13: null | Q13: , | R13: null | S13: , '{ | T13: 0.1 | U13: }', ' | V13: [ {"value":"0", "encoding":"нет"}, {"value":"1", "encoding":"есть"} ] | W13: ', | X13: false | Y13: , ' | Z13: Жалоба на кашель | AA13: ', | AB13: 3177 | AC13: , | AD13: 3177 | AE13: ),
A14: ( | B14: 9 | C14: , ' | D14: Температура тела | E14: ', ' | F14: temperature | G14: ', | H14: 1 | I14: , | J14: true | K14: , | L14: 27.00 | M14: , | N14: true | O14: , | P14: 46.50 | Q14: , | R14: null | S14: , | T14: null | U14: , | V14: null | W14: , | X14: false | Y14: , ' | Z14: Температура тела пациента Есть значения в витальных параметрах | AA14: ', | AB14: 3178 | AC14: , | AD14: 3178 | AE14: ),
A15: ( | B15: 10 | C15: , ' | D15: Мокрота | E15: ', ' | F15: sputum | G15: ', | H15: 1 | I15: , | J15: false | K15: , | L15: null | M15: , | N15: null | O15: , | P15: null | Q15: , | R15: null | S15: , '{ | T15: 0.7 | U15: }', ' | V15: [ {"value":"0", "encoding":"без уточнения"}, {"value":"1", "encoding":"слизистая"}, {"value":"2", "encoding":"серозная"}, {"value":"3", "encoding":"слизисто-гнойная"}, {"value":"4", "encoding":"гнойная"}, {"value":"5", "encoding":"ржавая мокрота"}, {"value":"6", "encoding":"серозно-геморрагическая мокрота"}, {"value":"7", "encoding":"кровавая мокрота"} ] | W15: ', | X15: false | Y15: , ' | Z15: Характер мокроты | AA15: ', | AB15: 3179 | AC15: , | AD15: 3179 | AE15: ),
A16: ( | B16: 11 | C16: , ' | D16: Боль в грудной клетке | E16: ', ' | F16: chest_pain | G16: ', | H16: 1 | I16: , | J16: false | K16: , | L16: null | M16: , | N16: null | O16: , | P16: null | Q16: , | R16: null | S16: , '{ | T16: 0.1 | U16: }', ' | V16: [ {"value":"0", "encoding":"нет"}, {"value":"1", "encoding":"есть"} ] | W16: ', | X16: false | Y16: , ' | Z16: Боль в грудной клетке | AA16: ', | AB16: 3180 | AC16: , | AD16: 3180 | AE16: ),
A17: ( | B17: 12 | C17: , ' | D17: Артралгия | E17: ', ' | F17: arthralgia | G17: ', | H17: 1 | I17: , | J17: false | K17: , | L17: null | M17: , | N17: null | O17: , | P17: null | Q17: , | R17: null | S17: , '{ | T17: 0.1 | U17: }', ' | V17: [ {"value":"0", "encoding":"нет"}, {"value":"1", "encoding":"есть"} ] | W17: ', | X17: false | Y17: , ' | Z17: Боль в суставах | AA17: ', | AB17: 3181 | AC17: , | AD17: 3181 | AE17: ),
A18: ( | B18: 13 | C18: , ' | D18: Миалгия | E18: ', ' | F18: myalgia | G18: ', | H18: 1 | I18: , | J18: false | K18: , | L18: null | M18: , | N18: null | O18: , | P18: null | Q18: , | R18: null | S18: , '{ | T18: 0.1 | U18: }', ' | V18: [ {"value":"0", "encoding":"нет"}, {"value":"1", "encoding":"есть"} ] | W18: ', | X18: false | Y18: , ' | Z18: Боль в мышцах | AA18: ', | AB18: 3182 | AC18: , | AD18: 3182 | AE18: ),
A19: ( | B19: 14 | C19: , ' | D19: Оссалгия | E19: ', ' | F19: ossalgia | G19: ', | H19: 1 | I19: , | J19: false | K19: , | L19: null | M19: , | N19: null | O19: , | P19: null | Q19: , | R19: null | S19: , '{ | T19: 0.1 | U19: }', ' | V19: [ {"value":"0", "encoding":"нет"}, {"value":"1", "encoding":"есть"} ] | W19: ', | X19: false | Y19: , ' | Z19: Боль в костях | AA19: ', | AB19: 3183 | AC19: , | AD19: 3183 | AE19: ),
A20: ( | B20: 15 | C20: , ' | D20: Боль в глазных яблоках | E20: ', ' | F20: eyeballs_pain | G20: ', | H20: 1 | I20: , | J20: false | K20: , | L20: null | M20: , | N20: null | O20: , | P20: null | Q20: , | R20: null | S20: , '{ | T20: 0.1 | U20: }', ' | V20: [ {"value":"0", "encoding":"нет"}, {"value":"1", "encoding":"есть"} ] | W20: ', | X20: false | Y20: , ' | Z20: Боль в глазных яблоках | AA20: ', | AB20: 3184 | AC20: , | AD20: 3184 | AE20: ),
A21: ( | B21: 16 | C21: , ' | D21: Конъюнктивит | E21: ', ' | F21: conjunctivitis | G21: ', | H21: 1 | I21: , | J21: false | K21: , | L21: null | M21: , | N21: null | O21: , | P21: null | Q21: , | R21: null | S21: , '{ | T21: 0.1 | U21: }', ' | V21: [ {"value":"0", "encoding":"нет"}, {"value":"1", "encoding":"есть"} ] | W21: ', | X21: false | Y21: , ' | Z21: Конъюнктивит | AA21: ', | AB21: 3185 | AC21: , | AD21: 3185 | AE21: ),
A22: ( | B22: 17 | C22: , ' | D22: Головная боль | E22: ', ' | F22: headache | G22: ', | H22: 1 | I22: , | J22: false | K22: , | L22: null | M22: , | N22: null | O22: , | P22: null | Q22: , | R22: null | S22: , '{ | T22: 0.1 | U22: }', ' | V22: [ {"value":"0", "encoding":"нет"}, {"value":"1", "encoding":"есть"} ] | W22: ', | X22: false | Y22: , ' | Z22: Головная боль | AA22: ', | AB22: 3186 | AC22: , | AD22: 3186 | AE22: ),
A23: ( | B23: 18 | C23: , ' | D23: Боль в плечевом суставе | E23: ', ' | F23: shoulder_joint_pain | G23: ', | H23: 1 | I23: , | J23: false | K23: , | L23: null | M23: , | N23: null | O23: , | P23: null | Q23: , | R23: null | S23: , '{ | T23: 0.1 | U23: }', ' | V23: [ {"value":"0", "encoding":"нет"}, {"value":"1", "encoding":"есть"} ] | W23: ', | X23: false | Y23: , ' | Z23: Боль в плечевом суставе | AA23: ', | AB23: 3187 | AC23: , | AD23: 3187 | AE23: ),
A24: ( | B24: 19 | C24: , ' | D24: Боль в плече | E24: ', ' | F24: shoulder_pain | G24: ', | H24: 1 | I24: , | J24: false | K24: , | L24: null | M24: , | N24: null | O24: , | P24: null | Q24: , | R24: null | S24: , '{ | T24: 0.1 | U24: }', ' | V24: [ {"value":"0", "encoding":"нет"}, {"value":"1", "encoding":"есть"} ] | W24: ', | X24: false | Y24: , ' | Z24: Боль в плече | AA24: ', | AB24: 3188 | AC24: , | AD24: 3188 | AE24: ),
A25: ( | B25: 20 | C25: , ' | D25: Атрофия мышц предплечья | E25: ', ' | F25: muscles_forearm_atrophy | G25: ', | H25: 1 | I25: , | J25: false | K25: , | L25: null | M25: , | N25: null | O25: , | P25: null | Q25: , | R25: null | S25: , '{ | T25: 0.1 | U25: }', ' | V25: [ {"value":"0", "encoding":"нет"}, {"value":"1", "encoding":"есть"} ] | W25: ', | X25: false | Y25: , ' | Z25: Атрофия мышц предплечья | AA25: ', | AB25: 3189 | AC25: , | AD25: 3189 | AE25: ),
A26: ( | B26: 21 | C26: , ' | D26: Голос | E26: ', ' | F26: voice | G26: ', | H26: 1 | I26: , | J26: false | K26: , | L26: null | M26: , | N26: null | O26: , | P26: null | Q26: , | R26: null | S26: , '{ | T26: 0.4 | U26: }', ' | V26: [ {"value":"0", "encoding":"нормальный"}, {"value":"1", "encoding":"осиплый"}, {"value":"2", "encoding":"охриплый"}, {"value":"3", "encoding":"тихий"}, {"value":"4", "encoding":"потерян"} ] | W26: ', | X26: false | Y26: , ' | Z26: Голос | AA26: ', | AB26: 3190 | AC26: , | AD26: 3190 | AE26: ),
... A62: ( | B62: 57 | C62: , ' | D62: Контакт с больными туберкулезом в анамнезе | E62: ', ' | F62: contact_with_tuberculosis_patients_anamnez | G62: ', | H62: 1 | I62: , | J62: false | K62: , | L62: null | M62: , | N62: null | O62: , | P62: null | Q62: , | R62: null | S62: , '{ | T62: 0.1 | U62: }', ' | V62: [ {"value":"0", "encoding":"нет"}, {"value":"1", "encoding":"есть"} ] | W62: ', | X62: false | Y62: , | Z62: null | AA62: , | AB62: 3226 | AC62: , | AD62: 3226 | AE62: ),
A63: ( | B63: 58 | C63: , ' | D63: Возраст | E63: ', ' | F63: age | G63: ', | H63: 1 | I63: , | J63: true | K63: , | L63: 0 | M63: , | N63: true | O63: , | P63: 120 | Q63: , | R63: true | S63: , | T63: null | U63: , | V63: null | W63: , | X63: false | Y63: , | Z63: null | AA63: , | AB63: 3227 | AC63: , | AD63: 3227 | AE63: ),
A64: ( | B64: 59 | C64: , ' | D64: Курение в анамнезе | E64: ', ' | F64: smoking_anamnez | G64: ', | H64: 1 | I64: , | J64: false | K64: , | L64: null | M64: , | N64: null | O64: , | P64: null | Q64: , | R64: null | S64: , '{ | T64: 0.1 | U64: }', ' | V64: [ {"value":"0", "encoding":"нет"}, {"value":"1", "encoding":"есть"} ] | W64: ', | X64: false | Y64: , | Z64: null | AA64: , | AB64: 3228 | AC64: , | AD64: 3228 | AE64: ),
A65: ( | B65: 60 | C65: , ' | D65: ВИЧ-инфекция в анамнезе | E65: ', ' | F65: HIV_infection_anamnez | G65: ', | H65: 1 | I65: , | J65: false | K65: , | L65: null | M65: , | N65: null | O65: , | P65: null | Q65: , | R65: null | S65: , '{ | T65: 0.1 | U65: }', ' | V65: [ {"value":"0", "encoding":"нет"}, {"value":"1", "encoding":"есть"} ] | W65: ', | X65: false | Y65: , | Z65: null | AA65: , | AB65: 3229 | AC65: , | AD65: 3229 | AE65: ),
A66: ( | B66: 61 | C66: , ' | D66: Вдыхание радона в концентрации >4 пкюри/л | E66: ', ' | F66: radon_concentrations | G66: ', | H66: 1 | I66: , | J66: false | K66: , | L66: null | M66: , | N66: null | O66: , | P66: null | Q66: , | R66: null | S66: , '{ | T66: 0.1 | U66: }', ' | V66: [ {"value":"0", "encoding":"нет"}, {"value":"1", "encoding":"есть"} ] | W66: ', | X66: false | Y66: , | Z66: null | AA66: , | AB66: 3230 | AC66: , | AD66: 3230 | AE66: ),
A67: ( | B67: 62 | C67: , ' | D67: Работа в отрасли газификации и коксовании | E67: ', ' | F67: work_gasification_and_coking_industry | G67: ', | H67: 1 | I67: , | J67: false | K67: , | L67: null | M67: , | N67: null | O67: , | P67: null | Q67: , | R67: null | S67: , '{ | T67: 0.1 | U67: }', ' | V67: [ {"value":"0", "encoding":"нет"}, {"value":"1", "encoding":"есть"} ] | W67: ', | X67: false | Y67: , | Z67: null | AA67: , | AB67: 3231 | AC67: , | AD67: 3231 | AE67: ),
A68: ( | B68: 63 | C68: , ' | D68: Работа в отрасли алюминиевой промышленности | E68: ', ' | F68: working_aluminum_industry | G68: ', | H68: 1 | I68: , | J68: false | K68: , | L68: null | M68: , | N68: null | O68: , | P68: null | Q68: , | R68: null | S68: , '{ | T68: 0.1 | U68: }', ' | V68: [ {"value":"0", "encoding":"нет"}, {"value":"1", "encoding":"есть"} ] | W68: ', | X68: false | Y68: , | Z68: null | AA68: , | AB68: 3232 | AC68: , | AD68: 3232 | AE68: ),
A69: ( | B69: 64 | C69: , ' | D69: Работа в отрасли добычи гематита | E69: ', ' | F69: working_hematite_mining_industry | G69: ', | H69: 1 | I69: , | J69: false | K69: , | L69: null | M69: , | N69: null | O69: , | P69: null | Q69: , | R69: null | S69: , '{ | T69: 0.1 | U69: }', ' | V69: [ {"value":"0", "encoding":"нет"}, {"value":"1", "encoding":"есть"} ] | W69: ', | X69: false | Y69: , | Z69: null | AA69: , | AB69: 3233 | AC69: , | AD69: 3233 | AE69: ),
A70: ( | B70: 65 | C70: , ' | D70: Работа в отрасли литейной промышленности | E70: ', ' | F70: working_foundry_industry | G70: ', | H70: 1 | I70: , | J70: false | K70: , | L70: null | M70: , | N70: null | O70: , | P70: null | Q70: , | R70: null | S70: , '{ | T70: 0.1 | U70: }', ' | V70: [ {"value":"0", "encoding":"нет"}, {"value":"1", "encoding":"есть"} ] | W70: ', | X70: false | Y70: , | Z70: null | AA70: , | AB70: 3234 | AC70: , | AD70: 3234 | AE70: ),
A71: ( | B71: 66 | C71: , ' | D71: Работа в отрасли производства изопропилового спирта | E71: ', ' | F71: working_isopropyl_alcohol_industry | G71: ', | H71: 1 | I71: , | J71: false | K71: , | L71: null | M71: , | N71: null | O71: , | P71: null | Q71: , | R71: null | S71: , '{ | T71: 0.1 | U71: }', ' | V71: [ {"value":"0", "encoding":"нет"}, {"value":"1", "encoding":"есть"} ] | W71: ', | X71: false | Y71: , | Z71: null | AA71: , | AB71: 3235 | AC71: , | AD71: 3235 | AE71: ),
A72: ( | B72: 67 | C72: , ' | D72: Работа в отрасли производства фуксина | E72: ', ' | F72: working_fuchsin_industry | G72: ', | H72: 1 | I72: , | J72: false | K72: , | L72: null | M72: , | N72: null | O72: , | P72: null | Q72: , | R72: null | S72: , '{ | T72: 0.1 | U72: }', ' | V72: [ {"value":"0", "encoding":"нет"}, {"value":"1", "encoding":"есть"} ] | W72: ', | X72: false | Y72: , | Z72: null | AA72: , | AB72: 3236 | AC72: , | AD72: 3236 | AE72: ),
A73: ( | B73: 68 | C73: , ' | D73: Работа в отрасли резиновой промышленности | E73: ', ' | F73: working_rubber_industry | G73: ', | H73: 1 | I73: , | J73: false | K73: , | L73: null | M73: , | N73: null | O73: , | P73: null | Q73: , | R73: null | S73: , '{ | T73: 0.1 | U73: }', ' | V73: [ {"value":"0", "encoding":"нет"}, {"value":"1", "encoding":"есть"} ] | W73: ', | X73: false | Y73: , | Z73: null | AA73: , | AB73: 3237 | AC73: , | AD73: 3237 | AE73: ),
A74: ( | B74: 69 | C74: , ' | D74: Постоянный контакт с асбестом | E74: ', ' | F74: constant_contact_with_asbestos | G74: ', | H74: 1 | I74: , | J74: false | K74: , | L74: null | M74: , | N74: null | O74: , | P74: null | Q74: , | R74: null | S74: , '{ | T74: 0.1 | U74: }', ' | V74: [ {"value":"0", "encoding":"нет"}, {"value":"1", "encoding":"есть"} ] | W74: ', | X74: false | Y74: , | Z74: null | AA74: , | AB74: 3238 | AC74: , | AD74: 3238 | AE74: ),
A75: ( | B75: 70 | C75: , ' | D75: Постоянный контакт с бериллием | E75: ', ' | F75: constant_contact_with_beryllium | G75: ', | H75: 1 | I75: , | J75: false | K75: , | L75: null | M75: , | N75: null | O75: , | P75: null | Q75: , | R75: null | S75: , '{ | T75: 0.1 | U75: }', ' | V75: [ {"value":"0", "encoding":"нет"}, {"value":"1", "encoding":"есть"} ] | W75: ', | X75: false | Y75: , | Z75: null | AA75: , | AB75: 3239 | AC75: , | AD75: 3239 | AE75: ),
... A135: ( | B135: 130 | C135: , ' | D135: Чувство нехватки воздуха | E135: ', ' | F135: Feeling short of air | G135: ', | H135: 1 | I135: , | J135: false | K135: , | L135: null | M135: , | N135: null | O135: , | P135: null | Q135: , | R135: null | S135: , '{ | T135: 0.1 | U135: }', ' | V135: [ {"value":"0", "encoding":"нет"}, {"value":"1", "encoding":"есть"} ] | W135: ', | X135: false | Y135: , | Z135: null | AA135: , | AB135: 3299 | AC135: , | AD135: 3299 | AE135: ),
A136: ( | B136: 131 | C136: , ' | D136: Сатурация крови кислородом при пульсоксиметрии, % | E136: ', ' | F136: blood_oxygen_saturation | G136: ', | H136: 1 | I136: , | J136: true | K136: , | L136: 30.00 | M136: , | N136: true | O136: , | P136: 100.00 | Q136: , | R136: true | S136: , | T136: null | U136: , | V136: null | W136: , | X136: false | Y136: , ' | Z136: Есть в витальных параметрах и Инструментальных исследованиях | AA136: ', | AB136: 3300 | AC136: , | AD136: 3300 | AE136: ),
A137: ( | B137: 132 | C137: , ' | D137: Увеличение шейных лимфоузлов при пальпации | E137: ', ' | F137: enlarged_cervical_lymph_nodes_upon_palpation | G137: ', | H137: 1 | I137: , | J137: false | K137: , | L137: null | M137: , | N137: null | O137: , | P137: null | Q137: , | R137: null | S137: , '{ | T137: 0.1 | U137: }', ' | V137: [ {"value":"0", "encoding":"нет"}, {"value":"1", "encoding":"есть"} ] | W137: ', | X137: false | Y137: , ' | Z137: Физикальные параметры - Результаты пальпации лимфатических узлов | AA137: ', | AB137: 3301 | AC137: , | AD137: 3301 | AE137: ),
A138: ( | B138: 133 | C138: , ' | D138: Увеличение лимфоузлов при пальпации | E138: ', ' | F138: enlarged_lymph_nodes_upon_palpation | G138: ', | H138: 1 | I138: , | J138: false | K138: , | L138: null | M138: , | N138: null | O138: , | P138: null | Q138: , | R138: null | S138: , '{ | T138: 0.1 | U138: }', ' | V138: [ {"value":"0", "encoding":"нет"}, {"value":"1", "encoding":"есть"} ] | W138: ', | X138: false | Y138: , | Z138: null | AA138: , | AB138: 3302 | AC138: , | AD138: 3302 | AE138: ),
A139: ( | B139: 134 | C139: , ' | D139: Болезненность шейных лимфоузлов при пальпации | E139: ', ' | F139: soreness_cervical_lymph_nodes_palpation | G139: ', | H139: 1 | I139: , | J139: false | K139: , | L139: null | M139: , | N139: null | O139: , | P139: null | Q139: , | R139: null | S139: , '{ | T139: 0.1 | U139: }', ' | V139: [ {"value":"0", "encoding":"нет"}, {"value":"1", "encoding":"есть"} ] | W139: ', | X139: false | Y139: , | Z139: null | AA139: , | AB139: 3303 | AC139: , | AD139: 3303 | AE139: ),
A140: ( | B140: 135 | C140: , ' | D140: Тахипноэ | E140: ', ' | F140: tachypnea | G140: ', | H140: 1 | I140: , | J140: false | K140: , | L140: null | M140: , | N140: null | O140: , | P140: null | Q140: , | R140: null | S140: , '{ | T140: 0.1 | U140: }', ' | V140: [ {"value":"0", "encoding":"нет"}, {"value":"1", "encoding":"есть"} ] | W140: ', | X140: false | Y140: , ' | Z140: анамнез заболевания, если ЧДД (Частота дыхания) > 20, то тахипноэ | AA140: ', | AB140: 3304 | AC140: , | AD140: 3304 | AE140: ),
A141: ( | B141: 136 | C141: , ' | D141: Пневмофиброз на КТ ОГК | E141: ', ' | F141: pneumofibrosis_CT_OGK | G141: ', | H141: 1 | I141: , | J141: false | K141: , | L141: null | M141: , | N141: null | O141: , | P141: null | Q141: , | R141: null | S141: , '{ | T141: 0.1 | U141: }', ' | V141: [ {"value":"0", "encoding":"нет"}, {"value":"1", "encoding":"есть"} ] | W141: ', | X141: false | Y141: , | Z141: null | AA141: , | AB141: 3305 | AC141: , | AD141: 3305 | AE141: ),
A142: ( | B142: 137 | C142: , ' | D142: Эмфизема на КТ ОГК | E142: ', ' | F142: emphysema_CT_OGK | G142: ', | H142: 1 | I142: , | J142: false | K142: , | L142: null | M142: , | N142: null | O142: , | P142: null | Q142: , | R142: null | S142: , '{ | T142: 0.1 | U142: }', ' | V142: [ {"value":"0", "encoding":"нет"}, {"value":"1", "encoding":"есть"} ] | W142: ', | X142: false | Y142: , | Z142: null | AA142: , | AB142: 3306 | AC142: , | AD142: 3306 | AE142: ),
A143: ( | B143: 138 | C143: , ' | D143: Кальцинированные очаги в легких на рентгенограмме | E143: ', ' | F143: calcified_lesions_lungs_x-ray | G143: ', | H143: 1 | I143: , | J143: false | K143: , | L143: null | M143: , | N143: null | O143: , | P143: null | Q143: , | R143: null | S143: , '{ | T143: 0.1 | U143: }', ' | V143: [ {"value":"0", "encoding":"нет"}, {"value":"1", "encoding":"есть"} ] | W143: ', | X143: false | Y143: , | Z143: null | AA143: , | AB143: 3307 | AC143: , | AD143: 3307 | AE143: ),
A144: ( | B144: 139 | C144: , ' | D144: Кальцинированные очаги во внутригрудных лимфатических узлах на рентгенограмме | E144: ', ' | F144: calcified_lesions_hilar_lymph_nodes_x-ray | G144: ', | H144: 1 | I144: , | J144: false | K144: , | L144: null | M144: , | N144: null | O144: , | P144: null | Q144: , | R144: null | S144: , '{ | T144: 0.1 | U144: }', ' | V144: [ {"value":"0", "encoding":"нет"}, {"value":"1", "encoding":"есть"} ] | W144: ', | X144: false | Y144: , | Z144: null | AA144: , | AB144: 3308 | AC144: , | AD144: 3308 | AE144: ),
A145: ( | B145: 140 | C145: , ' | D145: Положительный ТБ-фероновый тест | E145: ', ' | F145: positive_TB-feron_test | G145: ', | H145: 1 | I145: , | J145: false | K145: , | L145: null | M145: , | N145: null | O145: , | P145: null | Q145: , | R145: null | S145: , '{ | T145: 0.1 | U145: }', ' | V145: [ {"value":"0", "encoding":"нет"}, {"value":"1", "encoding":"есть"} ] | W145: ', | X145: false | Y145: , | Z145: null | AA145: , | AB145: 3309 | AC145: , | AD145: 3309 | AE145: ),
A146: ( | B146: 141 | C146: , ' | D146: Положительный T-SPOT тест | E146: ', ' | F146: positive_T-SPOT_test | G146: ', | H146: 1 | I146: , | J146: false | K146: , | L146: null | M146: , | N146: null | O146: , | P146: null | Q146: , | R146: null | S146: , '{ | T146: 0.1 | U146: }', ' | V146: [ {"value":"0", "encoding":"нет"}, {"value":"1", "encoding":"есть"} ] | W146: ', | X146: false | Y146: , | Z146: null | AA146: , | AB146: 3310 | AC146: , | AD146: 3310 | AE146: ),
A147: ( | B147: 142 | C147: , ' | D147: Наличие ДНК МБТ в мокроте (GeneXpert MTB/RIF) | E147: ', ' | F147: presence_MTB_DNA_sputum_(GeneXpert_MTB_RIF) | G147: ', | H147: 1 | I147: , | J147: false | K147: , | L147: null | M147: , | N147: null | O147: , | P147: null | Q147: , | R147: null | S147: , '{ | T147: 0.1 | U147: }', ' | V147: [ {"value":"0", "encoding":"нет"}, {"value":"1", "encoding":"есть"} ] | W147: ', | X147: false | Y147: , | Z147: null | AA147: , | AB147: 3311 | AC147: , | AD147: 3311 | AE147: ),
A148: ( | B148: 143 | C148: , ' | D148: Положительный результат квантиферонового теста | E148: ', ' | F148: positive_quantiferon_test | G148: ', | H148: 1 | I148: , | J148: false | K148: , | L148: null | M148: , | N148: null | O148: , | P148: null | Q148: , | R148: null | S148: , '{ | T148: 0.1 | U148: }', ' | V148: [ {"value":"0", "encoding":"нет"}, {"value":"1", "encoding":"есть"} ] | W148: ', | X148: false | Y148: , | Z148: null | AA148: , | AB148: 3312 | AC148: , | AD148: 3312 | AE148: ),
... A172: ( | B172: 167 | C172: , ' | D172: Наличие бактерий при культуральном исследовании плевральной жидкости | E172: ', ' | F172: bacteria_pleural_fluid_culture | G172: ', | H172: 1 | I172: , | J172: false | K172: , | L172: null | M172: , | N172: null | O172: , | P172: null | Q172: , | R172: null | S172: , '{ | T172: 0.1 | U172: }', ' | V172: [ {"value":"0", "encoding":"нет"}, {"value":"1", "encoding":"есть"} ] | W172: ', | X172: false | Y172: , | Z172: null | AA172: , | AB172: 3336 | AC172: , | AD172: 3336 | AE172: ),
A173: ( | B173: 168 | C173: , ' | D173: Уровень СРБ (мг/л) | E173: ', ' | F173: CRP_level | G173: ', | H173: 1 | I173: , | J173: true | K173: , | L173: 0.00 | M173: , | N173: true | O173: , | P173: 1000.00 | Q173: , | R173: true | S173: , | T173: null | U173: , | V173: null | W173: , | X173: false | Y173: , ' | Z173: Анализ крови развернутый - C-реактивный белок, массовая концентрация в сыворотке или плазме крови C-реактивный белок, обнаружение в сыворотке или плазме крови Анализ крови биохимический - C-реактивный белок, массовая концентрация в сыворотке или плазме крови Уровня С-реактивного белка | AA173: ', | AB173: 3337 | AC173: , | AD173: 3337 | AE173: ),
A174: ( | B174: 169 | C174: , ' | D174: Уровень прокальцитонина (мкг/л) | E174: ', ' | F174: procalcitonin | G174: ', | H174: 1 | I174: , | J174: true | K174: , | L174: 0.00 | M174: , | N174: true | O174: , | P174: 100.00 | Q174: , | R174: true | S174: , | T174: null | U174: , | V174: null | W174: , | X174: false | Y174: , ' | Z174: Анализ крови биохимический - Прокальцитонин, массовая концентрация в сыворотке или плазме крови Прокальцитонин, массовая концентрация в сыворотке или плазме крови иммунологическим методом | AA174: ', | AB174: 3338 | AC174: , | AD174: 3338 | AE174: ),
A175: ( | B175: 170 | C175: , ' | D175: Уровень фибриногена (г/л) | E175: ', ' | F175: fibrinogen | G175: ', | H175: 1 | I175: , | J175: true | K175: , | L175: 0.1 | M175: , | N175: true | O175: , | P175: 1000.00 | Q175: , | R175: true | S175: , | T175: null | U175: , | V175: null | W175: , | X175: false | Y175: , ' | Z175: Анализ крови биохимический - Фибриноген по Клауссу в бедной тромбоцитами плазме Коагулограмма - Фибриноген расчетный в бедной тромбоцитами плазме Фибриноген по Клауссу в бедной тромбоцитами плазме Уровня фрибиногена - Фибриноген расчетный в бедной тромбоцитами плазме | AA175: ', | AB175: 3339 | AC175: , | AD175: 3339 | AE175: ),
A176: ( | B176: 171 | C176: , ' | D176: Диурез снижен | E176: ', ' | F176: diuresis_reduced | G176: ', | H176: 1 | I176: , | J176: false | K176: , | L176: null | M176: , | N176: null | O176: , | P176: null | Q176: , | R176: null | S176: , '{ | T176: 0.1 | U176: }', ' | V176: [ {"value":"0", "encoding":"нет"}, {"value":"1", "encoding":"есть"} ] | W176: ', | X176: false | Y176: , ' | Z176: Пока везде пишут, что он в норме | AA176: ', | AB176: 3340 | AC176: , | AD176: 3340 | AE176: ),
A177: ( | B177: 172 | C177: , ' | D177: Тромбоциты (*10^9/л) | E177: ', ' | F177: platelets | G177: ', | H177: 1 | I177: , | J177: true | K177: , | L177: 1.00 | M177: , | N177: true | O177: , | P177: 1000.00 | Q177: , | R177: true | S177: , | T177: null | U177: , | V177: null | W177: , | X177: false | Y177: , | Z177: null | AA177: , | AB177: 3341 | AC177: , | AD177: 3341 | AE177: ),
A178: ( | B178: 173 | C178: , ' | D178: СОЭ (мм/ч) | E178: ', ' | F178: ESR | G178: ', | H178: 1 | I178: , | J178: true | K178: , | L178: 1.00 | M178: , | N178: true | O178: , | P178: 50.00 | Q178: , | R178: true | S178: , | T178: null | U178: , | V178: null | W178: , | X178: false | Y178: , | Z178: null | AA178: , | AB178: 3342 | AC178: , | AD178: 3342 | AE178: ),
A179: ( | B179: 174 | C179: , ' | D179: Лейкоциты при поступлении (*10^9/л) | E179: ', ' | F179: leukocytes_ar | G179: ', | H179: 1 | I179: , | J179: true | K179: , | L179: 0.10 | M179: , | N179: true | O179: , | P179: 100.00 | Q179: , | R179: true | S179: , | T179: null | U179: , | V179: null | W179: , | X179: false | Y179: , ' | Z179: Не известно что значение получено при поступлении | AA179: ', | AB179: 3343 | AC179: , | AD179: 3343 | AE179: ),
A180: ( | B180: 175 | C180: , ' | D180: Положительный результат количественного ИФА крови на противотуберкулезные АТ | E180: ', ' | F180: positive_quantitative_blood_ELISA_anti-tuberculosis_antibodies | G180: ', | H180: 1 | I180: , | J180: false | K180: , | L180: null | M180: , | N180: null | O180: , | P180: null | Q180: , | R180: null | S180: , '{ | T180: 0.1 | U180: }', ' | V180: [ {"value":"0", "encoding":"нет"}, {"value":"1", "encoding":"есть"} ] | W180: ', | X180: false | Y180: , | Z180: null | AA180: , | AB180: 3344 | AC180: , | AD180: 3344 | AE180: ),
A181: ( | B181: 176 | C181: , ' | D181: Лимфоциты (%) | E181: ', ' | F181: lymphocytes | G181: ', | H181: 1 | I181: , | J181: true | K181: , | L181: 0.00 | M181: , | N181: true | O181: , | P181: 100.00 | Q181: , | R181: true | S181: , | T181: null | U181: , | V181: null | W181: , | X181: false | Y181: , | Z181: null | AA181: , | AB181: 3345 | AC181: , | AD181: 3345 | AE181: ),
A182: ( | B182: 177 | C182: , ' | D182: Лимфоциты (*10^9/л) | E182: ', ' | F182: absolute_lymphocytosis | G182: ', | H182: 1 | I182: , | J182: true | K182: , | L182: 0.00 | M182: , | N182: false | O182: , | P182: 100.00 | Q182: , | R182: true | S182: , | T182: null | U182: , | V182: null | W182: , | X182: false | Y182: , | Z182: null | AA182: , | AB182: 3346 | AC182: , | AD182: 3346 | AE182: ),
A183: ( | B183: 178 | C183: , ' | D183: Моноциты (%) | E183: ', ' | F183: monocytes | G183: ', | H183: 1 | I183: , | J183: true | K183: , | L183: 0.00 | M183: , | N183: true | O183: , | P183: 100.00 | Q183: , | R183: true | S183: , | T183: null | U183: , | V183: null | W183: , | X183: false | Y183: , ' | Z183: Норма 3-12 % | AA183: ', | AB183: 3347 | AC183: , | AD183: 3347 | AE183: ),
A184: ( | B184: 179 | C184: , ' | D184: Палочкоядерные нейтрофилы (%) | E184: ', ' | F184: band_neutrophils | G184: ', | H184: 1 | I184: , | J184: true | K184: , | L184: 0.00 | M184: , | N184: true | O184: , | P184: 100.00 | Q184: , | R184: true | S184: , | T184: null | U184: , | V184: null | W184: , | X184: false | Y184: , | Z184: null | AA184: , | AB184: 3348 | AC184: , | AD184: 3348 | AE184: ),
A185: ( | B185: 180 | C185: , ' | D185: Нейтрофилы | E185: ', ' | F185: neutrophils | G185: ', | H185: 1 | I185: , | J185: true | K185: , | L185: 1 | M185: , | N185: true | O185: , | P185: 100.00 | Q185: , | R185: true | S185: , | T185: null | U185: , | V185: null | W185: , | X185: false | Y185: , | Z185: null | AA185: , | AB185: 3349 | AC185: , | AD185: 3349 | AE185: ),
A186: ( | B186: 181 | C186: , ' | D186: Нейтрофильно-лейкоцитарное соотношение >20 | E186: ', ' | F186: neutrophil-leukocyte_ratio | G186: ', | H186: 1 | I186: , | J186: false | K186: , | L186: null | M186: , | N186: null | O186: , | P186: null | Q186: , | R186: null | S186: , '{ | T186: 0.1 | U186: }', ' | V186: [ {"value":"0", "encoding":"нет"}, {"value":"1", "encoding":"есть"} ] | W186: ', | X186: false | Y186: , | Z186: null | AA186: , | AB186: 3350 | AC186: , | AD186: 3350 | AE186: ),
A187: ( | B187: 182 | C187: , ' | D187: Лейкоциты (*10^9/л) | E187: ', ' | F187: leukocytes | G187: ', | H187: 1 | I187: , | J187: true | K187: , | L187: 0.10 | M187: , | N187: true | O187: , | P187: 100.00 | Q187: , | R187: true | S187: , | T187: null | U187: , | V187: null | W187: , | X187: false | Y187: , | Z187: null | AA187: , | AB187: 3351 | AC187: , | AD187: 3351 | AE187: ),
A188: ( | B188: 183 | C188: , ' | D188: Гематокрит (%) | E188: ', ' | F188: hematocrit | G188: ', | H188: 1 | I188: , | J188: true | K188: , | L188: 20.00 | M188: , | N188: true | O188: , | P188: 80.00 | Q188: , | R188: true | S188: , | T188: null | U188: , | V188: null | W188: , | X188: false | Y188: , | Z188: null | AA188: , | AB188: 3352 | AC188: , | AD188: 3352 | AE188: ),
A189: ( | B189: 184 | C189: , ' | D189: Уровень титра противовирусных IgG АТ | E189: ', ' | F189: increased_titer_antiviral_IgG_antibodies | G189: ', | H189: 1 | I189: , | J189: false | K189: , | L189: null | M189: , | N189: null | O189: , | P189: null | Q189: , | R189: null | S189: , '{ | T189: 0.1 | U189: }', ' | V189: [ {"value":"0", "encoding":"нет"}, {"value":"1", "encoding":"есть"} ] | W189: ', | X189: false | Y189: , | Z189: null | AA189: , | AB189: 3353 | AC189: , | AD189: 3353 | AE189: ),
A190: ( | B190: 185 | C190: , ' | D190: Уровень ферритина (мкг/л) | E190: ', ' | F190: ferritin | G190: ', | H190: 1 | I190: , | J190: true | K190: , | L190: 1.00 | M190: , | N190: true | O190: , | P190: 10000.00 | Q190: , | R190: true | S190: , | T190: null | U190: , | V190: null | W190: , | X190: false | Y190: , | Z190: null | AA190: , | AB190: 3354 | AC190: , | AD190: 3354 | AE190: ),
A191: ( | B191: 186 | C191: , ' | D191: Консолидированные легочные поля на рентгенограмме | E191: ', ' | F191: consolidated_pulmonary_fields_radiograph | G191: ', | H191: 1 | I191: , | J191: false | K191: , | L191: null | M191: , | N191: null | O191: , | P191: null | Q191: , | R191: null | S191: , '{ | T191: 0.1 | U191: }', ' | V191: [ {"value":"0", "encoding":"нет"}, {"value":"1", "encoding":"есть"} ] | W191: ', | X191: false | Y191: , | Z191: null | AA191: , | AB191: 3355 | AC191: , | AD191: 3355 | AE191: ),
A192: ( | B192: 187 | C192: , ' | D192: Сетчатые легочные поля на рентгенограмме | E192: ', ' | F192: reticular_lung_fields_x-ray | G192: ', | H192: 1 | I192: , | J192: false | K192: , | L192: null | M192: , | N192: null | O192: , | P192: null | Q192: , | R192: null | S192: , '{ | T192: 0.1 | U192: }', ' | V192: [ {"value":"0", "encoding":"нет"}, {"value":"1", "encoding":"есть"} ] | W192: ', | X192: false | Y192: , | Z192: null | AA192: , | AB192: 3356 | AC192: , | AD192: 3356 | AE192: ),
A193: ( | B193: 188 | C193: , ' | D193: Плотность легочных полей повышена на рентгенограмме | E193: ', ' | F193: lung_field_density_increased_x-ray | G193: ', | H193: 1 | I193: , | J193: false | K193: , | L193: null | M193: , | N193: null | O193: , | P193: null | Q193: , | R193: null | S193: , '{ | T193: 0.1 | U193: }', ' | V193: [ {"value":"0", "encoding":"нет"}, {"value":"1", "encoding":"есть"} ] | W193: ', | X193: false | Y193: , | Z193: null | AA193: , | AB193: 3357 | AC193: , | AD193: 3357 | AE193: ),
A194: ( | B194: 189 | C194: , ' | D194: Диффузное усиление легочного рисунка на рентгенограмме | E194: ', ' | F194: diffuse_enhancement_pulmonary_pattern_radiograph | G194: ', | H194: 1 | I194: , | J194: false | K194: , | L194: null | M194: , | N194: null | O194: , | P194: null | Q194: , | R194: null | S194: , '{ | T194: 0.1 | U194: }', ' | V194: [ {"value":"0", "encoding":"нет"}, {"value":"1", "encoding":"есть"} ] | W194: ', | X194: false | Y194: , | Z194: null | AA194: , | AB194: 3358 | AC194: , | AD194: 3358 | AE194: ),
A195: ( | B195: 190 | C195: , ' | D195: Перибронхиальные инфильтраты на КТ ОГК | E195: ', ' | F195: peribronchial_infiltrates_CT_OGK | G195: ', | H195: 1 | I195: , | J195: false | K195: , | L195: null | M195: , | N195: null | O195: , | P195: null | Q195: , | R195: null | S195: , '{ | T195: 0.1 | U195: }', ' | V195: [ {"value":"0", "encoding":"нет"}, {"value":"1", "encoding":"есть"} ] | W195: ', | X195: false | Y195: , | Z195: null | AA195: , | AB195: 3359 | AC195: , | AD195: 3359 | AE195: ),
A196: ( | B196: 191 | C196: , ' | D196: Зоны консолидации легочной ткани | E196: ', ' | F196: zones_consolidation_lung_tissue | G196: ', | H196: 1 | I196: , | J196: false | K196: , | L196: null | M196: , | N196: null | O196: , | P196: null | Q196: , | R196: null | S196: , '{ | T196: 0.1 | U196: }', ' | V196: [ {"value":"0", "encoding":"нет"}, {"value":"1", "encoding":"есть"} ] | W196: ', | X196: false | Y196: , | Z196: null | AA196: , | AB196: 3360 | AC196: , | AD196: 3360 | AE196: ),
A197: ( | B197: 192 | C197: , ' | D197: "Матовое стекло" (КТ) | E197: ', ' | F197: frosted_glass | G197: ', | H197: 1 | I197: , | J197: false | K197: , | L197: null | M197: , | N197: null | O197: , | P197: null | Q197: , | R197: null | S197: , '{ | T197: 0.1 | U197: }', ' | V197: [ {"value":"0", "encoding":"нет"}, {"value":"1", "encoding":"есть"} ] | W197: ', | X197: false | Y197: , | Z197: null | AA197: , | AB197: 3361 | AC197: , | AD197: 3361 | AE197: ),
A198: ( | B198: 193 | C198: , ' | D198: Участок инфильтрации некруглой формы на КТ ОГК | E198: ', ' | F198: non-circular_infiltration_area_CT_scan_OGK | G198: ', | H198: 1 | I198: , | J198: false | K198: , | L198: null | M198: , | N198: null | O198: , | P198: null | Q198: , | R198: null | S198: , '{ | T198: 0.1 | U198: }', ' | V198: [ {"value":"0", "encoding":"нет"}, {"value":"1", "encoding":"есть"} ] | W198: ', | X198: false | Y198: , | Z198: null | AA198: , | AB198: 3362 | AC198: , | AD198: 3362 | AE198: ),
A199: ( | B199: 194 | C199: , ' | D199: Наличие очаговой инфильтрации на рентгенограмме | E199: ', ' | F199: presence_focal_infiltration_x-ray | G199: ', | H199: 1 | I199: , | J199: false | K199: , | L199: null | M199: , | N199: null | O199: , | P199: null | Q199: , | R199: null | S199: , '{ | T199: 0.1 | U199: }', ' | V199: [ {"value":"0", "encoding":"нет"}, {"value":"1", "encoding":"есть"} ] | W199: ', | X199: false | Y199: , | Z199: null | AA199: , | AB199: 3363 | AC199: , | AD199: 3363 | AE199: ),
A200: ( | B200: 195 | C200: , ' | D200: Наличие очагово-инфильтративных изменений в легких на рентгенограмме | E200: ', ' | F200: presence_focal_infiltrative_changes_lungs_x-ray | G200: ', | H200: 1 | I200: , | J200: false | K200: , | L200: null | M200: , | N200: null | O200: , | P200: null | Q200: , | R200: null | S200: , '{ | T200: 0.1 | U200: }', ' | V200: [ {"value":"0", "encoding":"нет"}, {"value":"1", "encoding":"есть"} ] | W200: ', | X200: false | Y200: , | Z200: null | AA200: , | AB200: 3364 | AC200: , | AD200: 3364 | AE200: ),
A201: ( | B201: 196 | C201: , ' | D201: Одиночный очаг на рентгенограмме ОГК | E201: ', ' | F201: single_lesion_chest_X-ray | G201: ', | H201: 1 | I201: , | J201: false | K201: , | L201: null | M201: , | N201: null | O201: , | P201: null | Q201: , | R201: null | S201: , '{ | T201: 0.1 | U201: }', ' | V201: [ {"value":"0", "encoding":"нет"}, {"value":"1", "encoding":"есть"} ] | W201: ', | X201: false | Y201: , | Z201: null | AA201: , | AB201: 3365 | AC201: , | AD201: 3365 | AE201: ),
A202: ( | B202: 197 | C202: , ' | D202: Очаговые тени мелкого размера на рентгенограмме | E202: ', ' | F202: patchy_shadows_size_radiograph_small | G202: ', | H202: 1 | I202: , | J202: false | K202: , | L202: null | M202: , | N202: null | O202: , | P202: null | Q202: , | R202: null | S202: , '{ | T202: 0.1 | U202: }', ' | V202: [ {"value":"0", "encoding":"нет"}, {"value":"1", "encoding":"есть"} ] | W202: ', | X202: false | Y202: , | Z202: null | AA202: , | AB202: 3366 | AC202: , | AD202: 3366 | AE202: ),
... A270: ( | B270: 265 | C270: , ' | D270: Очаг с симптомом паруса на рентгенограмме ОГК | E270: ', ' | F270: lesion_sail_symptom_radiograph_OGK | G270: ', | H270: 1 | I270: , | J270: false | K270: , | L270: null | M270: , | N270: null | O270: , | P270: null | Q270: , | R270: null | S270: , '{ | T270: 0.1 | U270: }', ' | V270: [ {"value":"0", "encoding":"нет"}, {"value":"1", "encoding":"есть"} ] | W270: ', | X270: false | Y270: , | Z270: null | AA270: , | AB270: 3434 | AC270: , | AD270: 3434 | AE270: ),
A271: ( | B271: 266 | C271: , ' | D271: Уровень ракового эмбрионального антигена (нг/мл) | E271: ', ' | F271: increased_level_carcinoembryonic_antigen | G271: ', | H271: 1 | I271: , | J271: true | K271: , | L271: 0.00 | M271: , | N271: true | O271: , | P271: 1000.00 | Q271: , | R271: true | S271: , | T271: null | U271: , ' | V271: null | W271: ', | X271: false | Y271: , | Z271: null | AA271: , | AB271: 3435 | AC271: , | AD271: 3435 | AE271: ),
A272: ( | B272: 267 | C272: , ' | D272: Уровень антигена плоскоклеточной карциномы в крови (нг/мл) | E272: ', ' | F272: increased_levels_squamous_cell_carcinoma_antigen_blood | G272: ', | H272: 1 | I272: , | J272: true | K272: , | L272: 0.00 | M272: , | N272: true | O272: , | P272: 1000.00 | Q272: , | R272: true | S272: , | T272: null | U272: , ' | V272: null | W272: ', | X272: false | Y272: , | Z272: null | AA272: , | AB272: 3436 | AC272: , | AD272: 3436 | AE272: ),
A273: ( | B273: 268 | C273: , ' | D273: Уровень фрагментов цитокератина 19 (CYFRA 21-1) в крови (нг/мл) | E273: ', ' | F273: increased_levels_cytokeratin_19_fragments_CYFRA_21-1_blood | G273: ', | H273: 1 | I273: , | J273: true | K273: , | L273: 0.00 | M273: , | N273: true | O273: , | P273: 1000.00 | Q273: , | R273: true | S273: , | T273: null | U273: , ' | V273: null | W273: ', | X273: false | Y273: , | Z273: null | AA273: , | AB273: 3437 | AC273: , | AD273: 3437 | AE273: ),
A274: ( | B274: 269 | C274: , ' | D274: Уровень нейронспецифической енолазы (NSE) в крови (нг/мл) | E274: ', ' | F274: increased_levels_NSE_blood | G274: ', | H274: 1 | I274: , | J274: true | K274: , | L274: 0.00 | M274: , | N274: true | O274: , | P274: 1000.00 | Q274: , | R274: true | S274: , | T274: null | U274: , ' | V274: null | W274: ', | X274: false | Y274: , | Z274: null | AA274: , | AB274: 3438 | AC274: , | AD274: 3438 | AE274: ),
A275: ( | B275: 270 | C275: , ' | D275: Уровень антигена ракового CA-125 в крови (Ед.) | E275: ', ' | F275: increased_levels_cancer_antigen_CA_125_blood | G275: ', | H275: 1 | I275: , | J275: true | K275: , | L275: 0.00 | M275: , | N275: true | O275: , | P275: 1000.00 | Q275: , | R275: true | S275: , | T275: null | U275: , ' | V275: null | W275: ', | X275: false | Y275: , | Z275: null | AA275: , | AB275: 3439 | AC275: , | AD275: 3439 | AE275: ),
A276: ( | B276: 271 | C276: , ' | D276: Эритроциты (*10^12/л) | E276: ', ' | F276: red_blood_cells | G276: ', | H276: 1 | I276: , | J276: true | K276: , | L276: 0.10 | M276: , | N276: true | O276: , | P276: 10.00 | Q276: , | R276: true | S276: , | T276: null | U276: , ' | V276: null | W276: ', | X276: false | Y276: , | Z276: null | AA276: , | AB276: 3440 | AC276: , | AD276: 3440 | AE276: ),
A277: ( | B277: 272 | C277: , ' | D277: Гемоглобин | E277: ', ' | F277: hemoglobin | G277: ', | H277: 1 | I277: , | J277: true | K277: , | L277: 0.10 | M277: , | N277: true | O277: , | P277: 300.00 | Q277: , | R277: true | S277: , | T277: null | U277: , ' | V277: null | W277: ', | X277: false | Y277: , | Z277: null | AA277: , | AB277: 3441 | AC277: , | AD277: 3441 | AE277: ),
A278: ( | B278: 273 | C278: , ' | D278: Врастание опухоли в грудную стенку на КТ ОГК | E278: ', ' | F278: tumor_ingrowth_chest_wall_chest_CT | G278: ', | H278: 1 | I278: , | J278: false | K278: , | L278: null | M278: , | N278: null | O278: , | P278: null | Q278: , | R278: null | S278: , '{ | T278: 0.1 | U278: }', ' | V278: [ {"value":"0", "encoding":"нет"}, {"value":"1", "encoding":"есть"} ] | W278: ', | X278: false | Y278: , | Z278: null | AA278: , | AB278: 3442 | AC278: , | AD278: 3442 | AE278: ),
A279: ( | B279: 274 | C279: , ' | D279: Врастание опухоли в средостени на КТ ОГК | E279: ', ' | F279: tumor_ingrowth_mediastinum_CT | G279: ', | H279: 1 | I279: , | J279: false | K279: , | L279: null | M279: , | N279: null | O279: , | P279: null | Q279: , | R279: null | S279: , '{ | T279: 0.1 | U279: }', ' | V279: [ {"value":"0", "encoding":"нет"}, {"value":"1", "encoding":"есть"} ] | W279: ', | X279: false | Y279: , | Z279: null | AA279: , | AB279: 3443 | AC279: , | AD279: 3443 | AE279: ),
A280: ( | B280: 275 | C280: , ' | D280: Врастание опухоли в верхнюю апертуре на КТ ОГК | E280: ', ' | F280: tumor_ingrowth_upper_aperture_CT_OGK | G280: ', | H280: 1 | I280: , | J280: false | K280: , | L280: null | M280: , | N280: null | O280: , | P280: null | Q280: , | R280: null | S280: , '{ | T280: 0.1 | U280: }', ' | V280: [ {"value":"0", "encoding":"нет"}, {"value":"1", "encoding":"есть"} ] | W280: ', | X280: false | Y280: , | Z280: null | AA280: , | AB280: 3444 | AC280: , | AD280: 3444 | AE280: ),
A281: ( | B281: 276 | C281: , ' | D281: Очаговая диссеминация в легком на КТ ОГК | E281: ', ' | F281: focal_dissemination_lung_CT_OGK | G281: ', | H281: 1 | I281: , | J281: false | K281: , | L281: null | M281: , | N281: null | O281: , | P281: null | Q281: , | R281: null | S281: , '{ | T281: 0.1 | U281: }', ' | V281: [ {"value":"0", "encoding":"нет"}, {"value":"1", "encoding":"есть"} ] | W281: ', | X281: false | Y281: , | Z281: null | AA281: , | AB281: 3445 | AC281: , | AD281: 3445 | AE281: ),
A282: ( | B282: 277 | C282: , ' | D282: Полость распада на КТ ОГК | E282: ', ' | F282: decay_cavity_CT_OGK | G282: ', | H282: 1 | I282: , | J282: false | K282: , | L282: null | M282: , | N282: null | O282: , | P282: null | Q282: , | R282: null | S282: , '{ | T282: 0.1 | U282: }', ' | V282: [ {"value":"0", "encoding":"нет"}, {"value":"1", "encoding":"есть"} ] | W282: ', | X282: false | Y282: , | Z282: null | AA282: , | AB282: 3446 | AC282: , | AD282: 3446 | AE282: ),
A283: ( | B283: 278 | C283: , ' | D283: Очаг частично солидного типа на КТ ОГК | E283: ', ' | F283: partially_solid_lesion_CT_OGK | G283: ', | H283: 1 | I283: , | J283: false | K283: , | L283: null | M283: , | N283: null | O283: , | P283: null | Q283: , | R283: null | S283: , '{ | T283: 0.1 | U283: }', ' | V283: [ {"value":"0", "encoding":"нет"}, {"value":"1", "encoding":"есть"} ] | W283: ', | X283: false | Y283: , | Z283: null | AA283: , | AB283: 3447 | AC283: , | AD283: 3447 | AE283: ),
A284: ( | B284: 279 | C284: , ' | D284: Очаг по типу "матового стекла" на КТ ОГК | E284: ', ' | F284: ground_glass_lesion_CT_OGK | G284: ', | H284: 1 | I284: , | J284: false | K284: , | L284: null | M284: , | N284: null | O284: , | P284: null | Q284: , | R284: null | S284: , '{ | T284: 0.1 | U284: }', ' | V284: [ {"value":"0", "encoding":"нет"}, {"value":"1", "encoding":"есть"} ] | W284: ', | X284: false | Y284: , | Z284: null | AA284: , | AB284: 3448 | AC284: , | AD284: 3448 | AE284: ),
A285: ( | B285: 280 | C285: , ' | D285: Очаг солидного типа с бугристым контуром на КТ ОГК | E285: ', ' | F285: solid_type_lesion_uberous_outline_CT_OGK | G285: ', | H285: 1 | I285: , | J285: false | K285: , | L285: null | M285: , | N285: null | O285: , | P285: null | Q285: , | R285: null | S285: , '{ | T285: 0.1 | U285: }', ' | V285: [ {"value":"0", "encoding":"нет"}, {"value":"1", "encoding":"есть"} ] | W285: ', | X285: false | Y285: , | Z285: null | AA285: , | AB285: 3449 | AC285: , | AD285: 3449 | AE285: ),
...

Sheet Скрипт node_activation_cond
C1: INSERT INTO public.node_activation_conditions(
E2: id, node_id, activation_condition_id, numeric_range_start_point, include_start_point, numeric_range_end_point, include_end_point, string_values, is_deleted, description, current_state, init_state)
C3: VALUES
B4: ( | C4: id | D4: , | E4: node_id | F4: , | G4: activation_condition_id | H4: , | I4: numeric_range_start_point | J4: , | K4: include_start_point | L4: , | M4: numeric_range_end_point | N4: , | O4: include_end_point | P4: , '{ | Q4: string_values | R4: }', | S4: is_deleted | T4: , ' | U4: description | V4: ', | W4: current_state | X4: , | Y4: init_state | Z4: ), | AA4: Свойство | AB4: Узел
A5: --- | B5: ( | D5: , | E5: null | F5: , | G5: 1 | H5: , | I5: null | J5: , | K5: null | L5: , | M5: null | N5: , | O5: null | P5: , '{ | Q5: 1 | R5: }', | S5: false | T5: , ' | U5: отсутствует | V5: ', | W5: 3631 | X5: , | Y5: 3631 | Z5: ), | AA5: =VLOOKUP(G5,'Скрипт activation_condition'!$B$6:$D$495,3,0) -> Кашель отсутсвует | AB5: =VLOOKUP(E5,'Перечень узлов'!$A$1:$B$697,2,0) -> #N/A
A6: --- | B6: ( | D6: , | E6: null | F6: , | G6: 2 | H6: , | I6: null | J6: , | K6: null | L6: , | M6: null | N6: , | O6: null | P6: , '{ | Q6: 1 | R6: }', | S6: false | T6: , ' | U6: без уточнения | V6: ', | W6: 3632 | X6: , | Y6: 3632 | Z6: ), | AA6: =VLOOKUP(G6,'Скрипт activation_condition'!$B$6:$D$495,3,0) -> Кашель без уточнения | AB6: =VLOOKUP(E6,'Перечень узлов'!$A$1:$B$697,2,0) -> #N/A
B7: ( | C7: 1 | D7: , | E7: 15 | F7: , | G7: 3 | H7: , | I7: null | J7: , | K7: null | L7: , | M7: null | N7: , | O7: null | P7: , '{ | Q7: 1 | R7: }', | S7: false | T7: , ' | U7: сухой | V7: ', | W7: 3633 | X7: , | Y7: 3633 | Z7: ), | AA7: =VLOOKUP(G7,'Скрипт activation_condition'!$B$6:$D$495,3,0) -> Кашель непродуктивный | AB7: =VLOOKUP(E7,'Перечень узлов'!$A$1:$B$697,2,0) -> Сухой кашель
B8: ( | C8: =C7+1 -> 2 | D8: , | E8: 17 | F8: , | G8: 4 | H8: , | I8: null | J8: , | K8: null | L8: , | M8: null | N8: , | O8: null | P8: , '{ | Q8: 1 | R8: }', | S8: false | T8: , ' | U8: малопродуктивный | V8: ', | W8: 3634 | X8: , | Y8: 3634 | Z8: ), | AA8: =VLOOKUP(G8,'Скрипт activation_condition'!$B$6:$D$495,3,0) -> Кашель малопродуктивный | AB8: =VLOOKUP(E8,'Перечень узлов'!$A$1:$B$697,2,0) -> Малопродуктивный кашель
B9: ( | C9: =C8+1 -> 3 | D9: , | E9: 9 | F9: , | G9: 5 | H9: , | I9: null | J9: , | K9: null | L9: , | M9: null | N9: , | O9: null | P9: , '{ | Q9: 1 | R9: }', | S9: false | T9: , ' | U9: влажный | V9: ', | W9: 3635 | X9: , | Y9: 3635 | Z9: ), | AA9: =VLOOKUP(G9,'Скрипт activation_condition'!$B$6:$D$495,3,0) -> Кашель продуктивный | AB9: =VLOOKUP(E9,'Перечень узлов'!$A$1:$B$697,2,0) -> Продуктивный кашель
B10: ( | C10: =C9+1 -> 4 | D10: , | E10: 10 | F10: , | G10: 6 | H10: , | I10: null | J10: , | K10: null | L10: , | M10: null | N10: , | O10: null | P10: , '{ | Q10: 1 | R10: }', | S10: false | T10: , ' | U10: надсадный | V10: ', | W10: 3636 | X10: , | Y10: 3636 | Z10: ), | AA10: =VLOOKUP(G10,'Скрипт activation_condition'!$B$6:$D$495,3,0) -> Кашель надсадный | AB10: =VLOOKUP(E10,'Перечень узлов'!$A$1:$B$697,2,0) -> Надсадный кашель
B11: ( | C11: =C10+1 -> 5 | D11: , | E11: 18 | F11: , | G11: 7 | H11: , | I11: null | J11: , | K11: null | L11: , | M11: null | N11: , | O11: null | P11: , '{ | Q11: 1 | R11: }', | S11: false | T11: , ' | U11: изнуряющий | V11: ', | W11: 3637 | X11: , | Y11: 3637 | Z11: ), | AA11: =VLOOKUP(G11,'Скрипт activation_condition'!$B$6:$D$495,3,0) -> Кашель изнуряющий | AB11: =VLOOKUP(E11,'Перечень узлов'!$A$1:$B$697,2,0) -> Изнуряющий кашель
B12: ( | C12: =C11+1 -> 6 | D12: , | E12: 16 | F12: , | G12: 8 | H12: , | I12: null | J12: , | K12: null | L12: , | M12: null | N12: , | O12: null | P12: , '{ | Q12: 1 | R12: }', | S12: false | T12: , ' | U12: с кровью | V12: ', | W12: 3638 | X12: , | Y12: 3638 | Z12: ), | AA12: =VLOOKUP(G12,'Скрипт activation_condition'!$B$6:$D$495,3,0) -> Кашель с примесью крови | AB12: =VLOOKUP(E12,'Перечень узлов'!$A$1:$B$697,2,0) -> Кровохарканье
A13: --- | B13: ( | D13: , | E13: null | F13: , | G13: 9 | H13: , | I13: 27.00 | J13: , | K13: true | L13: , | M13: 35.40 | N13: , | O13: true | P13: , | Q13: null | R13: , | S13: false | T13: , ' | U13: Низкая температура | V13: ', | W13: 3639 | X13: , | Y13: 3639 | Z13: ), | AA13: =VLOOKUP(G13,'Скрипт activation_condition'!$B$6:$D$495,3,0) -> Температура тела | AB13: =VLOOKUP(E13,'Перечень узлов'!$A$1:$B$697,2,0) -> #N/A
A14: --- | B14: ( | D14: , | E14: null | F14: , | G14: 9 | H14: , | I14: 35.50 | J14: , | K14: true | L14: , | M14: 37.00 | N14: , | O14: true | P14: , | Q14: null | R14: , | S14: false | T14: , ' | U14: Нормальная температура тела | V14: ', | W14: 3640 | X14: , | Y14: 3640 | Z14: ), | AA14: =VLOOKUP(G14,'Скрипт activation_condition'!$B$6:$D$495,3,0) -> Температура тела | AB14: =VLOOKUP(E14,'Перечень узлов'!$A$1:$B$697,2,0) -> #N/A
B15: ( | C15: =C12+1 -> 7 | D15: , | E15: 171 | F15: , | G15: 9 | H15: , | I15: 37.10 | J15: , | K15: true | L15: , | M15: 38.00 | N15: , | O15: true | P15: , | Q15: null | R15: , | S15: false | T15: , ' | U15: Субфебрильная температура тела | V15: ', | W15: 3641 | X15: , | Y15: 3641 | Z15: ), | AA15: =VLOOKUP(G15,'Скрипт activation_condition'!$B$6:$D$495,3,0) -> Температура тела | AB15: =VLOOKUP(E15,'Перечень узлов'!$A$1:$B$697,2,0) -> Субфебрильная температура
B16: ( | C16: =C15+1 -> 8 | D16: , | E16: 172 | F16: , | G16: 9 | H16: , | I16: 38.10 | J16: , | K16: true | L16: , | M16: 39.50 | N16: , | O16: true | P16: , | Q16: null | R16: , | S16: false | T16: , ' | U16: Фебрильная температура тела | V16: ', | W16: 3642 | X16: , | Y16: 3642 | Z16: ), | AA16: =VLOOKUP(G16,'Скрипт activation_condition'!$B$6:$D$495,3,0) -> Температура тела | AB16: =VLOOKUP(E16,'Перечень узлов'!$A$1:$B$697,2,0) -> Фебрильная температура
B17: ( | C17: =C16+1 -> 9 | D17: , | E17: 173 | F17: , | G17: 9 | H17: , | I17: 39.60 | J17: , | K17: true | L17: , | M17: 42.00 | N17: , | O17: true | P17: , | Q17: null | R17: , | S17: false | T17: , ' | U17: Пиретическая температура тела | V17: ', | W17: 3643 | X17: , | Y17: 3643 | Z17: ), | AA17: =VLOOKUP(G17,'Скрипт activation_condition'!$B$6:$D$495,3,0) -> Температура тела | AB17: =VLOOKUP(E17,'Перечень узлов'!$A$1:$B$697,2,0) -> Пиретическая температура
B18: ( | C18: =C17+1 -> 10 | D18: , | E18: 637 | F18: , | G18: 9 | H18: , | I18: 42.10 | J18: , | K18: true | L18: , | M18: 46.50 | N18: , | O18: true | P18: , | Q18: null | R18: , | S18: false | T18: , ' | U18: Гиперпирексическая температура тела | V18: ', | W18: 3644 | X18: , | Y18: 3644 | Z18: ), | AA18: =VLOOKUP(G18,'Скрипт activation_condition'!$B$6:$D$495,3,0) -> Температура тела | AB18: =VLOOKUP(E18,'Перечень узлов'!$A$1:$B$697,2,0) -> Гиперпирексическая температура
A19: --- | B19: ( | D19: , | E19: null | F19: , | G19: 10 | H19: , | I19: null | J19: , | K19: null | L19: , | M19: null | N19: , | O19: null | P19: , '{ | Q19: 0 | R19: }', | S19: false | T19: , ' | U19: без уточнения | V19: ', | W19: 3645 | X19: , | Y19: 3645 | Z19: ), | AA19: =VLOOKUP(G19,'Скрипт activation_condition'!$B$6:$D$495,3,0) -> Мокрота | AB19: =VLOOKUP(E19,'Перечень узлов'!$A$1:$B$697,2,0) -> #N/A
B20: ( | C20: =C18+1 -> 11 | D20: , | E20: 14 | F20: , | G20: 10 | H20: , | I20: null | J20: , | K20: null | L20: , | M20: null | N20: , | O20: null | P20: , '{ | Q20: 1 | R20: }', | S20: false | T20: , ' | U20: слизистая | V20: ', | W20: 3646 | X20: , | Y20: 3646 | Z20: ), | AA20: =VLOOKUP(G20,'Скрипт activation_condition'!$B$6:$D$495,3,0) -> Мокрота | AB20: =VLOOKUP(E20,'Перечень узлов'!$A$1:$B$697,2,0) -> Слизистая мокрота
A21: --- | B21: ( | D21: , | E21: null | F21: , | G21: 10 | H21: , | I21: null | J21: , | K21: null | L21: , | M21: null | N21: , | O21: null | P21: , '{ | Q21: 2 | R21: }', | S21: false | T21: , ' | U21: серозная | V21: ', | W21: 3647 | X21: , | Y21: 3647 | Z21: ), | AA21: =VLOOKUP(G21,'Скрипт activation_condition'!$B$6:$D$495,3,0) -> Мокрота | AB21: =VLOOKUP(E21,'Перечень узлов'!$A$1:$B$697,2,0) -> #N/A
B22: ( | C22: =C20+1 -> 12 | D22: , | E22: 12 | F22: , | G22: 10 | H22: , | I22: null | J22: , | K22: null | L22: , | M22: null | N22: , | O22: null | P22: , '{ | Q22: 3 | R22: }', | S22: false | T22: , ' | U22: слизисто-гнойная | V22: ', | W22: 3648 | X22: , | Y22: 3648 | Z22: ), | AA22: =VLOOKUP(G22,'Скрипт activation_condition'!$B$6:$D$495,3,0) -> Мокрота | AB22: =VLOOKUP(E22,'Перечень узлов'!$A$1:$B$697,2,0) -> Слизисто-гнойная мокрота
A23: --- | B23: ( | D23: , | E23: null | F23: , | G23: 10 | H23: , | I23: null | J23: , | K23: null | L23: , | M23: null | N23: , | O23: null | P23: , '{ | Q23: 4 | R23: }', | S23: false | T23: , ' | U23: гнойная | V23: ', | W23: 3649 | X23: , | Y23: 3649 | Z23: ), | AA23: =VLOOKUP(G23,'Скрипт activation_condition'!$B$6:$D$495,3,0) -> Мокрота | AB23: =VLOOKUP(E23,'Перечень узлов'!$A$1:$B$697,2,0) -> #N/A
B24: ( | C24: =C22+1 -> 13 | D24: , | E24: 13 | F24: , | G24: 10 | H24: , | I24: null | J24: , | K24: null | L24: , | M24: null | N24: , | O24: null | P24: , '{ | Q24: 5 | R24: }', | S24: false | T24: , ' | U24: "ржавая" мокрота | V24: ', | W24: 3650 | X24: , | Y24: 3650 | Z24: ), | AA24: =VLOOKUP(G24,'Скрипт activation_condition'!$B$6:$D$495,3,0) -> Мокрота | AB24: =VLOOKUP(E24,'Перечень узлов'!$A$1:$B$697,2,0) -> "Ржавая" мокрота
B25: ( | C25: =C24+1 -> 14 | D25: , | E25: 11 | F25: , | G25: 10 | H25: , | I25: null | J25: , | K25: null | L25: , | M25: null | N25: , | O25: null | P25: , '{ | Q25: 6 | R25: }', | S25: false | T25: , ' | U25: серозно-геморрагическая | V25: ', | W25: 3651 | X25: , | Y25: 3651 | Z25: ), | AA25: =VLOOKUP(G25,'Скрипт activation_condition'!$B$6:$D$495,3,0) -> Мокрота | AB25: =VLOOKUP(E25,'Перечень узлов'!$A$1:$B$697,2,0) -> Серозно-геморрагическая мокрота
B26: ( | C26: =C25+1 -> 15 | D26: , | E26: 40 | F26: , | G26: 10 | H26: , | I26: null | J26: , | K26: null | L26: , | M26: null | N26: , | O26: null | P26: , '{ | Q26: 7 | R26: }', | S26: false | T26: , ' | U26: кровавая мокрота | V26: ', | W26: 3652 | X26: , | Y26: 3652 | Z26: ), | AA26: =VLOOKUP(G26,'Скрипт activation_condition'!$B$6:$D$495,3,0) -> Мокрота | AB26: =VLOOKUP(E26,'Перечень узлов'!$A$1:$B$697,2,0) -> Мокрота с примесью крови
B27: ( | C27: =C26+1 -> 16 | D27: , | E27: 19 | F27: , | G27: 11 | H27: , | I27: null | J27: , | K27: null | L27: , | M27: null | N27: , | O27: null | P27: , '{ | Q27: 1 | R27: }', | S27: false | T27: , ' | U27: боль в грудной клетке имеется | V27: ', | W27: 3653 | X27: , | Y27: 3653 | Z27: ), | AA27: =VLOOKUP(G27,'Скрипт activation_condition'!$B$6:$D$495,3,0) -> Боль в грудной клетке | AB27: =VLOOKUP(E27,'Перечень узлов'!$A$1:$B$697,2,0) -> Боль в грудной клетке
B28: ( | C28: =C27+1 -> 17 | D28: , | E28: 20 | F28: , | G28: 12 | H28: , | I28: null | J28: , | K28: null | L28: , | M28: null | N28: , | O28: null | P28: , '{ | Q28: 1 | R28: }', | S28: false | T28: , ' | U28: боль в суставах имеется | V28: ', | W28: 3654 | X28: , | Y28: 3654 | Z28: ), | AA28: =VLOOKUP(G28,'Скрипт activation_condition'!$B$6:$D$495,3,0) -> Артралгия | AB28: =VLOOKUP(E28,'Перечень узлов'!$A$1:$B$697,2,0) -> Артралгия
B29: ( | C29: =C28+1 -> 18 | D29: , | E29: 21 | F29: , | G29: 13 | H29: , | I29: null | J29: , | K29: null | L29: , | M29: null | N29: , | O29: null | P29: , '{ | Q29: 1 | R29: }', | S29: false | T29: , ' | U29: боль в мышцах имеется | V29: ', | W29: 3655 | X29: , | Y29: 3655 | Z29: ), | AA29: =VLOOKUP(G29,'Скрипт activation_condition'!$B$6:$D$495,3,0) -> Миалгия | AB29: =VLOOKUP(E29,'Перечень узлов'!$A$1:$B$697,2,0) -> Миалгия
B30: ( | C30: =C29+1 -> 19 | D30: , | E30: 22 | F30: , | G30: 14 | H30: , | I30: null | J30: , | K30: null | L30: , | M30: null | N30: , | O30: null | P30: , '{ | Q30: 1 | R30: }', | S30: false | T30: , ' | U30: боль в костях имеется | V30: ', | W30: 3656 | X30: , | Y30: 3656 | Z30: ), | AA30: =VLOOKUP(G30,'Скрипт activation_condition'!$B$6:$D$495,3,0) -> Оссалгия | AB30: =VLOOKUP(E30,'Перечень узлов'!$A$1:$B$697,2,0) -> Оссалгия
B31: ( | C31: =C30+1 -> 20 | D31: , | E31: 23 | F31: , | G31: 15 | H31: , | I31: null | J31: , | K31: null | L31: , | M31: null | N31: , | O31: null | P31: , '{ | Q31: 1 | R31: }', | S31: false | T31: , ' | U31: Боль в глазных яблоках | V31: ', | W31: 3657 | X31: , | Y31: 3657 | Z31: ), | AA31: =VLOOKUP(G31,'Скрипт activation_condition'!$B$6:$D$495,3,0) -> Боль в глазных яблоках | AB31: =VLOOKUP(E31,'Перечень узлов'!$A$1:$B$697,2,0) -> Боль в глазных яблоках
B32: ( | C32: =C31+1 -> 21 | D32: , | E32: 24 | F32: , | G32: 16 | H32: , | I32: null | J32: , | K32: null | L32: , | M32: null | N32: , | O32: null | P32: , '{ | Q32: 1 | R32: }', | S32: false | T32: , ' | U32: Конъюнктивит | V32: ', | W32: 3658 | X32: , | Y32: 3658 | Z32: ), | AA32: =VLOOKUP(G32,'Скрипт activation_condition'!$B$6:$D$495,3,0) -> Конъюнктивит | AB32: =VLOOKUP(E32,'Перечень узлов'!$A$1:$B$697,2,0) -> Конъюнктивит
B33: ( | C33: =C32+1 -> 22 | D33: , | E33: 25 | F33: , | G33: 17 | H33: , | I33: null | J33: , | K33: null | L33: , | M33: null | N33: , | O33: null | P33: , '{ | Q33: 1 | R33: }', | S33: false | T33: , ' | U33: Головная боль | V33: ', | W33: 3659 | X33: , | Y33: 3659 | Z33: ), | AA33: =VLOOKUP(G33,'Скрипт activation_condition'!$B$6:$D$495,3,0) -> Головная боль | AB33: =VLOOKUP(E33,'Перечень узлов'!$A$1:$B$697,2,0) -> Головная боль
B34: ( | C34: =C33+1 -> 23 | D34: , | E34: 26 | F34: , | G34: 18 | H34: , | I34: null | J34: , | K34: null | L34: , | M34: null | N34: , | O34: null | P34: , '{ | Q34: 1 | R34: }', | S34: false | T34: , ' | U34: Боль в плечевом суставе | V34: ', | W34: 3660 | X34: , | Y34: 3660 | Z34: ), | AA34: =VLOOKUP(G34,'Скрипт activation_condition'!$B$6:$D$495,3,0) -> Боль в плечевом суставе | AB34: =VLOOKUP(E34,'Перечень узлов'!$A$1:$B$697,2,0) -> Боль в плечевом суставе
B35: ( | C35: =C34+1 -> 24 | D35: , | E35: 27 | F35: , | G35: 19 | H35: , | I35: null | J35: , | K35: null | L35: , | M35: null | N35: , | O35: null | P35: , '{ | Q35: 1 | R35: }', | S35: false | T35: , ' | U35: Боль в плече | V35: ', | W35: 3661 | X35: , | Y35: 3661 | Z35: ), | AA35: =VLOOKUP(G35,'Скрипт activation_condition'!$B$6:$D$495,3,0) -> Боль в плече | AB35: =VLOOKUP(E35,'Перечень узлов'!$A$1:$B$697,2,0) -> Боль в плече
B36: ( | C36: =C35+1 -> 25 | D36: , | E36: 28 | F36: , | G36: 20 | H36: , | I36: null | J36: , | K36: null | L36: , | M36: null | N36: , | O36: null | P36: , '{ | Q36: 1 | R36: }', | S36: false | T36: , ' | U36: Атрофия мышц предплечья | V36: ', | W36: 3662 | X36: , | Y36: 3662 | Z36: ), | AA36: =VLOOKUP(G36,'Скрипт activation_condition'!$B$6:$D$495,3,0) -> Атрофия мышц предплечья | AB36: =VLOOKUP(E36,'Перечень узлов'!$A$1:$B$697,2,0) -> Атрофия мышц предплечья
... B41: ( | C41: =C40+1 -> 30 | D41: , | E41: 669 | F41: , | G41: 21 | H41: , | I41: null | J41: , | K41: null | L41: , | M41: null | N41: , | O41: null | P41: , '{ | Q41: 4 | R41: }', | S41: false | T41: , ' | U41: Потеря голоса | V41: ', | W41: 3667 | X41: , | Y41: 3667 | Z41: ), | AA41: =VLOOKUP(G41,'Скрипт activation_condition'!$B$6:$D$495,3,0) -> Голос | AB41: =VLOOKUP(E41,'Перечень узлов'!$A$1:$B$697,2,0) -> Потеря голоса
A42: --- | B42: ( | C42: =C41+1 -> 31 | D42: , | E42: null | F42: , | G42: 22 | H42: , | I42: null | J42: , | K42: null | L42: , | M42: null | N42: , | O42: null | P42: , '{ | Q42: 0 | R42: }', | S42: false | T42: , ' | U42: Насморк отсутствует | V42: ', | W42: 3668 | X42: , | Y42: 3668 | Z42: ), | AA42: =VLOOKUP(G42,'Скрипт activation_condition'!$B$6:$D$495,3,0) -> Насморк | AB42: =VLOOKUP(E42,'Перечень узлов'!$A$1:$B$697,2,0) -> #N/A
B43: ( | C43: =C42+1 -> 32 | D43: , | E43: 31 | F43: , | G43: 22 | H43: , | I43: null | J43: , | K43: null | L43: , | M43: null | N43: , | O43: null | P43: , '{ | Q43: 1 | R43: }', | S43: false | T43: , ' | U43: Заложенность носа | V43: ', | W43: 3669 | X43: , | Y43: 3669 | Z43: ), | AA43: =VLOOKUP(G43,'Скрипт activation_condition'!$B$6:$D$495,3,0) -> Насморк | AB43: =VLOOKUP(E43,'Перечень узлов'!$A$1:$B$697,2,0) -> Заложенность носа
B44: ( | C44: =C43+1 -> 33 | D44: , | E44: 32 | F44: , | G44: 22 | H44: , | I44: null | J44: , | K44: null | L44: , | M44: null | N44: , | O44: null | P44: , '{ | Q44: 2 | R44: }', | S44: false | T44: , ' | U44: Острый ринит | V44: ', | W44: 3670 | X44: , | Y44: 3670 | Z44: ), | AA44: =VLOOKUP(G44,'Скрипт activation_condition'!$B$6:$D$495,3,0) -> Насморк | AB44: =VLOOKUP(E44,'Перечень узлов'!$A$1:$B$697,2,0) -> Ринит
B45: ( | C45: =C44+1 -> 34 | D45: , | E45: 33 | F45: , | G45: 23 | H45: , | I45: null | J45: , | K45: null | L45: , | M45: null | N45: , | O45: null | P45: , '{ | Q45: 1 | R45: }', | S45: false | T45: , ' | U45: Чихание | V45: ', | W45: 3671 | X45: , | Y45: 3671 | Z45: ), | AA45: =VLOOKUP(G45,'Скрипт activation_condition'!$B$6:$D$495,3,0) -> Чихание | AB45: =VLOOKUP(E45,'Перечень узлов'!$A$1:$B$697,2,0) -> Чихание
A46: --- | B46: ( | D46: , | E46: null | F46: , | G46: 24 | H46: , | I46: null | J46: , | K46: null | L46: , | M46: null | N46: , | O46: null | P46: , '{ | Q46: 0 | R46: }', | S46: false | T46: , ' | U46: Одышка отсутствует | V46: ', | W46: 3672 | X46: , | Y46: 3672 | Z46: ), | AA46: =VLOOKUP(G46,'Скрипт activation_condition'!$B$6:$D$495,3,0) -> Одышка | AB46: =VLOOKUP(E46,'Перечень узлов'!$A$1:$B$697,2,0) -> #N/A
B47: ( | C47: =C45+1 -> 35 | D47: , | E47: 34 | F47: , | G47: 24 | H47: , | I47: null | J47: , | K47: null | L47: , | M47: null | N47: , | O47: null | P47: , '{ | Q47: 1 | R47: }', | S47: false | T47: , ' | U47: Одышка при физической активности | V47: ', | W47: 3673 | X47: , | Y47: 3673 | Z47: ), | AA47: =VLOOKUP(G47,'Скрипт activation_condition'!$B$6:$D$495,3,0) -> Одышка | AB47: =VLOOKUP(E47,'Перечень узлов'!$A$1:$B$697,2,0) -> Одышка при физической активности
B48: ( | C48: =C47+1 -> 36 | D48: , | E48: 635 | F48: , | G48: 24 | H48: , | I48: null | J48: , | K48: null | L48: , | M48: null | N48: , | O48: null | P48: , '{ | Q48: 2 | R48: }', | S48: false | T48: , ' | U48: Одышка в покое | V48: ', | W48: 3674 | X48: , | Y48: 3674 | Z48: ), | AA48: =VLOOKUP(G48,'Скрипт activation_condition'!$B$6:$D$495,3,0) -> Одышка | AB48: =VLOOKUP(E48,'Перечень узлов'!$A$1:$B$697,2,0) -> Одышка в покое
A49: --- | B49: ( | D49: , | E49: null | F49: , | G49: 25 | H49: , | I49: null | J49: , | K49: null | L49: , | M49: null | N49: , | O49: null | P49: , '{ | Q49: -1 | R49: }', | S49: false | T49: , ' | U49: Пол не определён | V49: ', | W49: 3675 | X49: , | Y49: 3675 | Z49: ), | AA49: =VLOOKUP(G49,'Скрипт activation_condition'!$B$6:$D$495,3,0) -> Пол | AB49: =VLOOKUP(E49,'Перечень узлов'!$A$1:$B$697,2,0) -> #N/A
B50: ( | C50: =C48+1 -> 37 | D50: , | E50: 35 | F50: , | G50: 25 | H50: , | I50: null | J50: , | K50: null | L50: , | M50: null | N50: , | O50: null | P50: , '{ | Q50: 0 | R50: }', | S50: false | T50: , ' | U50: Мужской пол | V50: ', | W50: 3676 | X50: , | Y50: 3676 | Z50: ), | AA50: =VLOOKUP(G50,'Скрипт activation_condition'!$B$6:$D$495,3,0) -> Пол | AB50: =VLOOKUP(E50,'Перечень узлов'!$A$1:$B$697,2,0) -> Мужской пол
B51: ( | C51: =C50+1 -> 38 | D51: , | E51: 36 | F51: , | G51: 25 | H51: , | I51: null | J51: , | K51: null | L51: , | M51: null | N51: , | O51: null | P51: , '{ | Q51: 1 | R51: }', | S51: false | T51: , ' | U51: Женский пол | V51: ', | W51: 3677 | X51: , | Y51: 3677 | Z51: ), | AA51: =VLOOKUP(G51,'Скрипт activation_condition'!$B$6:$D$495,3,0) -> Пол | AB51: =VLOOKUP(E51,'Перечень узлов'!$A$1:$B$697,2,0) -> Женский пол
B52: ( | C52: =C51+1 -> 39 | D52: , | E52: 37 | F52: , | G52: 26 | H52: , | I52: null | J52: , | K52: null | L52: , | M52: null | N52: , | O52: null | P52: , '{ | Q52: 0 | R52: }', | S52: false | T52: , ' | U52: Безработный | V52: ', | W52: 3678 | X52: , | Y52: 3678 | Z52: ), | AA52: =VLOOKUP(G52,'Скрипт activation_condition'!$B$6:$D$495,3,0) -> Наличие работы | AB52: =VLOOKUP(E52,'Перечень узлов'!$A$1:$B$697,2,0) -> Безработный
A53: --- | B53: ( | D53: , | E53: null | F53: , | G53: 26 | H53: , | I53: null | J53: , | K53: null | L53: , | M53: null | N53: , | O53: null | P53: , '{ | Q53: 1 | R53: }', | S53: false | T53: , ' | U53: Работает | V53: ', | W53: 3679 | X53: , | Y53: 3679 | Z53: ), | AA53: =VLOOKUP(G53,'Скрипт activation_condition'!$B$6:$D$495,3,0) -> Наличие работы | AB53: =VLOOKUP(E53,'Перечень узлов'!$A$1:$B$697,2,0) -> #N/A
A54: --- | B54: ( | D54: , | E54: null | F54: , | G54: 26 | H54: , | I54: null | J54: , | K54: null | L54: , | M54: null | N54: , | O54: null | P54: , '{ | Q54: 2 | R54: }', | S54: false | T54: , ' | U54: Учащийся | V54: ', | W54: 3680 | X54: , | Y54: 3680 | Z54: ), | AA54: =VLOOKUP(G54,'Скрипт activation_condition'!$B$6:$D$495,3,0) -> Наличие работы | AB54: =VLOOKUP(E54,'Перечень узлов'!$A$1:$B$697,2,0) -> #N/A
A55: --- | B55: ( | D55: , | E55: null | F55: , | G55: 26 | H55: , | I55: null | J55: , | K55: null | L55: , | M55: null | N55: , | O55: null | P55: , '{ | Q55: 3 | R55: }', | S55: false | T55: , ' | U55: Пенсионер | V55: ', | W55: 3681 | X55: , | Y55: 3681 | Z55: ), | AA55: =VLOOKUP(G55,'Скрипт activation_condition'!$B$6:$D$495,3,0) -> Наличие работы | AB55: =VLOOKUP(E55,'Перечень узлов'!$A$1:$B$697,2,0) -> #N/A
A56: --- | B56: ( | D56: , | E56: null | F56: , | G56: 27 | H56: , | I56: null | J56: , | K56: null | L56: , | M56: null | N56: , | O56: null | P56: , '{ | Q56: 0 | R56: }', | S56: false | T56: , ' | U56: Отсутствие МБТ в мокроте | V56: ', | W56: 3682 | X56: , | Y56: 3682 | Z56: ), | AA56: =VLOOKUP(G56,'Скрипт activation_condition'!$B$6:$D$495,3,0) -> Наличие МБТ в мокроте | AB56: =VLOOKUP(E56,'Перечень узлов'!$A$1:$B$697,2,0) -> #N/A
